// converted by version  [v3.0.5]
// on Mon Feb 14 16:15:20 CST 2022

.package com/josh/vku2f {
	.aid 0xA0:0x0:0x0:0x6:0x47;
	.version 0.1;

	.imports {
		0xA0:0x0:0x0:0x0:0x62:0x0:0x1 1.0;		//java/lang
		0xA0:0x0:0x0:0x0:0x62:0x1:0x2 1.6;		//javacard/security
		0xA0:0x0:0x0:0x0:0x62:0x1:0x1 1.6;		//javacard/framework
		0xA0:0x0:0x0:0x0:0x62:0x2:0x9 1.0;		//javacardx/apdu
		0xA0:0x0:0x0:0x0:0x62:0x2:0x1 1.6;		//javacardx/crypto
	}

	.applet {
		0xA0:0x0:0x0:0x6:0x47:0x2F:0x0:0x1 CTAP2;
	}

	.constantPool {
		// 0
		instanceFieldRef 1.16 AttestationKeyPair/kp;
		// 1
		instanceFieldRef 1.15 AttestationKeyPair/sig;
		// 2
		instanceFieldRef byte[] AttestationKeyPair/x509cert;
		// 3
		instanceFieldRef short AttestationKeyPair/x509len;
		// 4
		instanceFieldRef boolean[] AuthenticatorGetAssertion/options;
		// 5
		instanceFieldRef byte[] AuthenticatorGetAssertion/rpId;
		// 6
		instanceFieldRef byte[] AuthenticatorGetAssertion/clientDataHash;
		// 7
		instanceFieldRef PublicKeyCredentialDescriptor[] AuthenticatorGetAssertion/allow;
		// 8
		instanceFieldRef boolean[] AuthenticatorMakeCredential/options;
		// 9
		instanceFieldRef byte[] AuthenticatorMakeCredential/dataHash;
		// 10
		instanceFieldRef PublicKeyCredentialRpEntity AuthenticatorMakeCredential/rp;
		// 11
		instanceFieldRef PublicKeyCredentialUserEntity AuthenticatorMakeCredential/user;
		// 12
		instanceFieldRef PublicKeyCredentialParams AuthenticatorMakeCredential/params;
		// 13
		instanceFieldRef PublicKeyCredentialDescriptor[] AuthenticatorMakeCredential/exclude;
		// 14
		instanceFieldRef byte[] CBORBase/mBuffer;
		// 15
		instanceFieldRef short[] CBORBase/mStatusWords;
		// 16
		instanceFieldRef byte[] CTAP2/inBuf;
		// 17
		instanceFieldRef byte[] CTAP2/scratch;
		// 18
		instanceFieldRef short[] CTAP2/vars;
		// 19
		instanceFieldRef CBORDecoder CTAP2/cborDecoder;
		// 20
		instanceFieldRef CBOREncoder CTAP2/cborEncoder;
		// 21
		instanceFieldRef CredentialArray CTAP2/discoverableCreds;
		// 22
		instanceFieldRef 1.11 CTAP2/sha;
		// 23
		instanceFieldRef AttestationKeyPair CTAP2/attestation;
		// 24
		instanceFieldRef short[] CTAP2/nextAssertion;
		// 25
		instanceFieldRef boolean CTAP2/persoComplete;
		// 26
		instanceFieldRef boolean[] CTAP2/isChaining;
		// 27
		instanceFieldRef short[] CTAP2/chainRam;
		// 28
		instanceFieldRef short[] CTAP2/outChainRam;
		// 29
		instanceFieldRef boolean[] CTAP2/isOutChaining;
		// 30
		instanceFieldRef 1.16 CTAP2/ecDhKey;
		// 31
		instanceFieldRef boolean[] CTAP2/ecDhSet;
		// 32
		instanceFieldRef StoredCredential CTAP2/tempCred;
		// 33
		instanceFieldRef AuthenticatorMakeCredential CTAP2/cred;
		// 34
		instanceFieldRef PublicKeyCredentialRpEntity StoredCredential/rp;
		// 35
		instanceFieldRef AuthenticatorGetAssertion CTAP2/assertion;
		// 36
		instanceFieldRef StoredCredential[] CTAP2/assertionCreds;
		// 37
		instanceFieldRef byte[] PublicKeyCredentialDescriptor/id;
		// 38
		instanceFieldRef byte[] StoredCredential/id;
		// 39
		instanceFieldRef byte[] CTAP2/info;
		// 40
		instanceFieldRef PublicKeyCredentialUserEntity StoredCredential/user;
		// 41
		instanceFieldRef byte PublicKeyCredentialUserEntity/numData;
		// 42
		instanceFieldRef DomString PublicKeyCredentialUserEntity/displayName;
		// 43
		instanceFieldRef byte[] DomString/str;
		// 44
		instanceFieldRef short DomString/len;
		// 45
		instanceFieldRef byte[] PublicKeyCredentialUserEntity/id;
		// 46
		instanceFieldRef DomString PublicKeyCredentialEntity/name;
		// 47
		instanceFieldRef byte[] PublicKeyCredentialUserEntity/icon;
		// 48
		instanceFieldRef short CredentialArray/count;
		// 49
		instanceFieldRef StoredCredential[] CredentialArray/creds;
		// 50
		instanceFieldRef boolean[] CredentialArray/slotStatus;
		// 51
		instanceFieldRef short CredentialArray/size;
		// 52
		instanceFieldRef short CredentialArray/counter;
		// 53
		instanceFieldRef byte[] PublicKeyCredentialDescriptor/type;
		// 54
		instanceFieldRef DomString PublicKeyCredentialEntity/name;
		// 55
		instanceFieldRef short[] PublicKeyCredentialParams/paramList;
		// 56
		instanceFieldRef short PublicKeyCredentialParams/listIndex;
		// 57
		instanceFieldRef DomString PublicKeyCredentialRpEntity/rpId;
		// 58
		instanceFieldRef boolean[] PublicKeyCredentialUserEntity/dataPresent;
		// 59
		instanceFieldRef byte[] StoredCredential/sigCounter;
		// 60
		instanceFieldRef boolean StoredCredential/initialised;
		// 61
		instanceFieldRef boolean StoredCredential/hmacEnabled;
		// 62
		instanceFieldRef byte[] StoredCredential/credRandom;
		// 63
		instanceFieldRef 1.16 StoredCredential/kp;
		// 64
		instanceFieldRef 1.15 StoredES256Credential/sig;
		// 65
		instanceFieldRef 1.15 StoredPS256Credential/kpSignature;
		// 66
		instanceFieldRef 4.1 StoredRS256Credential/kpSignature;
		// 67
		virtualMethodRef PublicKeyCredentialParams/getAlgorithm()B;
		// 68
		staticMethodRef 1.16.0(BS)V;		// javacard/security/KeyPair.<init>(BS)V
		// 69
		staticMethodRef 0.0.0()V;		// java/lang/Object.<init>()V
		// 70
		staticMethodRef 2.10.5()[B;		// javacard/framework/APDU.getCurrentAPDUBuffer()[B
		// 71
		virtualMethodRef CBORBase/increaseOffset(S)S;
		// 72
		virtualMethodRef CBORBase/getCurrentOffset()S;
		// 73
		virtualMethodRef CBORBase/getBufferLength()S;
		// 74
		staticMethodRef 2.7.1(S)V;		// javacard/framework/ISOException.throwIt(S)V
		// 75
		virtualMethodRef CBORBase/getBuffer()[B;
		// 76
		staticMethodRef CBORBase/<init>()V;
		// 77
		virtualMethodRef CBORBase/getRawByte()B;
		// 78
		virtualMethodRef CBORDecoder/getIntegerSize()B;
		// 79
		virtualMethodRef CBORBase/increaseOffset(S)S;
		// 80
		virtualMethodRef CBORDecoder/readLength()S;
		// 81
		virtualMethodRef CBORBase/getCurrentOffset()S;
		// 82
		virtualMethodRef CBORDecoder/readRawByte()B;
		// 83
		virtualMethodRef CBORBase/getBuffer()[B;
		// 84
		virtualMethodRef CBORBase/getCurrentOffsetAndIncrease(S)S;
		// 85
		staticMethodRef 2.16.4([BS)S;		// javacard/framework/Util.getShort([BS)S
		// 86
		staticMethodRef 2.16.2([BS[BSS)S;		// javacard/framework/Util.arrayCopyNonAtomic([BS[BSS)S
		// 87
		virtualMethodRef CBORDecoder/readInt16()S;
		// 88
		virtualMethodRef CBORDecoder/readRawByteArray([BSS)S;
		// 89
		virtualMethodRef CBORBase/getBufferLength()S;
		// 90
		staticMethodRef ICUtil/isLessThanAsUnsignedShort(SS)Z;
		// 91
		virtualMethodRef CBOREncoder/writeRawByte(B)S;
		// 92
		staticMethodRef CBOREncoder/writeUInt8(BB)S;
		// 93
		staticMethodRef CBOREncoder/writeUInt16(BS)S;
		// 94
		staticMethodRef CBOREncoder/writeRawShort(S)S;
		// 95
		virtualMethodRef CBORBase/getBuffer()[B;
		// 96
		virtualMethodRef CBORBase/getCurrentOffset()S;
		// 97
		virtualMethodRef CBORBase/increaseOffset(S)S;
		// 98
		staticMethodRef 2.16.6([BSS)S;		// javacard/framework/Util.setShort([BSS)S
		// 99
		virtualMethodRef CBORBase/getBufferLength()S;
		// 100
		staticMethodRef CBOREncoder/encodeValue(BS)S;
		// 101
		virtualMethodRef CBORBase/getCurrentOffsetAndIncrease(S)S;
		// 102
		staticMethodRef CBOREncoder/writeRawByteArray([BSS)S;
		// 103
		staticMethodRef 2.3.0()V;		// javacard/framework/Applet.<init>()V
		// 104
		staticMethodRef 2.16.1([BS[BSS)S;		// javacard/framework/Util.arrayCopy([BS[BSS)S
		// 105
		.classRef 1.19;		// javacard/security/ECPublicKey
		// 106
		.classRef 0.2;		// java/lang/Exception
		// 107
		.classRef CBORDecoder;
		// 108
		staticMethodRef CBORDecoder/<init>()V;
		// 109
		staticMethodRef 2.8.15(SB)[S;		// javacard/framework/JCSystem.makeTransientShortArray(SB)[S
		// 110
		.classRef CBOREncoder;
		// 111
		staticMethodRef CBOREncoder/<init>()V;
		// 112
		virtualMethodRef 1.16.3()Ljavacard/security/PublicKey;;		// getPublic()Ljavacard/security/PublicKey;
			.descriptor	Ljavacard/security/PublicKey;	1.3;

		// 113
		.classRef CredentialArray;
		// 114
		staticMethodRef CredentialArray/<init>(S)V;
		// 115
		virtualMethodRef CBORDecoder/readMajorType(B)S;
		// 116
		staticMethodRef 1.11.0(BZ)Ljavacard/security/MessageDigest;;		// javacard/security/MessageDigest.getInstance(BZ)Ljavacard/security/MessageDigest;
			.descriptor	Ljavacard/security/MessageDigest;	1.11;

		// 117
		staticMethodRef 2.8.13(SB)[B;		// javacard/framework/JCSystem.makeTransientByteArray(SB)[B
		// 118
		.classRef AttestationKeyPair;
		// 119
		staticMethodRef AttestationKeyPair/<init>()V;
		// 120
		virtualMethodRef CBORDecoder/readInt8()B;
		// 121
		virtualMethodRef CBORDecoder/readTextString([BS)S;
		// 122
		.classRef 1.17;		// javacard/security/ECKey
		// 123
		staticMethodRef 2.8.12(SB)[Z;		// javacard/framework/JCSystem.makeTransientBooleanArray(SB)[Z
		// 124
		virtualMethodRef CBORDecoder/readByteString([BS)S;
		// 125
		staticMethodRef KeyParams/sec256r1params(Ljavacard/security/ECKey;)V;
			.descriptor	Ljavacard/security/ECKey;	1.17;

		// 126
		.classRef PublicKeyCredentialDescriptor;
		// 127
		virtualMethodRef 1.16.1()V;		// genKeyPair()V
		// 128
		staticMethodRef 1.13.1(BBSZ)Ljavacard/security/Key;;		// javacard/security/KeyBuilder.buildKey(BBSZ)Ljavacard/security/Key;
			.descriptor	Ljavacard/security/Key;	1.0;

		// 129
		.classRef 1.18;		// javacard/security/ECPrivateKey
		// 130
		staticMethodRef 1.16.1(Ljavacard/security/PublicKey;Ljavacard/security/PrivateKey;)V;		// javacard/security/KeyPair.<init>(Ljavacard/security/PublicKey;Ljavacard/security/PrivateKey;)V
			.descriptor	Ljavacard/security/PublicKey;	1.3;
			.descriptor	Ljavacard/security/PrivateKey;	1.2;

		// 131
		staticMethodRef 2.15.2(S)V;		// javacard/framework/UserException.throwIt(S)V
		// 132
		staticFieldRef byte[] Utf8Strings/UTF8_ID;
		// 133
		virtualMethodRef 2.10.1()[B;		// getBuffer()[B
		// 134
		staticMethodRef 2.16.0([BS[BSS)B;		// javacard/framework/Util.arrayCompare([BS[BSS)B
		// 135
		staticMethodRef PublicKeyCredentialDescriptor/<init>([BSS)V;
		// 136
		staticMethodRef CTAP2/doApduIngestion(Ljavacard/framework/APDU;)S;
			.descriptor	Ljavacard/framework/APDU;	2.10;

		// 137
		virtualMethodRef CTAP2/authMakeCredential(Ljavacard/framework/APDU;S)V;
			.descriptor	Ljavacard/framework/APDU;	2.10;

		// 138
		virtualMethodRef CTAP2/authGetAssertion(Ljavacard/framework/APDU;S)V;
			.descriptor	Ljavacard/framework/APDU;	2.10;

		// 139
		virtualMethodRef CTAP2/authGetInfo(Ljavacard/framework/APDU;)V;
			.descriptor	Ljavacard/framework/APDU;	2.10;

		// 140
		staticMethodRef CTAP2/authGetNextAssertion(Ljavacard/framework/APDU;[B)V;
			.descriptor	Ljavacard/framework/APDU;	2.10;

		// 141
		virtualMethodRef CTAP2/attestSignRaw(Ljavacard/framework/APDU;S)V;
			.descriptor	Ljavacard/framework/APDU;	2.10;

		// 142
		virtualMethodRef CTAP2/attestSetCert(Ljavacard/framework/APDU;S)V;
			.descriptor	Ljavacard/framework/APDU;	2.10;

		// 143
		virtualMethodRef CTAP2/persoComplete(Ljavacard/framework/APDU;)V;
			.descriptor	Ljavacard/framework/APDU;	2.10;

		// 144
		virtualMethodRef CTAP2/getAttestPublic(Ljavacard/framework/APDU;)V;
			.descriptor	Ljavacard/framework/APDU;	2.10;

		// 145
		staticMethodRef CTAP2/getCert(Ljavacard/framework/APDU;)V;
			.descriptor	Ljavacard/framework/APDU;	2.10;

		// 146
		virtualMethodRef CTAP2/getCount(Ljavacard/framework/APDU;)V;
			.descriptor	Ljavacard/framework/APDU;	2.10;

		// 147
		staticMethodRef CTAP2/doReset(Ljavacard/framework/APDU;)V;
			.descriptor	Ljavacard/framework/APDU;	2.10;

		// 148
		virtualMethodRef CTAP2/returnError(Ljavacard/framework/APDU;B)V;
			.descriptor	Ljavacard/framework/APDU;	2.10;

		// 149
		virtualMethodRef AttestationKeyPair/isCertSet()Z;
		// 150
		virtualMethodRef AttestationKeyPair/getPubkey([BS)S;
		// 151
		virtualMethodRef 2.10.7()S;		// setOutgoing()S
		// 152
		virtualMethodRef 2.10.9(S)V;		// setOutgoingLength(S)V
		// 153
		virtualMethodRef 2.10.5([BSS)V;		// sendBytesLong([BSS)V
		// 154
		virtualMethodRef CredentialArray/getCount()S;
		// 155
		virtualMethodRef AttestationKeyPair/sign([BSS[BS)S;
		// 156
		virtualMethodRef AttestationKeyPair/setCert([BSS)V;
		// 157
		virtualMethodRef 1.11.1([BSS[BS)S;		// doFinal([BSS[BS)S
		// 158
		.classRef 2.15;		// javacard/framework/UserException
		// 159
		virtualMethodRef CBORBase/init([BSS)V;
		// 160
		.classRef AuthenticatorMakeCredential;
		// 161
		staticMethodRef AuthenticatorMakeCredential/<init>(Lcom/josh/vku2f/CBORDecoder;)V;
		// 162
		virtualMethodRef 2.15.1()S;		// getReason()S
		// 163
		virtualMethodRef CTAP2/returnError(Ljavacard/framework/APDU;S)V;
			.descriptor	Ljavacard/framework/APDU;	2.10;

		// 164
		virtualMethodRef AuthenticatorMakeCredential/getAlgorithm()B;
		// 165
		.classRef StoredES256Credential;
		// 166
		staticMethodRef StoredES256Credential/<init>(Lcom/josh/vku2f/AuthenticatorMakeCredential;)V;
		// 167
		.classRef StoredRS256Credential;
		// 168
		staticMethodRef StoredRS256Credential/<init>(Lcom/josh/vku2f/AuthenticatorMakeCredential;)V;
		// 169
		.classRef StoredPS256Credential;
		// 170
		staticMethodRef StoredPS256Credential/<init>(Lcom/josh/vku2f/AuthenticatorMakeCredential;)V;
		// 171
		virtualMethodRef AuthenticatorMakeCredential/isResident()Z;
		// 172
		virtualMethodRef AuthenticatorMakeCredential/isExclude()Z;
		// 173
		staticMethodRef CTAP2/isPresent([Lcom/josh/vku2f/PublicKeyCredentialDescriptor;)Z;
		// 174
		staticMethodRef CTAP2/addResident(Ljavacard/framework/APDU;Lcom/josh/vku2f/StoredCredential;)V;
			.descriptor	Ljavacard/framework/APDU;	2.10;

		// 175
		virtualMethodRef CBORBase/init([BSS)V;
		// 176
		virtualMethodRef CBOREncoder/startMap(S)S;
		// 177
		staticFieldRef byte[] Utf8Strings/UTF8_PACKED;
		// 178
		virtualMethodRef CBOREncoder/encodeTextString([BSS)S;
		// 179
		virtualMethodRef StoredCredential/getAttestedLen()S;
		// 180
		virtualMethodRef CBOREncoder/startByteString(S)S;
		// 181
		staticFieldRef byte[] Utf8Strings/UTF8_TYPE;
		// 182
		virtualMethodRef PublicKeyCredentialRpEntity/getRp([BS)V;
		// 183
		virtualMethodRef PublicKeyCredentialRpEntity/getRpLen()S;
		// 184
		virtualMethodRef StoredCredential/readCounter([BS)S;
		// 185
		virtualMethodRef StoredCredential/getAttestedData([BS)S;
		// 186
		virtualMethodRef CBOREncoder/encodeNegativeUInt8(B)S;
		// 187
		staticFieldRef byte[] Utf8Strings/UTF8_SIG;
		// 188
		virtualMethodRef AttestationKeyPair/update([BSS)V;
		// 189
		virtualMethodRef CBOREncoder/encodeByteString([BSS)S;
		// 190
		staticFieldRef byte[] Utf8Strings/UTF8_X5C;
		// 191
		virtualMethodRef CBOREncoder/startArray(S)S;
		// 192
		virtualMethodRef CTAP2/sendLongChaining(Ljavacard/framework/APDU;S)V;
			.descriptor	Ljavacard/framework/APDU;	2.10;

		// 193
		.classRef AuthenticatorGetAssertion;
		// 194
		staticMethodRef AuthenticatorGetAssertion/<init>(Lcom/josh/vku2f/CBORDecoder;)V;
		// 195
		staticFieldRef byte[] Utf8Strings/UTF8_UP;
		// 196
		staticMethodRef CTAP2/findCredentials(Ljavacard/framework/APDU;Lcom/josh/vku2f/AuthenticatorGetAssertion;)[Lcom/josh/vku2f/StoredCredential;;
			.descriptor	Ljavacard/framework/APDU;	2.10;

		// 197
		virtualMethodRef CBORDecoder/readBoolean()Z;
		// 198
		virtualMethodRef AuthenticatorGetAssertion/getHash([BS)S;
		// 199
		staticMethodRef CTAP2/doAssertionCommon(Lcom/josh/vku2f/CBOREncoder;S)V;
		// 200
		staticMethodRef CTAP2/generateDH(Ljavacard/framework/APDU;)V;
			.descriptor	Ljavacard/framework/APDU;	2.10;

		// 201
		virtualMethodRef CredentialArray/addCredential(Lcom/josh/vku2f/StoredCredential;)V;
		// 202
		virtualMethodRef CBOREncoder/encodeUInt8(B)S;
		// 203
		virtualMethodRef AuthenticatorGetAssertion/hasAllow()Z;
		// 204
		.classRef StoredCredential;
		// 205
		virtualMethodRef CredentialArray/getLength()S;
		// 206
		virtualMethodRef CredentialArray/getCred(S)Lcom/josh/vku2f/StoredCredential;;
		// 207
		virtualMethodRef PublicKeyCredentialRpEntity/checkId([BSS)Z;
		// 208
		staticFieldRef byte[] Utf8Strings/UTF8_UV;
		// 209
		virtualMethodRef CBORDecoder/skipEntry()S;
		// 210
		staticMethodRef 2.8.18()V;		// javacard/framework/JCSystem.requestObjectDeletion()V
		// 211
		virtualMethodRef StoredCredential/checkId([BSS)Z;
		// 212
		virtualMethodRef 2.10.8(SS)V;		// setOutgoingAndSend(SS)V
		// 213
		staticMethodRef 1.15.0(BZ)Ljavacard/security/Signature;;		// javacard/security/Signature.getInstance(BZ)Ljavacard/security/Signature;
			.descriptor	Ljavacard/security/Signature;	1.15;

		// 214
		staticFieldRef byte[] Utf8Strings/UTF8_FIDO2;
		// 215
		staticFieldRef byte[] CTAP2/aaguid;
		// 216
		virtualMethodRef CBOREncoder/encodeBoolean(Z)S;
		// 217
		virtualMethodRef CBOREncoder/encodeUInt16(S)S;
		// 218
		staticMethodRef 2.8.1()V;		// javacard/framework/JCSystem.beginTransaction()V
		// 219
		staticMethodRef 2.8.2()V;		// javacard/framework/JCSystem.commitTransaction()V
		// 220
		virtualMethodRef StoredCredential/performSignature([BSS[BS)S;
		// 221
		.classRef 1.16;		// javacard/security/KeyPair
		// 222
		.classRef PublicKeyCredentialRpEntity;
		// 223
		virtualMethodRef StoredCredential/getPresentUser()[Z;
		// 224
		staticMethodRef PublicKeyCredentialRpEntity/<init>()V;
		// 225
		virtualMethodRef 1.16.2()Ljavacard/security/PrivateKey;;		// getPrivate()Ljavacard/security/PrivateKey;
			.descriptor	Ljavacard/security/PrivateKey;	1.2;

		// 226
		virtualMethodRef PublicKeyCredentialRpEntity/setRp([BS)V;
		// 227
		staticFieldRef byte[] Utf8Strings/UTF8_NAME;
		// 228
		virtualMethodRef PublicKeyCredentialEntity/setName([BS)V;
		// 229
		.classRef PublicKeyCredentialUserEntity;
		// 230
		virtualMethodRef 2.10.6()S;		// setIncomingAndReceive()S
		// 231
		virtualMethodRef 2.10.15()S;		// getIncomingLength()S
		// 232
		staticMethodRef CTAP2/isCommandChainingCLA(Ljavacard/framework/APDU;)Z;
			.descriptor	Ljavacard/framework/APDU;	2.10;

		// 233
		virtualMethodRef 2.10.16()S;		// getOffsetCdata()S
		// 234
		virtualMethodRef 2.10.11()B;		// getCurrentState()B
		// 235
		virtualMethodRef 2.10.3(S)S;		// receiveBytes(S)S
		// 236
		virtualMethodRef AttestationKeyPair/getCert([BS)S;
		// 237
		virtualMethodRef 2.3.3()Z;		// selectingApplet()Z
		// 238
		virtualMethodRef 2.10.12()Z;		// isCommandChainingCLA()Z
		// 239
		virtualMethodRef 2.10.14()Z;		// isISOInterindustryCLA()Z
		// 240
		virtualMethodRef CTAP2/isChaining()Z;
		// 241
		virtualMethodRef CTAP2/getData(Ljavacard/framework/APDU;)V;
			.descriptor	Ljavacard/framework/APDU;	2.10;

		// 242
		virtualMethodRef CTAP2/handle(Ljavacard/framework/APDU;)V;
			.descriptor	Ljavacard/framework/APDU;	2.10;

		// 243
		.classRef CTAP2;
		// 244
		staticMethodRef CTAP2/<init>()V;
		// 245
		virtualMethodRef 2.3.2([BSB)V;		// register([BSB)V
		// 246
		virtualMethodRef 2.3.1()V;		// register()V
		// 247
		staticMethodRef 2.4.0(S)V;		// javacard/framework/CardException.<init>(S)V
		// 248
		staticFieldRef CTAP2Exception CTAP2Exception/systemInstance;
		// 249
		virtualMethodRef 2.4.2(S)V;		// setReason(S)V
		// 250
		staticMethodRef PublicKeyCredentialUserEntity/<init>()V;
		// 251
		virtualMethodRef 1.15.3(Ljavacard/security/Key;B)V;		// init(Ljavacard/security/Key;B)V
			.descriptor	Ljavacard/security/Key;	1.0;

		// 252
		virtualMethodRef PublicKeyCredentialUserEntity/setId([BSS)V;
		// 253
		virtualMethodRef PublicKeyCredentialUserEntity/setName([BS)V;
		// 254
		virtualMethodRef CredentialArray/alreadyExists(Lcom/josh/vku2f/StoredCredential;)S;
		// 255
		staticFieldRef byte[] Utf8Strings/UTF8_DISPLAYNAME;
		// 256
		virtualMethodRef PublicKeyCredentialUserEntity/checkId([BSS)Z;
		// 257
		virtualMethodRef PublicKeyCredentialRpEntity/checkId(Lcom/josh/vku2f/PublicKeyCredentialRpEntity;)Z;
		// 258
		virtualMethodRef PublicKeyCredentialUserEntity/checkId(Lcom/josh/vku2f/PublicKeyCredentialUserEntity;)Z;
		// 259
		virtualMethodRef DomString/checkEquals([BSS)Z;
		// 260
		staticFieldRef byte[] KeyParams/secp256r1p;
		// 261
		staticFieldRef byte[] KeyParams/secp256r1A;
		// 262
		staticFieldRef byte[] KeyParams/secp256r1B;
		// 263
		staticFieldRef byte[] KeyParams/secp256r1G;
		// 264
		staticFieldRef byte[] KeyParams/secp256r1R;
		// 265
		virtualMethodRef PublicKeyCredentialUserEntity/setDisplayName([BS)V;
		// 266
		.classRef DomString;
		// 267
		staticMethodRef DomString/<init>([BS)V;
		// 268
		staticFieldRef byte[] Utf8Strings/UTF8_ICON;
		// 269
		virtualMethodRef PublicKeyCredentialUserEntity/setIcon([BS)V;
		// 270
		.classRef PublicKeyCredentialParams;
		// 271
		staticMethodRef PublicKeyCredentialEntity/<init>()V;
		// 272
		staticMethodRef PublicKeyCredentialParams/<init>(S)V;
		// 273
		virtualMethodRef DomString/checkEquals(Lcom/josh/vku2f/DomString;)Z;
		// 274
		virtualMethodRef 1.15.5([BSS[BS)S;		// sign([BSS[BS)S
		// 275
		.classRef 0.5;		// java/lang/ArrayIndexOutOfBoundsException
		// 276
		staticFieldRef 1.14 ServerKeyCrypto/rng;
		// 277
		staticMethodRef 1.14.0(B)Ljavacard/security/RandomData;;		// javacard/security/RandomData.getInstance(B)Ljavacard/security/RandomData;
			.descriptor	Ljavacard/security/RandomData;	1.14;

		// 278
		staticFieldRef 1.14 StoredCredential/rng;
		// 279
		staticMethodRef ServerKeyCrypto/getRng()Ljavacard/security/RandomData;;
			.descriptor	Ljavacard/security/RandomData;	1.14;

		// 280
		virtualMethodRef 1.14.1([BSS)V;		// generateData([BSS)V
		// 281
		staticFieldRef byte[] Utf8Strings/UTF8_ALG;
		// 282
		virtualMethodRef CBORDecoder/getMajorType()B;
		// 283
		virtualMethodRef CBORDecoder/readEncodedInteger([BS)S;
		// 284
		virtualMethodRef PublicKeyCredentialParams/addAlgorithm(S)V;
		// 285
		staticMethodRef 2.16.3([BSSB)S;		// javacard/framework/Util.arrayFillNonAtomic([BSSB)S
		// 286
		staticMethodRef StoredCredential/<init>()V;
		// 287
		staticMethodRef 2.16.5(BB)S;		// javacard/framework/Util.makeShort(BB)S
		// 288
		virtualMethodRef AuthenticatorMakeCredential/getUser()Lcom/josh/vku2f/PublicKeyCredentialUserEntity;;
		// 289
		virtualMethodRef AuthenticatorMakeCredential/getRp()Lcom/josh/vku2f/PublicKeyCredentialRpEntity;;
		// 290
		staticFieldRef byte[] Utf8Strings/UTF8_PUBLIC_KEY;
		// 291
		virtualMethodRef StoredCredential/incrementCounter()V;
		// 292
		virtualMethodRef StoredCredential/doAttestationCommon([BS)V;
		// 293
		virtualMethodRef 1.15.6([BSS)V;		// update([BSS)V
		// 294
		virtualMethodRef StoredCredential/incrementCounter()V;
		// 295
		virtualMethodRef StoredCredential/doAttestationCommon([BS)V;
		// 296
		.classRef 1.9;		// javacard/security/RSAPublicKey
		// 297
		staticMethodRef 4.1.0(BZ)Ljavacardx/crypto/Cipher;;		// javacardx/crypto/Cipher.getInstance(BZ)Ljavacardx/crypto/Cipher;
			.descriptor	Ljavacardx/crypto/Cipher;	4.1;

		// 298
		staticFieldRef byte[] Utf8Strings/UTF8_RK;
		// 299
		virtualMethodRef 4.1.3(Ljavacard/security/Key;B)V;		// init(Ljavacard/security/Key;B)V
			.descriptor	Ljavacard/security/Key;	1.0;

		// 300
		virtualMethodRef StoredCredential/incrementCounter()V;
		// 301
		virtualMethodRef 4.1.1([BSS[BS)S;		// doFinal([BSS[BS)S
		// 302
		virtualMethodRef StoredCredential/doAttestationCommon([BS)V;
		// 303
		virtualMethodRef CBOREncoder/encodeNegativeUInt16(S)S;
	}

	.class public AttestationKeyPair 0 extends 0.0 {		// extends java/lang/Object

		.fields {
			public short x509len 0;		// S
			public byte[] x509cert 1;		// [B
			private 1.16 kp 2;		// Ljavacard/security/KeyPair;
			private 1.15 sig 3;		// Ljavacard/security/Signature;
		}

		.publicMethodTable 1 {
			equals(Ljava/lang/Object;)Z;
			sign([BSS[BS)S;
			update([BSS)V;
			setCert([BSS)V;
			getCert([BS)S;
			isCertSet()Z;
			getPubkey([BS)S;
		}

		.packageMethodTable 0 {
		}

		.method public <init>()V 0 {
			.stack 5;
			.locals 0;

				L0:	aload_0;
					invokespecial 69;		// java/lang/Object.<init>()V
					aload_0;
					new 221;		// javacard/security/KeyPair
					dup;
					sconst_5;
					sspush 256;
					invokespecial 68;		// javacard/security/KeyPair.<init>(BS)V
					putfield_a 0;		// reference com/josh/vku2f/AttestationKeyPair.kp
					getfield_a_this 0;		// reference com/josh/vku2f/AttestationKeyPair.kp
					invokevirtual 112;		// getPublic()Ljavacard/security/PublicKey;
					checkcast 0 122;		// T_CLASSORINTERFACE javacard/security/ECKey
					invokestatic 125;		// com/josh/vku2f/KeyParams.sec256r1params(Ljavacard/security/ECKey;)V
					getfield_a_this 0;		// reference com/josh/vku2f/AttestationKeyPair.kp
					invokevirtual 127;		// genKeyPair()V
					aload_0;
					bspush 33;
					sconst_0;
					invokestatic 213;		// javacard/security/Signature.getInstance(BZ)Ljavacard/security/Signature;
					putfield_a 1;		// reference com/josh/vku2f/AttestationKeyPair.sig
					getfield_a_this 1;		// reference com/josh/vku2f/AttestationKeyPair.sig
					getfield_a_this 0;		// reference com/josh/vku2f/AttestationKeyPair.kp
					invokevirtual 225;		// getPrivate()Ljavacard/security/PrivateKey;
					sconst_1;
					invokevirtual 251;		// init(Ljavacard/security/Key;B)V
					return;
		}

		.method public sign([BSS[BS)S 1 {
			.stack 6;
			.locals 0;

				L0:	getfield_a_this 1;		// reference com/josh/vku2f/AttestationKeyPair.sig
					aload_1;
					sload_2;
					sload_3;
					aload 4;
					sload 5;
					invokevirtual 274;		// sign([BSS[BS)S
					sreturn;
		}

		.method public update([BSS)V 2 {
			.stack 4;
			.locals 0;

				L0:	getfield_a_this 1;		// reference com/josh/vku2f/AttestationKeyPair.sig
					aload_1;
					sload_2;
					sload_3;
					invokevirtual 293;		// update([BSS)V
					return;
		}

		.method public setCert([BSS)V 3 {
			.stack 5;
			.locals 0;

				L0:	aload_0;
					sload_3;
					newarray 11;
					putfield_a 2;		// reference com/josh/vku2f/AttestationKeyPair.x509cert
					sload_3;
					putfield_s_this 3;		// short com/josh/vku2f/AttestationKeyPair.x509len
					aload_1;
					sload_2;
					getfield_a_this 2;		// reference com/josh/vku2f/AttestationKeyPair.x509cert
					sconst_0;
					sload_3;
					invokestatic 104;		// javacard/framework/Util.arrayCopy([BS[BSS)S
					pop;
					return;
		}

		.method public getCert([BS)S 4 {
			.stack 5;
			.locals 0;

				L0:	getfield_a_this 2;		// reference com/josh/vku2f/AttestationKeyPair.x509cert
					sconst_0;
					aload_1;
					sload_2;
					getfield_a_this 2;		// reference com/josh/vku2f/AttestationKeyPair.x509cert
					arraylength;
					invokestatic 104;		// javacard/framework/Util.arrayCopy([BS[BSS)S
					pop;
					getfield_a_this 2;		// reference com/josh/vku2f/AttestationKeyPair.x509cert
					arraylength;
					sreturn;
		}

		.method public isCertSet()Z 5 {
			.stack 1;
			.locals 0;

				L0:	getfield_s_this 3;		// short com/josh/vku2f/AttestationKeyPair.x509len
					ifeq L2;
				L1:	sconst_1;
					goto L3;
				L2:	sconst_0;
				L3:	sreturn;
		}

		.method public getPubkey([BS)S 6 {
			.stack 3;
			.locals 0;

				L0:	getfield_a_this 0;		// reference com/josh/vku2f/AttestationKeyPair.kp
					invokevirtual 112;		// getPublic()Ljavacard/security/PublicKey;
					checkcast 0 105;		// T_CLASSORINTERFACE javacard/security/ECPublicKey
					aload_1;
					sload_2;
					invokeinterface 3 105 19;		// javacard/security/ECPublicKey
					sreturn;
		}

	}

	.class public AuthenticatorGetAssertion 1 extends 0.0 {		// extends java/lang/Object

		.fields {
			public byte[] rpId 0;		// [B
			 byte[] clientDataHash 1;		// [B
			 boolean[] options 2;		// [Z
			 PublicKeyCredentialDescriptor[] allow 3;		// [Lcom/josh/vku2f/PublicKeyCredentialDescriptor;
		}

		.publicMethodTable 1 {
			equals(Ljava/lang/Object;)Z;
			getHash([BS)S;
			hasAllow()Z;
		}

		.packageMethodTable 0 {
		}

		.method public <init>(Lcom/josh/vku2f/CBORDecoder;)V 0 {
			.stack 8;
			.locals 3;

				L0:	aload_0;
					invokespecial 69;		// java/lang/Object.<init>()V
				L1:	bspush 8;
					sconst_1;
					invokestatic 109;		// javacard/framework/JCSystem.makeTransientShortArray(SB)[S
					astore_2;
				L2:	goto L4;
				L3:	astore_3;
					bspush 8;
					newarray 12;
					astore_2;
				L4:	aload_0;
					sconst_2;
					newarray 10;
					putfield_a 4;		// reference com/josh/vku2f/AuthenticatorGetAssertion.options
					getfield_a_this 4;		// reference com/josh/vku2f/AuthenticatorGetAssertion.options
					sconst_0;
					sconst_1;
					bastore;
					getfield_a_this 4;		// reference com/josh/vku2f/AuthenticatorGetAssertion.options
					sconst_1;
					sconst_0;
					bastore;
					aload_2;
					sconst_0;
					aload_1;
					sconst_5;
					invokevirtual 115;		// readMajorType(B)S
					sastore;
				L5:	bspush 64;
					sconst_1;
					invokestatic 117;		// javacard/framework/JCSystem.makeTransientByteArray(SB)[B
					astore_3;
				L6:	goto L8;
				L7:	astore 4;
					bspush 64;
					newarray 11;
					astore_3;
				L8:	aload_2;
					sconst_1;
					sconst_0;
					sastore;
				L9:	aload_2;
					sconst_1;
					saload;
					aload_2;
					sconst_0;
					saload;
					if_scmpge_w L39;
				L10:	aload_2;
					sconst_2;
					aload_1;
					invokevirtual 120;		// readInt8()B
					sastore;
					aload_2;
					sconst_2;
					saload;
					stableswitch L37 1 7 L11 L12 L13 L34 L26 L35 L36;
				L11:	aload_2;
					sconst_3;
					aload_1;
					aload_3;
					sconst_0;
					invokevirtual 121;		// readTextString([BS)S
					sastore;
					aload_0;
					aload_2;
					sconst_3;
					saload;
					newarray 11;
					putfield_a 5;		// reference com/josh/vku2f/AuthenticatorGetAssertion.rpId
					aload_3;
					sconst_0;
					getfield_a_this 5;		// reference com/josh/vku2f/AuthenticatorGetAssertion.rpId
					sconst_0;
					aload_2;
					sconst_3;
					saload;
					invokestatic 104;		// javacard/framework/Util.arrayCopy([BS[BSS)S
					pop;
					goto_w L38;
				L12:	aload_2;
					sconst_3;
					aload_1;
					aload_3;
					sconst_0;
					invokevirtual 124;		// readByteString([BS)S
					sastore;
					aload_0;
					aload_2;
					sconst_3;
					saload;
					newarray 11;
					putfield_a 6;		// reference com/josh/vku2f/AuthenticatorGetAssertion.clientDataHash
					aload_3;
					sconst_0;
					getfield_a_this 6;		// reference com/josh/vku2f/AuthenticatorGetAssertion.clientDataHash
					sconst_0;
					aload_2;
					sconst_3;
					saload;
					invokestatic 104;		// javacard/framework/Util.arrayCopy([BS[BSS)S
					pop;
					goto_w L38;
				L13:	aload_2;
					sconst_3;
					aload_1;
					sconst_4;
					invokevirtual 115;		// readMajorType(B)S
					sastore;
					aload_0;
					aload_2;
					sconst_3;
					saload;
					anewarray 126;		// com/josh/vku2f/PublicKeyCredentialDescriptor
					putfield_a 7;		// reference com/josh/vku2f/AuthenticatorGetAssertion.allow
					aload_2;
					sconst_4;
					sconst_0;
					sastore;
				L14:	aload_2;
					sconst_4;
					saload;
					getfield_a_this 7;		// reference com/josh/vku2f/AuthenticatorGetAssertion.allow
					arraylength;
					if_scmpge_w L38;
				L15:	aload_2;
					sconst_3;
					aload_1;
					sconst_5;
					invokevirtual 115;		// readMajorType(B)S
					sastore;
					aload_2;
					sconst_3;
					saload;
					sconst_2;
					if_scmpeq L17;
				L16:	bspush 18;
					invokestatic 131;		// javacard/framework/UserException.throwIt(S)V
					goto_w L38;
				L17:	aload_2;
					sconst_5;
					sconst_0;
					sastore;
				L18:	aload_2;
					sconst_5;
					saload;
					sconst_2;
					if_scmpge L25;
				L19:	aload_2;
					sconst_3;
					aload_1;
					aload_3;
					sconst_0;
					invokevirtual 121;		// readTextString([BS)S
					sastore;
					aload_3;
					sconst_0;
					getstatic_a 132;		// reference com/josh/vku2f/Utf8Strings.UTF8_ID
					sconst_0;
					sconst_2;
					invokestatic 134;		// javacard/framework/Util.arrayCompare([BS[BSS)B
					ifne L21;
				L20:	aload_2;
					sconst_3;
					aload_1;
					aload_3;
					sconst_0;
					invokevirtual 124;		// readByteString([BS)S
					sastore;
					getfield_a_this 7;		// reference com/josh/vku2f/AuthenticatorGetAssertion.allow
					aload_2;
					sconst_4;
					saload;
					new 126;		// com/josh/vku2f/PublicKeyCredentialDescriptor
					dup;
					aload_3;
					sconst_0;
					aload_2;
					sconst_3;
					saload;
					invokespecial 135;		// com/josh/vku2f/PublicKeyCredentialDescriptor.<init>([BSS)V
					aastore;
					goto L24;
				L21:	aload_3;
					sconst_0;
					getstatic_a 181;		// reference com/josh/vku2f/Utf8Strings.UTF8_TYPE
					sconst_0;
					sconst_4;
					invokestatic 134;		// javacard/framework/Util.arrayCompare([BS[BSS)B
					ifne L23;
				L22:	aload_1;
					aload_3;
					sconst_0;
					invokevirtual 121;		// readTextString([BS)S
					pop;
					goto L24;
				L23:	bspush 18;
					invokestatic 131;		// javacard/framework/UserException.throwIt(S)V
					goto L25;
				L24:	aload_2;
					sconst_5;
					dup2;
					saload;
					sconst_1;
					sadd;
					sastore;
					goto L18;
				L25:	aload_2;
					sconst_4;
					dup2;
					saload;
					sconst_1;
					sadd;
					sastore;
					goto_w L14;
				L26:	aload_2;
					sconst_3;
					aload_1;
					sconst_5;
					invokevirtual 115;		// readMajorType(B)S
					sastore;
					aload_2;
					sconst_4;
					sconst_0;
					sastore;
				L27:	aload_2;
					sconst_4;
					saload;
					aload_2;
					sconst_3;
					saload;
					if_scmpge L38;
				L28:	aload_1;
					aload_3;
					sconst_0;
					invokevirtual 121;		// readTextString([BS)S
					pop;
					aload_3;
					sconst_0;
					getstatic_a 195;		// reference com/josh/vku2f/Utf8Strings.UTF8_UP
					sconst_0;
					sconst_2;
					invokestatic 134;		// javacard/framework/Util.arrayCompare([BS[BSS)B
					ifne L30;
				L29:	getfield_a_this 4;		// reference com/josh/vku2f/AuthenticatorGetAssertion.options
					sconst_0;
					aload_1;
					invokevirtual 197;		// readBoolean()Z
					bastore;
					goto L33;
				L30:	aload_3;
					sconst_0;
					getstatic_a 208;		// reference com/josh/vku2f/Utf8Strings.UTF8_UV
					sconst_0;
					sconst_2;
					invokestatic 134;		// javacard/framework/Util.arrayCompare([BS[BSS)B
					ifne L32;
				L31:	getfield_a_this 4;		// reference com/josh/vku2f/AuthenticatorGetAssertion.options
					sconst_1;
					aload_1;
					invokevirtual 197;		// readBoolean()Z
					bastore;
					goto L33;
				L32:	aload_1;
					invokevirtual 209;		// skipEntry()S
					pop;
				L33:	aload_2;
					sconst_4;
					dup2;
					saload;
					sconst_1;
					sadd;
					sastore;
					goto L27;
				L34:	aload_1;
					invokevirtual 209;		// skipEntry()S
					pop;
					goto L38;
				L35:	aload_1;
					invokevirtual 209;		// skipEntry()S
					pop;
					goto L38;
				L36:	aload_1;
					invokevirtual 209;		// skipEntry()S
					pop;
					goto L38;
				L37:	bspush -123;
					invokestatic 131;		// javacard/framework/UserException.throwIt(S)V
				L38:	aload_2;
					sconst_1;
					dup2;
					saload;
					sconst_1;
					sadd;
					sastore;
					goto_w L9;
				L39:	getfield_a_this 5;		// reference com/josh/vku2f/AuthenticatorGetAssertion.rpId
					ifnull L41;
				L40:	getfield_a_this 6;		// reference com/josh/vku2f/AuthenticatorGetAssertion.clientDataHash
					ifnonnull L42;
				L41:	bspush 20;
					invokestatic 131;		// javacard/framework/UserException.throwIt(S)V
				L42:	return;
			.exceptionTable {
				// start_block end_block handler_block catch_type_index
				L1 L2 L3 106;
				L5 L6 L7 106;
			}
		}

		.method public getHash([BS)S 1 {
			.stack 5;
			.locals 0;

				L0:	getfield_a_this 6;		// reference com/josh/vku2f/AuthenticatorGetAssertion.clientDataHash
					sconst_0;
					aload_1;
					sload_2;
					getfield_a_this 6;		// reference com/josh/vku2f/AuthenticatorGetAssertion.clientDataHash
					arraylength;
					invokestatic 104;		// javacard/framework/Util.arrayCopy([BS[BSS)S
					pop;
					getfield_a_this 6;		// reference com/josh/vku2f/AuthenticatorGetAssertion.clientDataHash
					arraylength;
					sreturn;
		}

		.method public hasAllow()Z 2 {
			.stack 1;
			.locals 0;

				L0:	getfield_a_this 7;		// reference com/josh/vku2f/AuthenticatorGetAssertion.allow
					ifnull L3;
				L1:	getfield_a_this 7;		// reference com/josh/vku2f/AuthenticatorGetAssertion.allow
					arraylength;
					ifle L3;
				L2:	sconst_1;
					goto L4;
				L3:	sconst_0;
				L4:	sreturn;
		}

	}

	.class public AuthenticatorMakeCredential 2 extends 0.0 {		// extends java/lang/Object

		.fields {
			public byte[] dataHash 0;		// [B
			public PublicKeyCredentialDescriptor[] exclude 1;		// [Lcom/josh/vku2f/PublicKeyCredentialDescriptor;
			private PublicKeyCredentialRpEntity rp 2;		// Lcom/josh/vku2f/PublicKeyCredentialRpEntity;
			private PublicKeyCredentialUserEntity user 3;		// Lcom/josh/vku2f/PublicKeyCredentialUserEntity;
			private PublicKeyCredentialParams params 4;		// Lcom/josh/vku2f/PublicKeyCredentialParams;
			private boolean[] options 5;		// [Z
		}

		.publicMethodTable 1 {
			equals(Ljava/lang/Object;)Z;
			getUser()Lcom/josh/vku2f/PublicKeyCredentialUserEntity;;
			getRp()Lcom/josh/vku2f/PublicKeyCredentialRpEntity;;
			isResident()Z;
			getAlgorithm()B;
			isExclude()Z;
			getDataHash([BS)S;
		}

		.packageMethodTable 0 {
		}

		.method public <init>(Lcom/josh/vku2f/CBORDecoder;)V 0 {
			.stack 7;
			.locals 10;

				L0:	aload_0;
					invokespecial 69;		// java/lang/Object.<init>()V
					aload_0;
					sconst_2;
					newarray 10;
					putfield_a 8;		// reference com/josh/vku2f/AuthenticatorMakeCredential.options
				L1:	bspush 8;
					sconst_1;
					invokestatic 109;		// javacard/framework/JCSystem.makeTransientShortArray(SB)[S
					astore_2;
				L2:	goto L4;
				L3:	astore_3;
					bspush 8;
					newarray 12;
					astore_2;
				L4:	bspush 64;
					sconst_2;
					invokestatic 117;		// javacard/framework/JCSystem.makeTransientByteArray(SB)[B
					astore_3;
				L5:	goto L7;
				L6:	astore 4;
					bspush 64;
					newarray 11;
					astore_3;
				L7:	bspush 64;
					sconst_2;
					invokestatic 117;		// javacard/framework/JCSystem.makeTransientByteArray(SB)[B
					astore 4;
				L8:	goto L10;
				L9:	astore 5;
					bspush 64;
					newarray 11;
					astore 4;
				L10:	aload_1;
					sconst_5;
					invokevirtual 115;		// readMajorType(B)S
					sstore 5;
					getfield_a_this 8;		// reference com/josh/vku2f/AuthenticatorMakeCredential.options
					sconst_0;
					sconst_1;
					bastore;
					getfield_a_this 8;		// reference com/josh/vku2f/AuthenticatorMakeCredential.options
					sconst_1;
					sconst_0;
					bastore;
					sconst_0;
					sstore 6;
				L11:	sload 6;
					sload 5;
					if_scmpge_w L93;
				L12:	aload_1;
					invokevirtual 120;		// readInt8()B
					sstore 7;
					sload 7;
					stableswitch L91 1 7 L13 L14 L24 L37 L61 L88 L75;
				L13:	aload_1;
					aload_3;
					sconst_0;
					invokevirtual 124;		// readByteString([BS)S
					sstore 8;
					aload_0;
					sload 8;
					newarray 11;
					putfield_a 9;		// reference com/josh/vku2f/AuthenticatorMakeCredential.dataHash
					aload_3;
					sconst_0;
					getfield_a_this 9;		// reference com/josh/vku2f/AuthenticatorMakeCredential.dataHash
					sconst_0;
					sload 8;
					invokestatic 104;		// javacard/framework/Util.arrayCopy([BS[BSS)S
					pop;
					goto_w L92;
				L14:	aload_0;
					new 222;		// com/josh/vku2f/PublicKeyCredentialRpEntity
					dup;
					invokespecial 224;		// com/josh/vku2f/PublicKeyCredentialRpEntity.<init>()V
					putfield_a 10;		// reference com/josh/vku2f/AuthenticatorMakeCredential.rp
					aload_1;
					sconst_5;
					invokevirtual 115;		// readMajorType(B)S
					sstore 8;
					sload 8;
					sconst_2;
					if_scmpge L16;
				L15:	bspush 18;
					invokestatic 131;		// javacard/framework/UserException.throwIt(S)V
				L16:	sconst_0;
					sstore 9;
				L17:	sload 9;
					sload 8;
					if_scmpge L23;
				L18:	aload_1;
					aload_3;
					sconst_0;
					invokevirtual 121;		// readTextString([BS)S
					pop;
					aload_3;
					sconst_0;
					getstatic_a 132;		// reference com/josh/vku2f/Utf8Strings.UTF8_ID
					sconst_0;
					sconst_2;
					invokestatic 134;		// javacard/framework/Util.arrayCompare([BS[BSS)B
					ifne L20;
				L19:	aload_1;
					aload_3;
					sconst_0;
					invokevirtual 121;		// readTextString([BS)S
					sstore 10;
					getfield_a_this 10;		// reference com/josh/vku2f/AuthenticatorMakeCredential.rp
					aload_3;
					sload 10;
					invokevirtual 226;		// setRp([BS)V
					goto L22;
				L20:	aload_3;
					sconst_0;
					getstatic_a 227;		// reference com/josh/vku2f/Utf8Strings.UTF8_NAME
					sconst_0;
					sconst_4;
					invokestatic 134;		// javacard/framework/Util.arrayCompare([BS[BSS)B
					ifne L22;
				L21:	aload_1;
					aload_3;
					sconst_0;
					invokevirtual 121;		// readTextString([BS)S
					sstore 10;
					getfield_a_this 10;		// reference com/josh/vku2f/AuthenticatorMakeCredential.rp
					aload_3;
					sload 10;
					invokevirtual 228;		// setName([BS)V
				L22:	sinc 9 1;
					goto L17;
				L23:	goto_w L92;
				L24:	aload_0;
					new 229;		// com/josh/vku2f/PublicKeyCredentialUserEntity
					dup;
					invokespecial 250;		// com/josh/vku2f/PublicKeyCredentialUserEntity.<init>()V
					putfield_a 11;		// reference com/josh/vku2f/AuthenticatorMakeCredential.user
					aload_1;
					sconst_5;
					invokevirtual 115;		// readMajorType(B)S
					sstore 8;
					sconst_0;
					sstore 9;
				L25:	sload 9;
					sload 8;
					if_scmpge_w L36;
				L26:	aload_1;
					aload_3;
					sconst_0;
					invokevirtual 121;		// readTextString([BS)S
					pop;
					aload_3;
					sconst_0;
					getstatic_a 132;		// reference com/josh/vku2f/Utf8Strings.UTF8_ID
					sconst_0;
					sconst_2;
					invokestatic 134;		// javacard/framework/Util.arrayCompare([BS[BSS)B
					ifne L28;
				L27:	aload_1;
					aload_3;
					sconst_0;
					invokevirtual 124;		// readByteString([BS)S
					sstore 10;
					getfield_a_this 11;		// reference com/josh/vku2f/AuthenticatorMakeCredential.user
					aload_3;
					sconst_0;
					sload 10;
					invokevirtual 252;		// setId([BSS)V
					goto L35;
				L28:	aload_3;
					sconst_0;
					getstatic_a 227;		// reference com/josh/vku2f/Utf8Strings.UTF8_NAME
					sconst_0;
					sconst_4;
					invokestatic 134;		// javacard/framework/Util.arrayCompare([BS[BSS)B
					ifne L30;
				L29:	aload_1;
					aload_3;
					sconst_0;
					invokevirtual 121;		// readTextString([BS)S
					sstore 10;
					getfield_a_this 11;		// reference com/josh/vku2f/AuthenticatorMakeCredential.user
					aload_3;
					sload 10;
					invokevirtual 253;		// setName([BS)V
					goto L35;
				L30:	aload_3;
					sconst_0;
					getstatic_a 255;		// reference com/josh/vku2f/Utf8Strings.UTF8_DISPLAYNAME
					sconst_0;
					bspush 11;
					invokestatic 134;		// javacard/framework/Util.arrayCompare([BS[BSS)B
					ifne L32;
				L31:	aload_1;
					aload_3;
					sconst_0;
					invokevirtual 121;		// readTextString([BS)S
					sstore 10;
					getfield_a_this 11;		// reference com/josh/vku2f/AuthenticatorMakeCredential.user
					aload_3;
					sload 10;
					invokevirtual 265;		// setDisplayName([BS)V
					goto L35;
				L32:	aload_3;
					sconst_0;
					getstatic_a 268;		// reference com/josh/vku2f/Utf8Strings.UTF8_ICON
					sconst_0;
					sconst_4;
					invokestatic 134;		// javacard/framework/Util.arrayCompare([BS[BSS)B
					ifne L34;
				L33:	aload_1;
					aload 4;
					sconst_0;
					invokevirtual 121;		// readTextString([BS)S
					sstore 10;
					getfield_a_this 11;		// reference com/josh/vku2f/AuthenticatorMakeCredential.user
					aload 4;
					sload 10;
					invokevirtual 269;		// setIcon([BS)V
					goto L35;
				L34:	aload_1;
					invokevirtual 209;		// skipEntry()S
					pop;
				L35:	sinc 9 1;
					goto_w L25;
				L36:	goto_w L92;
				L37:	aload_1;
					sconst_4;
					invokevirtual 115;		// readMajorType(B)S
					sstore 8;
					aload_0;
					new 270;		// com/josh/vku2f/PublicKeyCredentialParams
					dup;
					sload 8;
					invokespecial 272;		// com/josh/vku2f/PublicKeyCredentialParams.<init>(S)V
					putfield_a 12;		// reference com/josh/vku2f/AuthenticatorMakeCredential.params
					sconst_0;
					sstore 9;
				L38:	sload 9;
					sload 8;
					if_scmpge_w L60;
				L39:	aload_1;
					sconst_5;
					invokevirtual 115;		// readMajorType(B)S
					sstore 10;
					sload 10;
					sconst_2;
					if_scmpeq L41;
				L40:	bspush 18;
					invokestatic 131;		// javacard/framework/UserException.throwIt(S)V
				L41:	sconst_0;
					sstore 11;
				L42:	sload 11;
					sconst_2;
					if_scmpge_w L59;
				L43:	aload_1;
					aload_3;
					sconst_0;
					invokevirtual 121;		// readTextString([BS)S
					pop;
					aload_3;
					sconst_0;
					getstatic_a 281;		// reference com/josh/vku2f/Utf8Strings.UTF8_ALG
					sconst_0;
					sconst_3;
					invokestatic 134;		// javacard/framework/Util.arrayCompare([BS[BSS)B
					ifne L54;
				L44:	aload_1;
					invokevirtual 282;		// getMajorType()B
					ifne L49;
				L45:	aload_1;
					aload 4;
					sconst_0;
					invokevirtual 283;		// readEncodedInteger([BS)S
					sstore 10;
					sload 10;
					sconst_1;
					if_scmpne L47;
				L46:	getfield_a_this 12;		// reference com/josh/vku2f/AuthenticatorMakeCredential.params
					aload 4;
					sconst_0;
					baload;
					invokevirtual 284;		// addAlgorithm(S)V
					goto_w L58;
				L47:	sload 10;
					sconst_2;
					if_scmpne L58;
				L48:	getfield_a_this 12;		// reference com/josh/vku2f/AuthenticatorMakeCredential.params
					aload 4;
					sconst_0;
					baload;
					aload 4;
					sconst_1;
					baload;
					invokestatic 287;		// javacard/framework/Util.makeShort(BB)S
					invokevirtual 284;		// addAlgorithm(S)V
					goto L58;
				L49:	aload_1;
					invokevirtual 282;		// getMajorType()B
					sconst_1;
					if_scmpne L58;
				L50:	aload_1;
					aload 4;
					sconst_0;
					invokevirtual 283;		// readEncodedInteger([BS)S
					sstore 10;
					sload 10;
					sconst_1;
					if_scmpne L52;
				L51:	getfield_a_this 12;		// reference com/josh/vku2f/AuthenticatorMakeCredential.params
					sconst_m1;
					aload 4;
					sconst_0;
					baload;
					ssub;
					invokevirtual 284;		// addAlgorithm(S)V
					goto L58;
				L52:	sload 10;
					sconst_2;
					if_scmpne L58;
				L53:	getfield_a_this 12;		// reference com/josh/vku2f/AuthenticatorMakeCredential.params
					sconst_m1;
					aload 4;
					sconst_0;
					baload;
					aload 4;
					sconst_1;
					baload;
					invokestatic 287;		// javacard/framework/Util.makeShort(BB)S
					ssub;
					invokevirtual 284;		// addAlgorithm(S)V
					goto L58;
				L54:	aload_3;
					sconst_0;
					getstatic_a 181;		// reference com/josh/vku2f/Utf8Strings.UTF8_TYPE
					sconst_0;
					sconst_4;
					invokestatic 134;		// javacard/framework/Util.arrayCompare([BS[BSS)B
					ifne L57;
				L55:	aload_1;
					aload_3;
					sconst_0;
					invokevirtual 121;		// readTextString([BS)S
					pop;
					aload_3;
					sconst_0;
					getstatic_a 290;		// reference com/josh/vku2f/Utf8Strings.UTF8_PUBLIC_KEY
					sconst_0;
					bspush 10;
					invokestatic 134;		// javacard/framework/Util.arrayCompare([BS[BSS)B
					ifeq L58;
				L56:	bspush 38;
					invokestatic 131;		// javacard/framework/UserException.throwIt(S)V
					goto L58;
				L57:	bspush 18;
					invokestatic 131;		// javacard/framework/UserException.throwIt(S)V
				L58:	sinc 11 1;
					goto_w L42;
				L59:	sinc 9 1;
					goto_w L38;
				L60:	goto_w L92;
				L61:	aload_1;
					sconst_4;
					invokevirtual 115;		// readMajorType(B)S
					sstore 8;
					aload_0;
					sload 8;
					anewarray 126;		// com/josh/vku2f/PublicKeyCredentialDescriptor
					putfield_a 13;		// reference com/josh/vku2f/AuthenticatorMakeCredential.exclude
					sconst_0;
					sstore 9;
				L62:	sload 9;
					sload 8;
					if_scmpge L74;
				L63:	aload_1;
					sconst_5;
					invokevirtual 115;		// readMajorType(B)S
					sstore 10;
					sload 10;
					sconst_2;
					if_scmpeq L65;
				L64:	bspush 18;
					invokestatic 131;		// javacard/framework/UserException.throwIt(S)V
				L65:	sconst_0;
					sstore 11;
				L66:	sload 11;
					sconst_2;
					if_scmpge L73;
				L67:	aload_1;
					aload_3;
					sconst_0;
					invokevirtual 121;		// readTextString([BS)S
					pop;
					aload_3;
					sconst_0;
					getstatic_a 132;		// reference com/josh/vku2f/Utf8Strings.UTF8_ID
					sconst_0;
					sconst_2;
					invokestatic 134;		// javacard/framework/Util.arrayCompare([BS[BSS)B
					ifne L69;
				L68:	aload_1;
					aload_3;
					sconst_0;
					invokevirtual 124;		// readByteString([BS)S
					sstore 10;
					getfield_a_this 13;		// reference com/josh/vku2f/AuthenticatorMakeCredential.exclude
					sload 9;
					new 126;		// com/josh/vku2f/PublicKeyCredentialDescriptor
					dup;
					aload_3;
					sconst_0;
					sload 10;
					invokespecial 135;		// com/josh/vku2f/PublicKeyCredentialDescriptor.<init>([BSS)V
					aastore;
					goto L72;
				L69:	aload_3;
					sconst_0;
					getstatic_a 181;		// reference com/josh/vku2f/Utf8Strings.UTF8_TYPE
					sconst_0;
					sconst_4;
					invokestatic 134;		// javacard/framework/Util.arrayCompare([BS[BSS)B
					ifne L71;
				L70:	aload_1;
					aload_3;
					sconst_0;
					invokevirtual 121;		// readTextString([BS)S
					pop;
					goto L72;
				L71:	bspush 17;
					invokestatic 131;		// javacard/framework/UserException.throwIt(S)V
					goto L73;
				L72:	sinc 11 1;
					goto L66;
				L73:	sinc 9 1;
					goto L62;
				L74:	goto_w L92;
				L75:	aload_1;
					invokevirtual 282;		// getMajorType()B
					sconst_5;
					if_scmpeq L77;
				L76:	bspush 17;
					invokestatic 131;		// javacard/framework/UserException.throwIt(S)V
					goto L92;
				L77:	aload_1;
					sconst_5;
					invokevirtual 115;		// readMajorType(B)S
					sstore 8;
					sconst_0;
					sstore 9;
				L78:	sload 9;
					sload 8;
					if_scmpge L87;
				L79:	aload_1;
					aload_3;
					sconst_0;
					invokevirtual 121;		// readTextString([BS)S
					pop;
					aload_3;
					sconst_0;
					getstatic_a 208;		// reference com/josh/vku2f/Utf8Strings.UTF8_UV
					sconst_0;
					sconst_2;
					invokestatic 134;		// javacard/framework/Util.arrayCompare([BS[BSS)B
					ifne L81;
				L80:	getfield_a_this 8;		// reference com/josh/vku2f/AuthenticatorMakeCredential.options
					sconst_1;
					aload_1;
					invokevirtual 197;		// readBoolean()Z
					bastore;
					goto L86;
				L81:	aload_3;
					sconst_0;
					getstatic_a 298;		// reference com/josh/vku2f/Utf8Strings.UTF8_RK
					sconst_0;
					sconst_2;
					invokestatic 134;		// javacard/framework/Util.arrayCompare([BS[BSS)B
					ifne L83;
				L82:	aload_1;
					invokevirtual 197;		// readBoolean()Z
					pop;
					goto L86;
				L83:	aload_3;
					sconst_0;
					getstatic_a 195;		// reference com/josh/vku2f/Utf8Strings.UTF8_UP
					sconst_0;
					sconst_2;
					invokestatic 134;		// javacard/framework/Util.arrayCompare([BS[BSS)B
					ifne L85;
				L84:	bspush 44;
					invokestatic 131;		// javacard/framework/UserException.throwIt(S)V
					goto L87;
				L85:	aload_1;
					invokevirtual 209;		// skipEntry()S
					pop;
				L86:	sinc 9 1;
					goto L78;
				L87:	goto L92;
				L88:	aload_1;
					invokevirtual 282;		// getMajorType()B
					sconst_5;
					if_scmpeq L90;
				L89:	bspush 17;
					invokestatic 131;		// javacard/framework/UserException.throwIt(S)V
					goto L92;
				L90:	aload_1;
					invokevirtual 209;		// skipEntry()S
					pop;
					goto L92;
				L91:	aload_1;
					invokevirtual 209;		// skipEntry()S
					pop;
				L92:	sinc 6 1;
					goto_w L11;
				L93:	getfield_a_this 9;		// reference com/josh/vku2f/AuthenticatorMakeCredential.dataHash
					ifnull L97;
				L94:	getfield_a_this 10;		// reference com/josh/vku2f/AuthenticatorMakeCredential.rp
					ifnull L97;
				L95:	getfield_a_this 11;		// reference com/josh/vku2f/AuthenticatorMakeCredential.user
					ifnull L97;
				L96:	getfield_a_this 12;		// reference com/josh/vku2f/AuthenticatorMakeCredential.params
					ifnonnull L98;
				L97:	bspush 20;
					invokestatic 131;		// javacard/framework/UserException.throwIt(S)V
				L98:	return;
			.exceptionTable {
				// start_block end_block handler_block catch_type_index
				L1 L2 L3 106;
				L4 L5 L6 106;
				L7 L8 L9 106;
			}
		}

		.method public getUser()Lcom/josh/vku2f/PublicKeyCredentialUserEntity; 1 {
			.stack 1;
			.locals 0;

				L0:	getfield_a_this 11;		// reference com/josh/vku2f/AuthenticatorMakeCredential.user
					areturn;
		}

		.method public getRp()Lcom/josh/vku2f/PublicKeyCredentialRpEntity; 2 {
			.stack 1;
			.locals 0;

				L0:	getfield_a_this 10;		// reference com/josh/vku2f/AuthenticatorMakeCredential.rp
					areturn;
		}

		.method public isResident()Z 3 {
			.stack 2;
			.locals 0;

				L0:	getfield_a_this 8;		// reference com/josh/vku2f/AuthenticatorMakeCredential.options
					sconst_0;
					baload;
					sreturn;
		}

		.method public getAlgorithm()B 4 {
			.stack 1;
			.locals 0;

				L0:	getfield_a_this 12;		// reference com/josh/vku2f/AuthenticatorMakeCredential.params
					invokevirtual 67;		// getAlgorithm()B
					sreturn;
		}

		.method public isExclude()Z 5 {
			.stack 1;
			.locals 0;

				L0:	getfield_a_this 13;		// reference com/josh/vku2f/AuthenticatorMakeCredential.exclude
					ifnull L3;
				L1:	getfield_a_this 13;		// reference com/josh/vku2f/AuthenticatorMakeCredential.exclude
					arraylength;
					ifle L3;
				L2:	sconst_1;
					goto L4;
				L3:	sconst_0;
				L4:	sreturn;
		}

		.method public getDataHash([BS)S 6 {
			.stack 5;
			.locals 0;

				L0:	getfield_a_this 9;		// reference com/josh/vku2f/AuthenticatorMakeCredential.dataHash
					sconst_0;
					aload_1;
					sload_2;
					getfield_a_this 9;		// reference com/josh/vku2f/AuthenticatorMakeCredential.dataHash
					arraylength;
					invokestatic 104;		// javacard/framework/Util.arrayCopy([BS[BSS)S
					pop;
					getfield_a_this 9;		// reference com/josh/vku2f/AuthenticatorMakeCredential.dataHash
					arraylength;
					sreturn;
		}

	}

	.class public abstract CBORBase 3 extends 0.0 {		// extends java/lang/Object

		.fields {
			protected short[] mStatusWords 0;		// [S
			protected byte[] mBuffer 1;		// [B
			protected static final byte MAJOR_TYPE_MASK = 7;		// B
			protected static final byte ADDINFO_MASK = 31;		// B
			public static final byte TYPE_UNSIGNED_INTEGER = 0;		// B
			public static final byte TYPE_NEGATIVE_INTEGER = 1;		// B
			public static final byte TYPE_BYTE_STRING = 2;		// B
			public static final byte TYPE_TEXT_STRING = 3;		// B
			public static final byte TYPE_ARRAY = 4;		// B
			public static final byte TYPE_MAP = 5;		// B
			public static final byte TYPE_TAG = 6;		// B
			public static final byte TYPE_FLOAT = 7;		// B
			protected static final byte ENCODED_ONE_BYTE = 24;		// B
			protected static final byte ENCODED_TWO_BYTES = 25;		// B
			protected static final byte ENCODED_FOUR_BYTES = 26;		// B
			protected static final byte ENCODED_EIGHT_BYTES = 27;		// B
			protected static final byte ENCODED_FALSE = -12;		// B
			protected static final byte ENCODED_TRUE = -11;		// B
			protected static final byte ENCODED_NULL = -10;		// B
			protected static final byte ENCODED_UNDEFINED = -9;		// B
			protected static final byte ENCODED_BREAK = -1;		// B
			public static final byte INVALID_INPUT = -1;		// B
		}

		.publicMethodTable 1 {
			equals(Ljava/lang/Object;)Z;
			init(SS)V;
			init([BSS)V;
			reset()V;
			getCurrentOffset()S;
			getBufferLength()S;
			getCurrentOffsetAndIncrease(S)S;
			increaseOffset(S)S;
			getRawByte()B;
			getBuffer()[B;
		}

		.packageMethodTable 0 {
		}

		.method public final init(SS)V 1 {
			.stack 4;
			.locals 0;

				L0:	aconst_null;
					putfield_a_this 14;		// reference com/josh/vku2f/CBORBase.mBuffer
					getfield_a_this 15;		// reference com/josh/vku2f/CBORBase.mStatusWords
					sconst_0;
					sload_1;
					sastore;
					getfield_a_this 15;		// reference com/josh/vku2f/CBORBase.mStatusWords
					sconst_1;
					sload_1;
					sload_2;
					sadd;
					sastore;
					return;
		}

		.method public final init([BSS)V 2 {
			.stack 4;
			.locals 0;

				L0:	aload_1;
					invokestatic 70;		// javacard/framework/APDU.getCurrentAPDUBuffer()[B
					if_acmpeq L2;
				L1:	aload_1;
					putfield_a_this 14;		// reference com/josh/vku2f/CBORBase.mBuffer
					goto L3;
				L2:	aconst_null;
					putfield_a_this 14;		// reference com/josh/vku2f/CBORBase.mBuffer
				L3:	getfield_a_this 15;		// reference com/josh/vku2f/CBORBase.mStatusWords
					sconst_0;
					sload_2;
					sastore;
					getfield_a_this 15;		// reference com/josh/vku2f/CBORBase.mStatusWords
					sconst_1;
					sload_2;
					sload_3;
					sadd;
					sastore;
					return;
		}

		.method public final reset()V 3 {
			.stack 3;
			.locals 0;

				L0:	aconst_null;
					putfield_a_this 14;		// reference com/josh/vku2f/CBORBase.mBuffer
					getfield_a_this 15;		// reference com/josh/vku2f/CBORBase.mStatusWords
					sconst_0;
					sconst_0;
					sastore;
					getfield_a_this 15;		// reference com/josh/vku2f/CBORBase.mStatusWords
					sconst_1;
					sconst_0;
					sastore;
					return;
		}

		.method public final getCurrentOffset()S 4 {
			.stack 2;
			.locals 0;

				L0:	getfield_a_this 15;		// reference com/josh/vku2f/CBORBase.mStatusWords
					sconst_0;
					saload;
					sreturn;
		}

		.method public final getBufferLength()S 5 {
			.stack 2;
			.locals 0;

				L0:	getfield_a_this 15;		// reference com/josh/vku2f/CBORBase.mStatusWords
					sconst_1;
					saload;
					sreturn;
		}

		.method protected final getCurrentOffsetAndIncrease(S)S 6 {
			.stack 2;
			.locals 1;

				L0:	getfield_a_this 15;		// reference com/josh/vku2f/CBORBase.mStatusWords
					sconst_0;
					saload;
					sstore_2;
					aload_0;
					sload_1;
					invokevirtual 71;		// increaseOffset(S)S
					pop;
					sload_2;
					sreturn;
		}

		.method protected final increaseOffset(S)S 7 {
			.stack 4;
			.locals 0;

				L0:	aload_0;
					invokevirtual 72;		// getCurrentOffset()S
					sload_1;
					sadd;
					aload_0;
					invokevirtual 73;		// getBufferLength()S
					if_scmpgt L2;
				L1:	sload_1;
					ifge L3;
				L2:	sspush 26368;
					invokestatic 74;		// javacard/framework/ISOException.throwIt(S)V
				L3:	getfield_a_this 15;		// reference com/josh/vku2f/CBORBase.mStatusWords
					sconst_0;
					dup2;
					saload;
					sload_1;
					sadd;
					sastore;
					getfield_a_this 15;		// reference com/josh/vku2f/CBORBase.mStatusWords
					sconst_0;
					saload;
					sreturn;
		}

		.method protected <init>()V 0 {
			.stack 3;
			.locals 0;

				L0:	aload_0;
					invokespecial 69;		// java/lang/Object.<init>()V
					aload_0;
					sconst_2;
					sconst_1;
					invokestatic 109;		// javacard/framework/JCSystem.makeTransientShortArray(SB)[S
					putfield_a 15;		// reference com/josh/vku2f/CBORBase.mStatusWords
					return;
		}

		.method protected getRawByte()B 8 {
			.stack 3;
			.locals 0;

				L0:	aload_0;
					invokevirtual 75;		// getBuffer()[B
					getfield_a_this 15;		// reference com/josh/vku2f/CBORBase.mStatusWords
					sconst_0;
					saload;
					baload;
					sreturn;
		}

		.method protected getBuffer()[B 9 {
			.stack 1;
			.locals 0;

				L0:	getfield_a_this 14;		// reference com/josh/vku2f/CBORBase.mBuffer
					ifnonnull L2;
				L1:	invokestatic 70;		// javacard/framework/APDU.getCurrentAPDUBuffer()[B
					areturn;
				L2:	getfield_a_this 14;		// reference com/josh/vku2f/CBORBase.mBuffer
					areturn;
		}

	}

	.class public CBORDecoder 4 extends CBORBase {

		.publicMethodTable 10 {
			equals(Ljava/lang/Object;)Z;
			init(SS)V;
			init([BSS)V;
			reset()V;
			getCurrentOffset()S;
			getBufferLength()S;
			getCurrentOffsetAndIncrease(S)S;
			increaseOffset(S)S;
			getRawByte()B;
			getBuffer()[B;
			getMajorType()B;
			getIntegerSize()B;
			skipEntry()S;
			readMajorType(B)S;
			readInt8()B;
			readInt16()S;
			readInt32([BS)V;
			readInt64([BS)V;
			readEncodedInteger([BS)S;
			readLength()S;
			readBoolean()Z;
			readByteString([BS)S;
			readTextString([BS)S;
			readRawByteArray([BSS)S;
			readRawByte()B;
		}

		.packageMethodTable 0 {
		}

		.method public <init>()V 0 {
			.stack 1;
			.locals 0;

				L0:	aload_0;
					invokespecial 76;		// com/josh/vku2f/CBORBase.<init>()V
					return;
		}

		.method public getMajorType()B 10 {
			.stack 2;
			.locals 0;

				L0:	aload_0;
					invokevirtual 77;		// getRawByte()B
					sconst_5;
					sushr;
					bspush 7;
					sand;
					s2b;
					sreturn;
		}

		.method public getIntegerSize()B 11 {
			.stack 2;
			.locals 1;

				L0:	aload_0;
					invokevirtual 77;		// getRawByte()B
					bspush 31;
					sand;
					sstore_1;
					sload_1;
					bspush 24;
					if_scmpgt L2;
				L1:	sconst_1;
					sreturn;
				L2:	sload_1;
					bspush 25;
					if_scmpne L4;
				L3:	sconst_2;
					sreturn;
				L4:	sload_1;
					bspush 26;
					if_scmpne L6;
				L5:	sconst_4;
					sreturn;
				L6:	sload_1;
					bspush 27;
					if_scmpne L8;
				L7:	bspush 8;
					sreturn;
				L8:	sconst_m1;
					sreturn;
		}

		.method public skipEntry()S 12 {
			.stack 3;
			.locals 3;

				L0:	sconst_1;
					sstore_1;
					aload_0;
					invokevirtual 282;		// getMajorType()B
					stableswitch L10 0 7 L1 L1 L4 L4 L6 L5 L10 L10;
				L1:	aload_0;
					invokevirtual 78;		// getIntegerSize()B
					sstore_2;
					sload_2;
					sconst_1;
					if_scmpne L3;
				L2:	aload_0;
					invokevirtual 120;		// readInt8()B
					pop;
					goto L10;
				L3:	aload_0;
					sconst_1;
					sload_2;
					sadd;
					invokevirtual 79;		// increaseOffset(S)S
					pop;
					goto L10;
				L4:	aload_0;
					aload_0;
					invokevirtual 80;		// readLength()S
					invokevirtual 79;		// increaseOffset(S)S
					pop;
					goto L10;
				L5:	sconst_2;
					sstore_1;
				L6:	sload_1;
					aload_0;
					invokevirtual 80;		// readLength()S
					smul;
					sstore_1;
					sconst_0;
					sstore_3;
				L7:	sload_3;
					sload_1;
					if_scmpge L9;
				L8:	aload_0;
					invokevirtual 209;		// skipEntry()S
					pop;
					sinc 3 1;
					goto L7;
				L9:	goto L10;
				L10:	aload_0;
					invokevirtual 81;		// getCurrentOffset()S
					sreturn;
		}

		.method public readMajorType(B)S 13 {
			.stack 2;
			.locals 0;

				L0:	sload_1;
					aload_0;
					invokevirtual 282;		// getMajorType()B
					if_scmpeq L2;
				L1:	bspush 17;
					invokestatic 131;		// javacard/framework/UserException.throwIt(S)V
					sconst_0;
					sreturn;
				L2:	aload_0;
					invokevirtual 80;		// readLength()S
					sreturn;
		}

		.method public readInt8()B 14 {
			.stack 2;
			.locals 1;

				L0:	aload_0;
					invokevirtual 82;		// readRawByte()B
					bspush 31;
					sand;
					sstore_1;
					sload_1;
					bspush 24;
					if_scmpge L2;
				L1:	sload_1;
					sreturn;
				L2:	sload_1;
					bspush 24;
					if_scmpne L4;
				L3:	aload_0;
					invokevirtual 82;		// readRawByte()B
					sspush 255;
					sand;
					s2b;
					sreturn;
				L4:	sspush 27012;
					invokestatic 74;		// javacard/framework/ISOException.throwIt(S)V
					sconst_0;
					sreturn;
		}

		.method public readInt16()S 15 {
			.stack 3;
			.locals 1;

				L0:	aload_0;
					invokevirtual 82;		// readRawByte()B
					bspush 31;
					sand;
					sstore_1;
					sload_1;
					bspush 25;
					if_scmpne L2;
				L1:	aload_0;
					invokevirtual 83;		// getBuffer()[B
					aload_0;
					sconst_2;
					invokevirtual 84;		// getCurrentOffsetAndIncrease(S)S
					invokestatic 85;		// javacard/framework/Util.getShort([BS)S
					sreturn;
				L2:	sspush 27012;
					invokestatic 74;		// javacard/framework/ISOException.throwIt(S)V
					sconst_0;
					sreturn;
		}

		.method public readInt32([BS)V 16 {
			.stack 5;
			.locals 1;

				L0:	aload_0;
					invokevirtual 82;		// readRawByte()B
					bspush 31;
					sand;
					sstore_3;
					sload_3;
					bspush 26;
					if_scmpne L2;
				L1:	aload_0;
					invokevirtual 83;		// getBuffer()[B
					aload_0;
					sconst_4;
					invokevirtual 84;		// getCurrentOffsetAndIncrease(S)S
					aload_1;
					sload_2;
					sconst_4;
					invokestatic 86;		// javacard/framework/Util.arrayCopyNonAtomic([BS[BSS)S
					pop;
					goto L3;
				L2:	sspush 27012;
					invokestatic 74;		// javacard/framework/ISOException.throwIt(S)V
				L3:	return;
		}

		.method public readInt64([BS)V 17 {
			.stack 5;
			.locals 1;

				L0:	aload_0;
					invokevirtual 82;		// readRawByte()B
					bspush 31;
					sand;
					sstore_3;
					sload_3;
					bspush 27;
					if_scmpne L2;
				L1:	aload_0;
					invokevirtual 83;		// getBuffer()[B
					aload_0;
					bspush 8;
					invokevirtual 84;		// getCurrentOffsetAndIncrease(S)S
					aload_1;
					sload_2;
					bspush 8;
					invokestatic 86;		// javacard/framework/Util.arrayCopyNonAtomic([BS[BSS)S
					pop;
					goto L3;
				L2:	sspush 27012;
					invokestatic 74;		// javacard/framework/ISOException.throwIt(S)V
				L3:	return;
		}

		.method public readEncodedInteger([BS)S 18 {
			.stack 5;
			.locals 1;

				L0:	aload_0;
					invokevirtual 78;		// getIntegerSize()B
					sstore_3;
					sload_3;
					sconst_1;
					if_scmpne L2;
				L1:	aload_1;
					sload_2;
					aload_0;
					invokevirtual 120;		// readInt8()B
					bastore;
					goto L3;
				L2:	aload_0;
					invokevirtual 83;		// getBuffer()[B
					aload_0;
					sconst_1;
					sload_3;
					sadd;
					invokevirtual 84;		// getCurrentOffsetAndIncrease(S)S
					aload_1;
					sload_2;
					sload_3;
					invokestatic 86;		// javacard/framework/Util.arrayCopyNonAtomic([BS[BSS)S
					pop;
				L3:	sload_3;
					sspush 255;
					sand;
					sreturn;
		}

		.method public readLength()S 19 {
			.stack 2;
			.locals 2;

				L0:	aload_0;
					invokevirtual 78;		// getIntegerSize()B
					sstore_1;
					sconst_0;
					sstore_2;
					sload_1;
					sconst_1;
					if_scmpne L2;
				L1:	aload_0;
					invokevirtual 120;		// readInt8()B
					sspush 255;
					sand;
					sstore_2;
					goto L5;
				L2:	sload_1;
					sconst_2;
					if_scmpne L4;
				L3:	aload_0;
					invokevirtual 87;		// readInt16()S
					sstore_2;
					goto L5;
				L4:	sspush 27012;
					invokestatic 74;		// javacard/framework/ISOException.throwIt(S)V
				L5:	sload_2;
					sreturn;
		}

		.method public readBoolean()Z 20 {
			.stack 2;
			.locals 1;

				L0:	aload_0;
					invokevirtual 82;		// readRawByte()B
					sstore_1;
					sload_1;
					bspush -11;
					if_scmpne L2;
				L1:	sconst_1;
					sreturn;
				L2:	sload_1;
					bspush -12;
					if_scmpne L4;
				L3:	sconst_0;
					sreturn;
				L4:	sspush 27012;
					invokestatic 74;		// javacard/framework/ISOException.throwIt(S)V
					sconst_1;
					sreturn;
		}

		.method public readByteString([BS)S 21 {
			.stack 4;
			.locals 1;

				L0:	aload_0;
					invokevirtual 282;		// getMajorType()B
					sconst_2;
					if_scmpeq L2;
				L1:	bspush 17;
					invokestatic 131;		// javacard/framework/UserException.throwIt(S)V
					sconst_0;
					sreturn;
				L2:	aload_0;
					invokevirtual 80;		// readLength()S
					sstore_3;
					aload_0;
					aload_1;
					sload_2;
					sload_3;
					invokevirtual 88;		// readRawByteArray([BSS)S
					sreturn;
		}

		.method public readTextString([BS)S 22 {
			.stack 4;
			.locals 1;

				L0:	aload_0;
					invokevirtual 282;		// getMajorType()B
					sconst_3;
					if_scmpeq L2;
				L1:	bspush 17;
					invokestatic 131;		// javacard/framework/UserException.throwIt(S)V
					sconst_0;
					sreturn;
				L2:	aload_0;
					invokevirtual 80;		// readLength()S
					sstore_3;
					aload_0;
					aload_1;
					sload_2;
					sload_3;
					invokevirtual 88;		// readRawByteArray([BSS)S
					sreturn;
		}

		.method public readRawByteArray([BSS)S 23 {
			.stack 5;
			.locals 0;

				L0:	sload_3;
					aload_1;
					arraylength;
					if_scmpgt L2;
				L1:	sload_3;
					aload_0;
					invokevirtual 81;		// getCurrentOffset()S
					sadd;
					aload_0;
					invokevirtual 89;		// getBufferLength()S
					if_scmple L3;
				L2:	sspush 26368;
					invokestatic 74;		// javacard/framework/ISOException.throwIt(S)V
				L3:	aload_0;
					invokevirtual 83;		// getBuffer()[B
					aload_0;
					invokevirtual 81;		// getCurrentOffset()S
					aload_1;
					sload_2;
					sload_3;
					invokestatic 86;		// javacard/framework/Util.arrayCopyNonAtomic([BS[BSS)S
					sstore_3;
					aload_0;
					sload_3;
					invokevirtual 79;		// increaseOffset(S)S
					pop;
					sload_3;
					sreturn;
		}

		.method public readRawByte()B 24 {
			.stack 6;
			.locals 0;

				L0:	aload_0;
					invokevirtual 83;		// getBuffer()[B
					getfield_a_this 15;		// reference com/josh/vku2f/CBORBase.mStatusWords
					sconst_0;
					dup2;
					saload;
					dup_x 19;
					sconst_1;
					sadd;
					sastore;
					baload;
					sreturn;
		}

	}

	.class public CBOREncoder 5 extends CBORBase {

		.publicMethodTable 10 {
			equals(Ljava/lang/Object;)Z;
			init(SS)V;
			init([BSS)V;
			reset()V;
			getCurrentOffset()S;
			getBufferLength()S;
			getCurrentOffsetAndIncrease(S)S;
			increaseOffset(S)S;
			getRawByte()B;
			getBuffer()[B;
			writeRawByte(B)S;
			startArray(S)S;
			startMap(S)S;
			startByteString(S)S;
			startTextString(S)S;
			encodeByteString([BSS)S;
			encodeTextString([BSS)S;
			encodeUInt8(B)S;
			encodeNegativeUInt8(B)S;
			encodeNegativeUInt16(S)S;
			encodeUInt16(S)S;
			encodeUInt32([BS)S;
			encodeUInt64([BS)S;
			encodeBoolean(Z)S;
		}

		.packageMethodTable 0 {
		}

		.method private final encodeValue(BS)S {
			.stack 3;
			.locals 0;

				L0:	sload_2;
					bspush 24;
					invokestatic 90;		// com/josh/vku2f/ICUtil.isLessThanAsUnsignedShort(SS)Z
					ifeq L2;
				L1:	aload_0;
					sload_1;
					sload_2;
					sor;
					s2b;
					invokevirtual 91;		// writeRawByte(B)S
					sreturn;
				L2:	sload_2;
					sspush 256;
					invokestatic 90;		// com/josh/vku2f/ICUtil.isLessThanAsUnsignedShort(SS)Z
					ifeq L4;
				L3:	aload_0;
					sload_1;
					sload_2;
					s2b;
					invokespecial 92;		// com/josh/vku2f/CBOREncoder.writeUInt8(BB)S
					sreturn;
				L4:	aload_0;
					sload_1;
					sload_2;
					invokespecial 93;		// com/josh/vku2f/CBOREncoder.writeUInt16(BS)S
					sreturn;
		}

		.method private final writeUInt8(BB)S {
			.stack 3;
			.locals 0;

				L0:	aload_0;
					sload_1;
					bspush 24;
					sor;
					invokevirtual 91;		// writeRawByte(B)S
					pop;
					aload_0;
					sload_2;
					invokevirtual 91;		// writeRawByte(B)S
					pop;
					sconst_2;
					sreturn;
		}

		.method private final writeUInt16(BS)S {
			.stack 3;
			.locals 0;

				L0:	aload_0;
					sload_1;
					bspush 25;
					sor;
					invokevirtual 91;		// writeRawByte(B)S
					pop;
					aload_0;
					sload_2;
					invokespecial 94;		// com/josh/vku2f/CBOREncoder.writeRawShort(S)S
					pop;
					sconst_3;
					sreturn;
		}

		.method public final writeRawByte(B)S 10 {
			.stack 3;
			.locals 0;

				L0:	aload_0;
					invokevirtual 95;		// getBuffer()[B
					aload_0;
					invokevirtual 96;		// getCurrentOffset()S
					sload_1;
					bastore;
					aload_0;
					sconst_1;
					invokevirtual 97;		// increaseOffset(S)S
					pop;
					sconst_1;
					sreturn;
		}

		.method private final writeRawShort(S)S {
			.stack 3;
			.locals 0;

				L0:	aload_0;
					invokevirtual 95;		// getBuffer()[B
					aload_0;
					invokevirtual 96;		// getCurrentOffset()S
					sload_1;
					invokestatic 98;		// javacard/framework/Util.setShort([BSS)S
					pop;
					aload_0;
					sconst_2;
					invokevirtual 97;		// increaseOffset(S)S
					pop;
					sconst_2;
					sreturn;
		}

		.method private final writeRawByteArray([BSS)S {
			.stack 5;
			.locals 1;

				L0:	sload_3;
					aload_1;
					arraylength;
					sload_2;
					sadd;
					if_scmpgt L2;
				L1:	sload_3;
					aload_0;
					invokevirtual 96;		// getCurrentOffset()S
					sadd;
					aload_0;
					invokevirtual 99;		// getBufferLength()S
					if_scmple L3;
				L2:	sspush 26368;
					invokestatic 74;		// javacard/framework/ISOException.throwIt(S)V
				L3:	aload_0;
					invokevirtual 96;		// getCurrentOffset()S
					sstore 4;
					aload_1;
					sload_2;
					aload_0;
					invokevirtual 95;		// getBuffer()[B
					sload 4;
					sload_3;
					invokestatic 86;		// javacard/framework/Util.arrayCopyNonAtomic([BS[BSS)S
					sload 4;
					ssub;
					sstore_3;
					aload_0;
					sload_3;
					invokevirtual 97;		// increaseOffset(S)S
					pop;
					sload_3;
					sreturn;
		}

		.method public <init>()V 0 {
			.stack 1;
			.locals 0;

				L0:	aload_0;
					invokespecial 76;		// com/josh/vku2f/CBORBase.<init>()V
					return;
		}

		.method public startArray(S)S 11 {
			.stack 3;
			.locals 0;

				L0:	aload_0;
					bspush -128;
					sload_1;
					invokespecial 100;		// com/josh/vku2f/CBOREncoder.encodeValue(BS)S
					pop;
					aload_0;
					invokevirtual 96;		// getCurrentOffset()S
					sreturn;
		}

		.method public startMap(S)S 12 {
			.stack 3;
			.locals 0;

				L0:	aload_0;
					bspush -96;
					sload_1;
					invokespecial 100;		// com/josh/vku2f/CBOREncoder.encodeValue(BS)S
					pop;
					aload_0;
					invokevirtual 96;		// getCurrentOffset()S
					sreturn;
		}

		.method public startByteString(S)S 13 {
			.stack 3;
			.locals 0;

				L0:	aload_0;
					bspush 64;
					sload_1;
					invokespecial 100;		// com/josh/vku2f/CBOREncoder.encodeValue(BS)S
					pop;
					aload_0;
					sload_1;
					invokevirtual 101;		// getCurrentOffsetAndIncrease(S)S
					sreturn;
		}

		.method public startTextString(S)S 14 {
			.stack 3;
			.locals 0;

				L0:	aload_0;
					bspush 96;
					sload_1;
					invokespecial 100;		// com/josh/vku2f/CBOREncoder.encodeValue(BS)S
					pop;
					aload_0;
					sload_1;
					invokevirtual 101;		// getCurrentOffsetAndIncrease(S)S
					sreturn;
		}

		.method public encodeByteString([BSS)S 15 {
			.stack 5;
			.locals 1;

				L0:	aload_0;
					bspush 64;
					sload_3;
					invokespecial 100;		// com/josh/vku2f/CBOREncoder.encodeValue(BS)S
					sstore 4;
					sload 4;
					aload_0;
					aload_1;
					sload_2;
					sload_3;
					invokespecial 102;		// com/josh/vku2f/CBOREncoder.writeRawByteArray([BSS)S
					sadd;
					sstore 4;
					sload 4;
					sreturn;
		}

		.method public encodeTextString([BSS)S 16 {
			.stack 5;
			.locals 1;

				L0:	aload_0;
					bspush 96;
					sload_3;
					invokespecial 100;		// com/josh/vku2f/CBOREncoder.encodeValue(BS)S
					sstore 4;
					sload 4;
					aload_0;
					aload_1;
					sload_2;
					sload_3;
					invokespecial 102;		// com/josh/vku2f/CBOREncoder.writeRawByteArray([BSS)S
					sadd;
					sstore 4;
					sload 4;
					sreturn;
		}

		.method public encodeUInt8(B)S 17 {
			.stack 4;
			.locals 0;

				L0:	aload_0;
					sconst_0;
					sload_1;
					sspush 255;
					sand;
					invokespecial 100;		// com/josh/vku2f/CBOREncoder.encodeValue(BS)S
					sreturn;
		}

		.method public encodeNegativeUInt8(B)S 18 {
			.stack 4;
			.locals 0;

				L0:	aload_0;
					bspush 32;
					sload_1;
					sspush 255;
					sand;
					invokespecial 100;		// com/josh/vku2f/CBOREncoder.encodeValue(BS)S
					sreturn;
		}

		.method public encodeNegativeUInt16(S)S 19 {
			.stack 3;
			.locals 0;

				L0:	aload_0;
					bspush 32;
					sload_1;
					invokespecial 100;		// com/josh/vku2f/CBOREncoder.encodeValue(BS)S
					sreturn;
		}

		.method public encodeUInt16(S)S 20 {
			.stack 3;
			.locals 0;

				L0:	aload_0;
					sconst_0;
					sload_1;
					invokespecial 100;		// com/josh/vku2f/CBOREncoder.encodeValue(BS)S
					sreturn;
		}

		.method public encodeUInt32([BS)S 21 {
			.stack 4;
			.locals 0;

				L0:	aload_0;
					bspush 26;
					invokevirtual 91;		// writeRawByte(B)S
					pop;
					aload_0;
					aload_1;
					sload_2;
					sconst_4;
					invokespecial 102;		// com/josh/vku2f/CBOREncoder.writeRawByteArray([BSS)S
					sconst_1;
					sadd;
					sreturn;
		}

		.method public encodeUInt64([BS)S 22 {
			.stack 4;
			.locals 0;

				L0:	aload_0;
					bspush 27;
					invokevirtual 91;		// writeRawByte(B)S
					pop;
					aload_0;
					aload_1;
					sload_2;
					bspush 8;
					invokespecial 102;		// com/josh/vku2f/CBOREncoder.writeRawByteArray([BSS)S
					sconst_1;
					sadd;
					sreturn;
		}

		.method public encodeBoolean(Z)S 23 {
			.stack 2;
			.locals 0;

				L0:	sload_1;
					ifeq L2;
				L1:	aload_0;
					bspush -11;
					invokevirtual 91;		// writeRawByte(B)S
					sreturn;
				L2:	aload_0;
					bspush -12;
					invokevirtual 91;		// writeRawByte(B)S
					sreturn;
		}

	}

	.class public CTAP2 6 extends 2.3 {		// extends javacard/framework/Applet

		.fields {
			private CBORDecoder cborDecoder 0;		// Lcom/josh/vku2f/CBORDecoder;
			private CBOREncoder cborEncoder 1;		// Lcom/josh/vku2f/CBOREncoder;
			private byte[] inBuf 2;		// [B
			private byte[] scratch 3;		// [B
			private short[] vars 4;		// [S
			private CredentialArray discoverableCreds 5;		// Lcom/josh/vku2f/CredentialArray;
			private 1.11 sha 6;		// Ljavacard/security/MessageDigest;
			private AttestationKeyPair attestation 7;		// Lcom/josh/vku2f/AttestationKeyPair;
			private byte[] info 8;		// [B
			private StoredCredential[] assertionCreds 9;		// [Lcom/josh/vku2f/StoredCredential;
			private short[] nextAssertion 10;		// [S
			 AuthenticatorGetAssertion assertion 11;		// Lcom/josh/vku2f/AuthenticatorGetAssertion;
			private boolean[] isChaining 12;		// [Z
			private short[] chainRam 13;		// [S
			private short[] outChainRam 14;		// [S
			private boolean[] isOutChaining 15;		// [Z
			private AuthenticatorMakeCredential cred 16;		// Lcom/josh/vku2f/AuthenticatorMakeCredential;
			private 1.16 ecDhKey 17;		// Ljavacard/security/KeyPair;
			private boolean[] ecDhSet 18;		// [Z
			private StoredCredential tempCred 19;		// Lcom/josh/vku2f/StoredCredential;
			private boolean persoComplete 20;		// Z
			public static final byte CTAP1_ERR_SUCCESS = 0;		// B
			public static final byte CTAP1_ERR_INVALID_COMMAND = 1;		// B
			public static final byte CTAP1_ERR_INVALID_PARAMETER = 2;		// B
			public static final byte CTAP1_ERR_INVALID_LENGTH = 3;		// B
			public static final byte CTAP1_ERR_INVALID_SEQ = 4;		// B
			public static final byte CTAP1_ERR_TIMEOUT = 5;		// B
			public static final byte CTAP1_ERR_CHANNEL_BUSY = 6;		// B
			public static final byte CTAP1_ERR_LOCK_REQUIRED = 10;		// B
			public static final byte CTAP1_ERR_INVALID_CHANNEL = 11;		// B
			public static final byte CTAP1_ERR_OTHER = 127;		// B
			public static final byte CTAP2_ERR_CBOR_UNEXPECTED_TYPE = 17;		// B
			public static final byte CTAP2_ERR_INVALID_CBOR = 18;		// B
			public static final byte CTAP2_ERR_MISSING_PARAMETER = 20;		// B
			public static final byte CTAP2_ERR_LIMIT_EXCEEDED = 21;		// B
			public static final byte CTAP2_ERR_UNSUPPORTED_EXTENSION = 22;		// B
			public static final byte CTAP2_ERR_CREDENTIAL_EXCLUDED = 25;		// B
			public static final byte CTAP2_ERR_PROCESSING = 33;		// B
			public static final byte CTAP2_ERR_INVALID_CREDENTIAL = 34;		// B
			public static final byte CTAP2_ERR_USER_ACTION_PENDING = 35;		// B
			public static final byte CTAP2_ERR_OPERATION_PENDING = 36;		// B
			public static final byte CTAP2_ERR_NO_OPERATIONS = 37;		// B
			public static final byte CTAP2_ERR_UNSUPPORTED_ALGORITHM = 38;		// B
			public static final byte CTAP2_ERR_OPERATION_DENIED = 39;		// B
			public static final byte CTAP2_ERR_KEY_STORE_FULL = 40;		// B
			public static final byte CTAP2_ERR_NO_OPERATION_PENDING = 42;		// B
			public static final byte CTAP2_ERR_UNSUPPORTED_OPTION = 43;		// B
			public static final byte CTAP2_ERR_INVALID_OPTION = 44;		// B
			public static final byte CTAP2_ERR_KEEPALIVE_CANCEL = 45;		// B
			public static final byte CTAP2_ERR_NO_CREDENTIALS = 46;		// B
			public static final byte CTAP2_ERR_USER_ACTION_TIMEOUT = 47;		// B
			public static final byte CTAP2_ERR_NOT_ALLOWED = 48;		// B
			public static final byte CTAP2_ERR_PIN_INVALID = 49;		// B
			public static final byte CTAP2_ERR_PIN_BLOCKED = 50;		// B
			public static final byte CTAP2_ERR_PIN_AUTH_INVALID = 51;		// B
			public static final byte CTAP2_ERR_PIN_AUTH_BLOCKED = 52;		// B
			public static final byte CTAP2_ERR_PIN_NOT_SET = 53;		// B
			public static final byte CTAP2_ERR_PIN_REQUIRED = 54;		// B
			public static final byte CTAP2_ERR_PIN_POLICY_VIOLATION = 55;		// B
			public static final byte CTAP2_ERR_PIN_TOKEN_EXPIRED = 56;		// B
			public static final byte CTAP2_ERR_REQUEST_TOO_LARGE = 57;		// B
			public static final byte CTAP2_ERR_ACTION_TIMEOUT = 58;		// B
			public static final byte CTAP2_ERR_UP_REQUIRED = 59;		// B
			public static final byte FIDO2_AUTHENTICATOR_MAKE_CREDENTIAL = 1;		// B
			public static final byte FIDO2_AUTHENTICATOR_GET_ASSERTION = 2;		// B
			public static final byte FIDO2_AUTHENTICATOR_GET_NEXT_ASSERTION = 8;		// B
			public static final byte FIDO2_AUTHENTICATOR_GET_INFO = 4;		// B
			public static final byte FIDO2_AUTHENTICATOR_CLIENT_PIN = 6;		// B
			public static final byte FIDO2_AUTHENTICATOR_RESET = 7;		// B
			public static final byte FIDO2_VENDOR_ATTEST_SIGN = 65;		// B
			public static final byte FIDO2_VENDOR_ATTEST_LOADCERT = 66;		// B
			public static final byte FIDO2_VENDOR_PERSO_COMPLETE = 67;		// B
			public static final byte FIDO2_VENDOR_ATTEST_GETPUB = 68;		// B
			public static final byte FIDO2_VENDOR_ATTEST_GETCERT = 74;		// B
			public static final byte FIDO2_DESELECT = 18;		// B
			public static final byte[] aaguid 0 = {-1,0,0,0,0,0,0,0,-1,0,0,0,0,0,0,0};		// [B
			private static final byte FIDO2_VENDOR_GET_COUNT = 69;		// B
			private static final byte ISO_INS_GET_DATA = -64;		// B
			private static final byte FIDO2_INS_NFCCTAP_MSG = 16;		// B
		}

		.publicMethodTable 7 {
			equals(Ljava/lang/Object;)Z;
			register()V;
			register([BSB)V;
			selectingApplet()Z;
			deselect()V;
			getShareableInterfaceObject(Ljavacard/framework/AID;B)Ljavacard/framework/Shareable;;
			select()Z;
			process(Ljavacard/framework/APDU;)V;
			handle(Ljavacard/framework/APDU;)V;
			persoComplete(Ljavacard/framework/APDU;)V;
			getAttestPublic(Ljavacard/framework/APDU;)V;
			getCount(Ljavacard/framework/APDU;)V;
			attestSignRaw(Ljavacard/framework/APDU;S)V;
			attestSetCert(Ljavacard/framework/APDU;S)V;
			authMakeCredential(Ljavacard/framework/APDU;S)V;
			authGetAssertion(Ljavacard/framework/APDU;S)V;
			clientPin(Ljavacard/framework/APDU;S)V;
			returnError(Ljavacard/framework/APDU;B)V;
			returnError(Ljavacard/framework/APDU;S)V;
			authGetInfo(Ljavacard/framework/APDU;)V;
			getData(Ljavacard/framework/APDU;)V;
			sendLongChaining(Ljavacard/framework/APDU;S)V;
			isChaining()Z;
		}

		.packageMethodTable 0 {
		}

		.implementedInterfaceInfoTable { 
			.interface 3.0 { 		// javacardx/apdu/ExtendedLength
			}

		}

		.method private <init>()V {
			.stack 5;
			.locals 2;

				L0:	aload_0;
					invokespecial 103;		// javacard/framework/Applet.<init>()V
				L1:	aload_0;
					sspush 1210;
					sconst_2;
					invokestatic 117;		// javacard/framework/JCSystem.makeTransientByteArray(SB)[B
					putfield_a 16;		// reference com/josh/vku2f/CTAP2.inBuf
				L2:	goto L4;
				L3:	astore_1;
					aload_0;
					sspush 1210;
					newarray 11;
					putfield_a 16;		// reference com/josh/vku2f/CTAP2.inBuf
				L4:	aload_0;
					sspush 512;
					sconst_2;
					invokestatic 117;		// javacard/framework/JCSystem.makeTransientByteArray(SB)[B
					putfield_a 17;		// reference com/josh/vku2f/CTAP2.scratch
				L5:	goto L7;
				L6:	astore_1;
					aload_0;
					sspush 512;
					newarray 11;
					putfield_a 17;		// reference com/josh/vku2f/CTAP2.scratch
				L7:	aload_0;
					bspush 8;
					sconst_2;
					invokestatic 109;		// javacard/framework/JCSystem.makeTransientShortArray(SB)[S
					putfield_a 18;		// reference com/josh/vku2f/CTAP2.vars
					aload_0;
					new 107;		// com/josh/vku2f/CBORDecoder
					dup;
					invokespecial 108;		// com/josh/vku2f/CBORDecoder.<init>()V
					putfield_a 19;		// reference com/josh/vku2f/CTAP2.cborDecoder
					aload_0;
					new 110;		// com/josh/vku2f/CBOREncoder
					dup;
					invokespecial 111;		// com/josh/vku2f/CBOREncoder.<init>()V
					putfield_a 20;		// reference com/josh/vku2f/CTAP2.cborEncoder
					aload_0;
					new 113;		// com/josh/vku2f/CredentialArray
					dup;
					sconst_5;
					invokespecial 114;		// com/josh/vku2f/CredentialArray.<init>(S)V
					putfield_a 21;		// reference com/josh/vku2f/CTAP2.discoverableCreds
					aload_0;
					sconst_4;
					sconst_0;
					invokestatic 116;		// javacard/security/MessageDigest.getInstance(BZ)Ljavacard/security/MessageDigest;
					putfield_a 22;		// reference com/josh/vku2f/CTAP2.sha
					aload_0;
					new 118;		// com/josh/vku2f/AttestationKeyPair
					dup;
					invokespecial 119;		// com/josh/vku2f/AttestationKeyPair.<init>()V
					putfield_a 23;		// reference com/josh/vku2f/CTAP2.attestation
					aload_0;
					sconst_1;
					sconst_1;
					invokestatic 109;		// javacard/framework/JCSystem.makeTransientShortArray(SB)[S
					putfield_a 24;		// reference com/josh/vku2f/CTAP2.nextAssertion
					sconst_0;
					putfield_b_this 25;		// boolean com/josh/vku2f/CTAP2.persoComplete
					aload_0;
					sconst_2;
					sconst_2;
					invokestatic 123;		// javacard/framework/JCSystem.makeTransientBooleanArray(SB)[Z
					putfield_a 26;		// reference com/josh/vku2f/CTAP2.isChaining
					aload_0;
					sconst_4;
					sconst_2;
					invokestatic 109;		// javacard/framework/JCSystem.makeTransientShortArray(SB)[S
					putfield_a 27;		// reference com/josh/vku2f/CTAP2.chainRam
					aload_0;
					sconst_4;
					sconst_2;
					invokestatic 109;		// javacard/framework/JCSystem.makeTransientShortArray(SB)[S
					putfield_a 28;		// reference com/josh/vku2f/CTAP2.outChainRam
					aload_0;
					sconst_2;
					sconst_2;
					invokestatic 123;		// javacard/framework/JCSystem.makeTransientBooleanArray(SB)[Z
					putfield_a 29;		// reference com/josh/vku2f/CTAP2.isOutChaining
					bspush 7;
					sconst_1;
					sspush 256;
					sconst_0;
					invokestatic 128;		// javacard/security/KeyBuilder.buildKey(BBSZ)Ljavacard/security/Key;
					checkcast 0 105;		// T_CLASSORINTERFACE javacard/security/ECPublicKey
					astore_1;
					bspush 8;
					sconst_1;
					sspush 256;
					sconst_0;
					invokestatic 128;		// javacard/security/KeyBuilder.buildKey(BBSZ)Ljavacard/security/Key;
					checkcast 0 129;		// T_CLASSORINTERFACE javacard/security/ECPrivateKey
					astore_2;
					aload_0;
					new 221;		// javacard/security/KeyPair
					dup;
					aload_1;
					aload_2;
					invokespecial 130;		// javacard/security/KeyPair.<init>(Ljavacard/security/PublicKey;Ljavacard/security/PrivateKey;)V
					putfield_a 30;		// reference com/josh/vku2f/CTAP2.ecDhKey
					aload_0;
					sconst_1;
					sconst_1;
					invokestatic 123;		// javacard/framework/JCSystem.makeTransientBooleanArray(SB)[Z
					putfield_a 31;		// reference com/josh/vku2f/CTAP2.ecDhSet
					return;
			.exceptionTable {
				// start_block end_block handler_block catch_type_index
				L1 L2 L3 106;
				L4 L5 L6 106;
			}
		}

		.method public handle(Ljavacard/framework/APDU;)V 8 {
			.stack 4;
			.locals 1;

			.descriptor	Ljavacard/framework/APDU;	2.10;

				L0:	aload_1;
					invokevirtual 133;		// getBuffer()[B
					astore_2;
					aconst_null;
					putfield_a_this 32;		// reference com/josh/vku2f/CTAP2.tempCred
					aconst_null;
					putfield_a_this 33;		// reference com/josh/vku2f/CTAP2.cred
					getfield_a_this 18;		// reference com/josh/vku2f/CTAP2.vars
					sconst_3;
					aload_0;
					aload_1;
					invokespecial 136;		// com/josh/vku2f/CTAP2.doApduIngestion(Ljavacard/framework/APDU;)S
					sastore;
					getfield_a_this 18;		// reference com/josh/vku2f/CTAP2.vars
					sconst_3;
					saload;
					ifne L2;
				L1:	sspush -28672;
					invokestatic 74;		// javacard/framework/ISOException.throwIt(S)V
					return;
				L2:	getfield_a_this 16;		// reference com/josh/vku2f/CTAP2.inBuf
					sconst_0;
					baload;
					slookupswitch L14 11 1 L3 2 L4 4 L5 7 L13 8 L6 65 L7 66 L8 67 L9 68 L10 69 L12 74 L11;
				L3:	aload_0;
					aload_1;
					getfield_a_this 18;		// reference com/josh/vku2f/CTAP2.vars
					sconst_3;
					saload;
					invokevirtual 137;		// authMakeCredential(Ljavacard/framework/APDU;S)V
					goto L15;
				L4:	aload_0;
					aload_1;
					getfield_a_this 18;		// reference com/josh/vku2f/CTAP2.vars
					sconst_3;
					saload;
					invokevirtual 138;		// authGetAssertion(Ljavacard/framework/APDU;S)V
					goto L15;
				L5:	aload_0;
					aload_1;
					invokevirtual 139;		// authGetInfo(Ljavacard/framework/APDU;)V
					goto L15;
				L6:	aload_0;
					aload_1;
					aload_2;
					invokespecial 140;		// com/josh/vku2f/CTAP2.authGetNextAssertion(Ljavacard/framework/APDU;[B)V
					goto L15;
				L7:	aload_0;
					aload_1;
					getfield_a_this 18;		// reference com/josh/vku2f/CTAP2.vars
					sconst_3;
					saload;
					invokevirtual 141;		// attestSignRaw(Ljavacard/framework/APDU;S)V
					goto L15;
				L8:	aload_0;
					aload_1;
					getfield_a_this 18;		// reference com/josh/vku2f/CTAP2.vars
					sconst_3;
					saload;
					invokevirtual 142;		// attestSetCert(Ljavacard/framework/APDU;S)V
					goto L15;
				L9:	aload_0;
					aload_1;
					invokevirtual 143;		// persoComplete(Ljavacard/framework/APDU;)V
					goto L15;
				L10:	aload_0;
					aload_1;
					invokevirtual 144;		// getAttestPublic(Ljavacard/framework/APDU;)V
					goto L15;
				L11:	aload_0;
					aload_1;
					invokespecial 145;		// com/josh/vku2f/CTAP2.getCert(Ljavacard/framework/APDU;)V
					goto L15;
				L12:	aload_0;
					aload_1;
					invokevirtual 146;		// getCount(Ljavacard/framework/APDU;)V
					goto L15;
				L13:	aload_0;
					aload_1;
					invokespecial 147;		// com/josh/vku2f/CTAP2.doReset(Ljavacard/framework/APDU;)V
					goto L15;
				L14:	aload_0;
					aload_1;
					sconst_1;
					invokevirtual 148;		// returnError(Ljavacard/framework/APDU;B)V
				L15:	return;
		}

		.method public persoComplete(Ljavacard/framework/APDU;)V 9 {
			.stack 3;
			.locals 0;

			.descriptor	Ljavacard/framework/APDU;	2.10;

				L0:	getfield_a_this 23;		// reference com/josh/vku2f/CTAP2.attestation
					invokevirtual 149;		// isCertSet()Z
					ifeq L3;
				L1:	getfield_b_this 25;		// boolean com/josh/vku2f/CTAP2.persoComplete
					ifne L3;
				L2:	sconst_1;
					putfield_b_this 25;		// boolean com/josh/vku2f/CTAP2.persoComplete
					aload_0;
					aload_1;
					sconst_0;
					invokevirtual 148;		// returnError(Ljavacard/framework/APDU;B)V
					goto L4;
				L3:	aload_0;
					aload_1;
					sconst_1;
					invokevirtual 148;		// returnError(Ljavacard/framework/APDU;B)V
				L4:	return;
		}

		.method public getAttestPublic(Ljavacard/framework/APDU;)V 10 {
			.stack 5;
			.locals 0;

			.descriptor	Ljavacard/framework/APDU;	2.10;

				L0:	getfield_b_this 25;		// boolean com/josh/vku2f/CTAP2.persoComplete
					ifeq L2;
				L1:	aload_0;
					aload_1;
					sconst_1;
					invokevirtual 148;		// returnError(Ljavacard/framework/APDU;B)V
					return;
				L2:	getfield_a_this 16;		// reference com/josh/vku2f/CTAP2.inBuf
					sconst_0;
					sconst_0;
					bastore;
					getfield_a_this 18;		// reference com/josh/vku2f/CTAP2.vars
					sconst_0;
					getfield_a_this 23;		// reference com/josh/vku2f/CTAP2.attestation
					getfield_a_this 16;		// reference com/josh/vku2f/CTAP2.inBuf
					sconst_1;
					invokevirtual 150;		// getPubkey([BS)S
					sconst_1;
					sadd;
					sastore;
					aload_1;
					invokevirtual 151;		// setOutgoing()S
					pop;
					aload_1;
					getfield_a_this 18;		// reference com/josh/vku2f/CTAP2.vars
					sconst_0;
					saload;
					invokevirtual 152;		// setOutgoingLength(S)V
					aload_1;
					getfield_a_this 16;		// reference com/josh/vku2f/CTAP2.inBuf
					sconst_0;
					getfield_a_this 18;		// reference com/josh/vku2f/CTAP2.vars
					sconst_0;
					saload;
					invokevirtual 153;		// sendBytesLong([BSS)V
					return;
		}

		.method public getCount(Ljavacard/framework/APDU;)V 11 {
			.stack 4;
			.locals 1;

			.descriptor	Ljavacard/framework/APDU;	2.10;

				L0:	getfield_a_this 21;		// reference com/josh/vku2f/CTAP2.discoverableCreds
					invokevirtual 154;		// getCount()S
					sstore_2;
					aload_1;
					invokevirtual 151;		// setOutgoing()S
					pop;
					aload_1;
					sconst_2;
					invokevirtual 152;		// setOutgoingLength(S)V
					getfield_a_this 16;		// reference com/josh/vku2f/CTAP2.inBuf
					sconst_0;
					sload_2;
					invokestatic 98;		// javacard/framework/Util.setShort([BSS)S
					pop;
					aload_1;
					getfield_a_this 16;		// reference com/josh/vku2f/CTAP2.inBuf
					sconst_0;
					sconst_2;
					invokevirtual 153;		// sendBytesLong([BSS)V
					return;
		}

		.method public attestSignRaw(Ljavacard/framework/APDU;S)V 12 {
			.stack 8;
			.locals 0;

			.descriptor	Ljavacard/framework/APDU;	2.10;

				L0:	getfield_b_this 25;		// boolean com/josh/vku2f/CTAP2.persoComplete
					ifeq L2;
				L1:	aload_0;
					aload_1;
					sconst_1;
					invokevirtual 148;		// returnError(Ljavacard/framework/APDU;B)V
					return;
				L2:	getfield_a_this 16;		// reference com/josh/vku2f/CTAP2.inBuf
					sconst_1;
					getfield_a_this 17;		// reference com/josh/vku2f/CTAP2.scratch
					sconst_0;
					sload_2;
					sconst_1;
					ssub;
					invokestatic 104;		// javacard/framework/Util.arrayCopy([BS[BSS)S
					pop;
					getfield_a_this 16;		// reference com/josh/vku2f/CTAP2.inBuf
					sconst_0;
					sconst_0;
					bastore;
					getfield_a_this 18;		// reference com/josh/vku2f/CTAP2.vars
					sconst_2;
					getfield_a_this 23;		// reference com/josh/vku2f/CTAP2.attestation
					getfield_a_this 17;		// reference com/josh/vku2f/CTAP2.scratch
					sconst_0;
					getfield_a_this 18;		// reference com/josh/vku2f/CTAP2.vars
					sconst_1;
					saload;
					getfield_a_this 16;		// reference com/josh/vku2f/CTAP2.inBuf
					sconst_1;
					invokevirtual 155;		// sign([BSS[BS)S
					sastore;
					aload_1;
					invokevirtual 151;		// setOutgoing()S
					pop;
					aload_1;
					getfield_a_this 18;		// reference com/josh/vku2f/CTAP2.vars
					sconst_2;
					saload;
					sconst_1;
					sadd;
					invokevirtual 152;		// setOutgoingLength(S)V
					aload_1;
					getfield_a_this 16;		// reference com/josh/vku2f/CTAP2.inBuf
					sconst_0;
					getfield_a_this 18;		// reference com/josh/vku2f/CTAP2.vars
					sconst_2;
					saload;
					sconst_1;
					sadd;
					invokevirtual 153;		// sendBytesLong([BSS)V
					return;
		}

		.method public attestSetCert(Ljavacard/framework/APDU;S)V 13 {
			.stack 6;
			.locals 2;

			.descriptor	Ljavacard/framework/APDU;	2.10;

				L0:	getfield_b_this 25;		// boolean com/josh/vku2f/CTAP2.persoComplete
					ifeq L2;
				L1:	aload_0;
					aload_1;
					sconst_1;
					invokevirtual 148;		// returnError(Ljavacard/framework/APDU;B)V
					return;
				L2:	getfield_a_this 23;		// reference com/josh/vku2f/CTAP2.attestation
					getfield_a_this 16;		// reference com/josh/vku2f/CTAP2.inBuf
					sconst_1;
					sload_2;
					sconst_1;
					ssub;
					invokevirtual 156;		// setCert([BSS)V
					sconst_4;
					sconst_0;
					invokestatic 116;		// javacard/security/MessageDigest.getInstance(BZ)Ljavacard/security/MessageDigest;
					astore_3;
					aload_3;
					getfield_a_this 23;		// reference com/josh/vku2f/CTAP2.attestation
					getfield_a 2;		// reference com/josh/vku2f/AttestationKeyPair.x509cert
					sconst_0;
					getfield_a_this 23;		// reference com/josh/vku2f/CTAP2.attestation
					getfield_s 3;		// short com/josh/vku2f/AttestationKeyPair.x509len
					getfield_a_this 16;		// reference com/josh/vku2f/CTAP2.inBuf
					sconst_3;
					invokevirtual 157;		// doFinal([BSS[BS)S
					sconst_3;
					sadd;
					sstore 4;
					getfield_a_this 16;		// reference com/josh/vku2f/CTAP2.inBuf
					sconst_0;
					sconst_0;
					bastore;
					getfield_a_this 16;		// reference com/josh/vku2f/CTAP2.inBuf
					sconst_1;
					getfield_a_this 23;		// reference com/josh/vku2f/CTAP2.attestation
					getfield_s 3;		// short com/josh/vku2f/AttestationKeyPair.x509len
					invokestatic 98;		// javacard/framework/Util.setShort([BSS)S
					pop;
					aload_1;
					invokevirtual 151;		// setOutgoing()S
					pop;
					aload_1;
					sload 4;
					invokevirtual 152;		// setOutgoingLength(S)V
					aload_1;
					getfield_a_this 16;		// reference com/josh/vku2f/CTAP2.inBuf
					sconst_0;
					sload 4;
					invokevirtual 153;		// sendBytesLong([BSS)V
					return;
		}

		.method public authMakeCredential(Ljavacard/framework/APDU;S)V 14 {
			.stack 10;
			.locals 1;

			.descriptor	Ljavacard/framework/APDU;	2.10;

				L0:	getfield_a_this 19;		// reference com/josh/vku2f/CTAP2.cborDecoder
					getfield_a_this 16;		// reference com/josh/vku2f/CTAP2.inBuf
					sconst_1;
					sload_2;
					invokevirtual 159;		// init([BSS)V
				L1:	aload_0;
					new 160;		// com/josh/vku2f/AuthenticatorMakeCredential
					dup;
					getfield_a_this 19;		// reference com/josh/vku2f/CTAP2.cborDecoder
					invokespecial 161;		// com/josh/vku2f/AuthenticatorMakeCredential.<init>(Lcom/josh/vku2f/CBORDecoder;)V
					putfield_a 33;		// reference com/josh/vku2f/CTAP2.cred
				L2:	goto L4;
				L3:	astore_3;
					aload_0;
					aload_1;
					aload_3;
					invokevirtual 162;		// getReason()S
					invokevirtual 163;		// returnError(Ljavacard/framework/APDU;S)V
					return;
				L4:	getfield_a_this 33;		// reference com/josh/vku2f/CTAP2.cred
					invokevirtual 164;		// getAlgorithm()B
					slookupswitch L8 3 33 L5 40 L6 44 L7;
				L5:	aload_0;
					new 165;		// com/josh/vku2f/StoredES256Credential
					dup;
					getfield_a_this 33;		// reference com/josh/vku2f/CTAP2.cred
					invokespecial 166;		// com/josh/vku2f/StoredES256Credential.<init>(Lcom/josh/vku2f/AuthenticatorMakeCredential;)V
					putfield_a 32;		// reference com/josh/vku2f/CTAP2.tempCred
					goto L9;
				L6:	aload_0;
					new 167;		// com/josh/vku2f/StoredRS256Credential
					dup;
					getfield_a_this 33;		// reference com/josh/vku2f/CTAP2.cred
					invokespecial 168;		// com/josh/vku2f/StoredRS256Credential.<init>(Lcom/josh/vku2f/AuthenticatorMakeCredential;)V
					putfield_a 32;		// reference com/josh/vku2f/CTAP2.tempCred
					goto L9;
				L7:	aload_0;
					new 169;		// com/josh/vku2f/StoredPS256Credential
					dup;
					getfield_a_this 33;		// reference com/josh/vku2f/CTAP2.cred
					invokespecial 170;		// com/josh/vku2f/StoredPS256Credential.<init>(Lcom/josh/vku2f/AuthenticatorMakeCredential;)V
					putfield_a 32;		// reference com/josh/vku2f/CTAP2.tempCred
					goto L9;
				L8:	aload_0;
					aload_1;
					bspush 38;
					invokevirtual 148;		// returnError(Ljavacard/framework/APDU;B)V
					return;
				L9:	getfield_a_this 33;		// reference com/josh/vku2f/CTAP2.cred
					invokevirtual 171;		// isResident()Z
					ifeq_w L14;
				L10:	getfield_a_this 33;		// reference com/josh/vku2f/CTAP2.cred
					invokevirtual 172;		// isExclude()Z
					ifeq L13;
				L11:	aload_0;
					getfield_a_this 33;		// reference com/josh/vku2f/CTAP2.cred
					getfield_a 13;		// reference com/josh/vku2f/AuthenticatorMakeCredential.exclude
					invokespecial 173;		// com/josh/vku2f/CTAP2.isPresent([Lcom/josh/vku2f/PublicKeyCredentialDescriptor;)Z
					ifeq L13;
				L12:	aload_0;
					aload_1;
					bspush 25;
					invokevirtual 148;		// returnError(Ljavacard/framework/APDU;B)V
					return;
				L13:	aload_0;
					aload_1;
					getfield_a_this 32;		// reference com/josh/vku2f/CTAP2.tempCred
					invokespecial 174;		// com/josh/vku2f/CTAP2.addResident(Ljavacard/framework/APDU;Lcom/josh/vku2f/StoredCredential;)V
					getfield_a_this 16;		// reference com/josh/vku2f/CTAP2.inBuf
					sconst_0;
					sconst_0;
					bastore;
					getfield_a_this 20;		// reference com/josh/vku2f/CTAP2.cborEncoder
					getfield_a_this 16;		// reference com/josh/vku2f/CTAP2.inBuf
					sconst_1;
					sspush 1199;
					invokevirtual 175;		// init([BSS)V
					getfield_a_this 18;		// reference com/josh/vku2f/CTAP2.vars
					sconst_0;
					getfield_a_this 20;		// reference com/josh/vku2f/CTAP2.cborEncoder
					sconst_3;
					invokevirtual 176;		// startMap(S)S
					sastore;
					getfield_a_this 20;		// reference com/josh/vku2f/CTAP2.cborEncoder
					sconst_1;
					invokevirtual 91;		// writeRawByte(B)S
					pop;
					getfield_a_this 20;		// reference com/josh/vku2f/CTAP2.cborEncoder
					getstatic_a 177;		// reference com/josh/vku2f/Utf8Strings.UTF8_PACKED
					sconst_0;
					bspush 6;
					invokevirtual 178;		// encodeTextString([BSS)S
					pop;
					getfield_a_this 20;		// reference com/josh/vku2f/CTAP2.cborEncoder
					sconst_2;
					invokevirtual 91;		// writeRawByte(B)S
					pop;
					getfield_a_this 18;		// reference com/josh/vku2f/CTAP2.vars
					sconst_0;
					getfield_a_this 20;		// reference com/josh/vku2f/CTAP2.cborEncoder
					bspush 37;
					getfield_a_this 32;		// reference com/josh/vku2f/CTAP2.tempCred
					invokevirtual 179;		// getAttestedLen()S
					sadd;
					invokevirtual 180;		// startByteString(S)S
					sastore;
					getfield_a_this 18;		// reference com/josh/vku2f/CTAP2.vars
					bspush 7;
					getfield_a_this 18;		// reference com/josh/vku2f/CTAP2.vars
					sconst_0;
					saload;
					sastore;
					getfield_a_this 32;		// reference com/josh/vku2f/CTAP2.tempCred
					getfield_a 34;		// reference com/josh/vku2f/StoredCredential.rp
					getfield_a_this 17;		// reference com/josh/vku2f/CTAP2.scratch
					sconst_0;
					invokevirtual 182;		// getRp([BS)V
					getfield_a_this 18;		// reference com/josh/vku2f/CTAP2.vars
					sconst_0;
					dup2;
					saload;
					getfield_a_this 22;		// reference com/josh/vku2f/CTAP2.sha
					getfield_a_this 17;		// reference com/josh/vku2f/CTAP2.scratch
					sconst_0;
					getfield_a_this 32;		// reference com/josh/vku2f/CTAP2.tempCred
					getfield_a 34;		// reference com/josh/vku2f/StoredCredential.rp
					invokevirtual 183;		// getRpLen()S
					getfield_a_this 16;		// reference com/josh/vku2f/CTAP2.inBuf
					getfield_a_this 18;		// reference com/josh/vku2f/CTAP2.vars
					sconst_0;
					saload;
					invokevirtual 157;		// doFinal([BSS[BS)S
					sadd;
					sastore;
					getfield_a_this 16;		// reference com/josh/vku2f/CTAP2.inBuf
					getfield_a_this 18;		// reference com/josh/vku2f/CTAP2.vars
					sconst_0;
					dup2;
					saload;
					dup_x 19;
					sconst_1;
					sadd;
					sastore;
					bspush 69;
					bastore;
					getfield_a_this 18;		// reference com/josh/vku2f/CTAP2.vars
					sconst_0;
					dup2;
					saload;
					getfield_a_this 32;		// reference com/josh/vku2f/CTAP2.tempCred
					getfield_a_this 16;		// reference com/josh/vku2f/CTAP2.inBuf
					getfield_a_this 18;		// reference com/josh/vku2f/CTAP2.vars
					sconst_0;
					saload;
					invokevirtual 184;		// readCounter([BS)S
					sadd;
					sastore;
					getfield_a_this 18;		// reference com/josh/vku2f/CTAP2.vars
					sconst_0;
					dup2;
					saload;
					getfield_a_this 32;		// reference com/josh/vku2f/CTAP2.tempCred
					getfield_a_this 16;		// reference com/josh/vku2f/CTAP2.inBuf
					getfield_a_this 18;		// reference com/josh/vku2f/CTAP2.vars
					sconst_0;
					saload;
					invokevirtual 185;		// getAttestedData([BS)S
					sadd;
					sastore;
					getfield_a_this 20;		// reference com/josh/vku2f/CTAP2.cborEncoder
					sconst_3;
					invokevirtual 91;		// writeRawByte(B)S
					pop;
					getfield_a_this 20;		// reference com/josh/vku2f/CTAP2.cborEncoder
					sconst_3;
					invokevirtual 176;		// startMap(S)S
					pop;
					getfield_a_this 20;		// reference com/josh/vku2f/CTAP2.cborEncoder
					getstatic_a 281;		// reference com/josh/vku2f/Utf8Strings.UTF8_ALG
					sconst_0;
					sconst_3;
					invokevirtual 178;		// encodeTextString([BSS)S
					pop;
					getfield_a_this 20;		// reference com/josh/vku2f/CTAP2.cborEncoder
					bspush 6;
					invokevirtual 186;		// encodeNegativeUInt8(B)S
					pop;
					getfield_a_this 20;		// reference com/josh/vku2f/CTAP2.cborEncoder
					getstatic_a 187;		// reference com/josh/vku2f/Utf8Strings.UTF8_SIG
					sconst_0;
					sconst_3;
					invokevirtual 178;		// encodeTextString([BSS)S
					pop;
					getfield_a_this 23;		// reference com/josh/vku2f/CTAP2.attestation
					getfield_a_this 16;		// reference com/josh/vku2f/CTAP2.inBuf
					getfield_a_this 18;		// reference com/josh/vku2f/CTAP2.vars
					bspush 7;
					saload;
					getfield_a_this 32;		// reference com/josh/vku2f/CTAP2.tempCred
					invokevirtual 179;		// getAttestedLen()S
					bspush 37;
					sadd;
					invokevirtual 188;		// update([BSS)V
					getfield_a_this 18;		// reference com/josh/vku2f/CTAP2.vars
					sconst_4;
					getfield_a_this 23;		// reference com/josh/vku2f/CTAP2.attestation
					getfield_a_this 33;		// reference com/josh/vku2f/CTAP2.cred
					getfield_a 9;		// reference com/josh/vku2f/AuthenticatorMakeCredential.dataHash
					sconst_0;
					getfield_a_this 33;		// reference com/josh/vku2f/CTAP2.cred
					getfield_a 9;		// reference com/josh/vku2f/AuthenticatorMakeCredential.dataHash
					arraylength;
					getfield_a_this 17;		// reference com/josh/vku2f/CTAP2.scratch
					sconst_0;
					invokevirtual 155;		// sign([BSS[BS)S
					sastore;
					getfield_a_this 20;		// reference com/josh/vku2f/CTAP2.cborEncoder
					getfield_a_this 17;		// reference com/josh/vku2f/CTAP2.scratch
					sconst_0;
					getfield_a_this 18;		// reference com/josh/vku2f/CTAP2.vars
					sconst_4;
					saload;
					invokevirtual 189;		// encodeByteString([BSS)S
					pop;
					getfield_a_this 20;		// reference com/josh/vku2f/CTAP2.cborEncoder
					getstatic_a 190;		// reference com/josh/vku2f/Utf8Strings.UTF8_X5C
					sconst_0;
					sconst_3;
					invokevirtual 178;		// encodeTextString([BSS)S
					pop;
					getfield_a_this 20;		// reference com/josh/vku2f/CTAP2.cborEncoder
					sconst_1;
					invokevirtual 191;		// startArray(S)S
					pop;
					getfield_a_this 20;		// reference com/josh/vku2f/CTAP2.cborEncoder
					getfield_a_this 23;		// reference com/josh/vku2f/CTAP2.attestation
					getfield_a 2;		// reference com/josh/vku2f/AttestationKeyPair.x509cert
					sconst_0;
					getfield_a_this 23;		// reference com/josh/vku2f/CTAP2.attestation
					getfield_s 3;		// short com/josh/vku2f/AttestationKeyPair.x509len
					invokevirtual 189;		// encodeByteString([BSS)S
					pop;
					aload_0;
					aload_1;
					getfield_a_this 20;		// reference com/josh/vku2f/CTAP2.cborEncoder
					invokevirtual 96;		// getCurrentOffset()S
					invokevirtual 192;		// sendLongChaining(Ljavacard/framework/APDU;S)V
					goto L15;
				L14:	aload_0;
					aload_1;
					bspush 43;
					invokevirtual 148;		// returnError(Ljavacard/framework/APDU;B)V
				L15:	return;
			.exceptionTable {
				// start_block end_block handler_block catch_type_index
				L1 L2 L3 158;
			}
		}

		.method public authGetAssertion(Ljavacard/framework/APDU;S)V 15 {
			.stack 6;
			.locals 1;

			.descriptor	Ljavacard/framework/APDU;	2.10;

				L0:	getfield_a_this 24;		// reference com/josh/vku2f/CTAP2.nextAssertion
					sconst_0;
					sconst_0;
					sastore;
					getfield_a_this 19;		// reference com/josh/vku2f/CTAP2.cborDecoder
					getfield_a_this 16;		// reference com/josh/vku2f/CTAP2.inBuf
					sconst_1;
					sload_2;
					invokevirtual 159;		// init([BSS)V
				L1:	aload_0;
					new 193;		// com/josh/vku2f/AuthenticatorGetAssertion
					dup;
					getfield_a_this 19;		// reference com/josh/vku2f/CTAP2.cborDecoder
					invokespecial 194;		// com/josh/vku2f/AuthenticatorGetAssertion.<init>(Lcom/josh/vku2f/CBORDecoder;)V
					putfield_a 35;		// reference com/josh/vku2f/CTAP2.assertion
				L2:	goto L4;
				L3:	astore_3;
					aload_0;
					aload_1;
					aload_3;
					invokevirtual 162;		// getReason()S
					invokevirtual 163;		// returnError(Ljavacard/framework/APDU;S)V
					return;
				L4:	aload_0;
					aload_0;
					aload_1;
					getfield_a_this 35;		// reference com/josh/vku2f/CTAP2.assertion
					invokespecial 196;		// com/josh/vku2f/CTAP2.findCredentials(Ljavacard/framework/APDU;Lcom/josh/vku2f/AuthenticatorGetAssertion;)[Lcom/josh/vku2f/StoredCredential;
					putfield_a 36;		// reference com/josh/vku2f/CTAP2.assertionCreds
					getfield_a_this 36;		// reference com/josh/vku2f/CTAP2.assertionCreds
					arraylength;
					ifeq L6;
				L5:	getfield_a_this 36;		// reference com/josh/vku2f/CTAP2.assertionCreds
					sconst_0;
					aaload;
					ifnonnull L7;
				L6:	aload_0;
					aload_1;
					bspush 46;
					invokevirtual 148;		// returnError(Ljavacard/framework/APDU;B)V
					return;
				L7:	getfield_a_this 22;		// reference com/josh/vku2f/CTAP2.sha
					getfield_a_this 35;		// reference com/josh/vku2f/CTAP2.assertion
					getfield_a 5;		// reference com/josh/vku2f/AuthenticatorGetAssertion.rpId
					sconst_0;
					getfield_a_this 35;		// reference com/josh/vku2f/CTAP2.assertion
					getfield_a 5;		// reference com/josh/vku2f/AuthenticatorGetAssertion.rpId
					arraylength;
					getfield_a_this 17;		// reference com/josh/vku2f/CTAP2.scratch
					sconst_0;
					invokevirtual 157;		// doFinal([BSS[BS)S
					pop;
					getfield_a_this 35;		// reference com/josh/vku2f/CTAP2.assertion
					getfield_a 4;		// reference com/josh/vku2f/AuthenticatorGetAssertion.options
					sconst_1;
					baload;
					ifeq L9;
				L8:	getfield_a_this 17;		// reference com/josh/vku2f/CTAP2.scratch
					bspush 32;
					sconst_5;
					bastore;
					goto L10;
				L9:	getfield_a_this 17;		// reference com/josh/vku2f/CTAP2.scratch
					bspush 32;
					sconst_1;
					bastore;
				L10:	getfield_a_this 36;		// reference com/josh/vku2f/CTAP2.assertionCreds
					sconst_0;
					aaload;
					getfield_a_this 17;		// reference com/josh/vku2f/CTAP2.scratch
					bspush 33;
					invokevirtual 184;		// readCounter([BS)S
					pop;
					getfield_a_this 35;		// reference com/josh/vku2f/CTAP2.assertion
					getfield_a_this 17;		// reference com/josh/vku2f/CTAP2.scratch
					bspush 37;
					invokevirtual 198;		// getHash([BS)S
					pop;
					getfield_a_this 16;		// reference com/josh/vku2f/CTAP2.inBuf
					sconst_0;
					sconst_0;
					bastore;
					getfield_a_this 20;		// reference com/josh/vku2f/CTAP2.cborEncoder
					getfield_a_this 16;		// reference com/josh/vku2f/CTAP2.inBuf
					sconst_1;
					sspush 1199;
					invokevirtual 175;		// init([BSS)V
					getfield_a_this 36;		// reference com/josh/vku2f/CTAP2.assertionCreds
					arraylength;
					sconst_1;
					if_scmple L12;
				L11:	aload_0;
					getfield_a_this 20;		// reference com/josh/vku2f/CTAP2.cborEncoder
					sconst_5;
					invokespecial 199;		// com/josh/vku2f/CTAP2.doAssertionCommon(Lcom/josh/vku2f/CBOREncoder;S)V
					goto L13;
				L12:	aload_0;
					getfield_a_this 20;		// reference com/josh/vku2f/CTAP2.cborEncoder
					sconst_4;
					invokespecial 199;		// com/josh/vku2f/CTAP2.doAssertionCommon(Lcom/josh/vku2f/CBOREncoder;S)V
				L13:	getfield_a_this 24;		// reference com/josh/vku2f/CTAP2.nextAssertion
					sconst_0;
					sconst_1;
					sastore;
					aload_0;
					aload_1;
					getfield_a_this 20;		// reference com/josh/vku2f/CTAP2.cborEncoder
					invokevirtual 96;		// getCurrentOffset()S
					invokevirtual 192;		// sendLongChaining(Ljavacard/framework/APDU;S)V
					return;
			.exceptionTable {
				// start_block end_block handler_block catch_type_index
				L1 L2 L3 158;
			}
		}

		.method private authGetNextAssertion(Ljavacard/framework/APDU;[B)V {
			.stack 6;
			.locals 0;

			.descriptor	Ljavacard/framework/APDU;	2.10;

				L0:	getfield_a_this 24;		// reference com/josh/vku2f/CTAP2.nextAssertion
					sconst_0;
					saload;
					ifeq_w L6;
				L1:	getfield_a_this 24;		// reference com/josh/vku2f/CTAP2.nextAssertion
					sconst_0;
					saload;
					getfield_a_this 36;		// reference com/josh/vku2f/CTAP2.assertionCreds
					arraylength;
					if_scmpge L6;
				L2:	getfield_a_this 22;		// reference com/josh/vku2f/CTAP2.sha
					getfield_a_this 35;		// reference com/josh/vku2f/CTAP2.assertion
					getfield_a 5;		// reference com/josh/vku2f/AuthenticatorGetAssertion.rpId
					sconst_0;
					getfield_a_this 35;		// reference com/josh/vku2f/CTAP2.assertion
					getfield_a 5;		// reference com/josh/vku2f/AuthenticatorGetAssertion.rpId
					arraylength;
					getfield_a_this 17;		// reference com/josh/vku2f/CTAP2.scratch
					sconst_0;
					invokevirtual 157;		// doFinal([BSS[BS)S
					pop;
					getfield_a_this 35;		// reference com/josh/vku2f/CTAP2.assertion
					getfield_a 4;		// reference com/josh/vku2f/AuthenticatorGetAssertion.options
					sconst_1;
					baload;
					ifeq L4;
				L3:	getfield_a_this 17;		// reference com/josh/vku2f/CTAP2.scratch
					bspush 32;
					sconst_5;
					bastore;
					goto L5;
				L4:	getfield_a_this 17;		// reference com/josh/vku2f/CTAP2.scratch
					bspush 32;
					sconst_1;
					bastore;
				L5:	getfield_a_this 36;		// reference com/josh/vku2f/CTAP2.assertionCreds
					getfield_a_this 24;		// reference com/josh/vku2f/CTAP2.nextAssertion
					sconst_0;
					saload;
					aaload;
					getfield_a_this 17;		// reference com/josh/vku2f/CTAP2.scratch
					bspush 33;
					invokevirtual 184;		// readCounter([BS)S
					pop;
					getfield_a_this 35;		// reference com/josh/vku2f/CTAP2.assertion
					getfield_a_this 17;		// reference com/josh/vku2f/CTAP2.scratch
					bspush 37;
					invokevirtual 198;		// getHash([BS)S
					pop;
					getfield_a_this 16;		// reference com/josh/vku2f/CTAP2.inBuf
					sconst_0;
					sconst_0;
					bastore;
					getfield_a_this 20;		// reference com/josh/vku2f/CTAP2.cborEncoder
					getfield_a_this 16;		// reference com/josh/vku2f/CTAP2.inBuf
					sconst_1;
					sspush 1199;
					invokevirtual 175;		// init([BSS)V
					aload_0;
					getfield_a_this 20;		// reference com/josh/vku2f/CTAP2.cborEncoder
					sconst_4;
					invokespecial 199;		// com/josh/vku2f/CTAP2.doAssertionCommon(Lcom/josh/vku2f/CBOREncoder;S)V
					getfield_a_this 24;		// reference com/josh/vku2f/CTAP2.nextAssertion
					sconst_0;
					dup2;
					saload;
					sconst_1;
					sadd;
					sastore;
					aload_0;
					aload_1;
					getfield_a_this 20;		// reference com/josh/vku2f/CTAP2.cborEncoder
					invokevirtual 96;		// getCurrentOffset()S
					invokevirtual 192;		// sendLongChaining(Ljavacard/framework/APDU;S)V
				L6:	return;
		}

		.method public clientPin(Ljavacard/framework/APDU;S)V 16 {
			.stack 4;
			.locals 1;

			.descriptor	Ljavacard/framework/APDU;	2.10;

				L0:	getfield_a_this 19;		// reference com/josh/vku2f/CTAP2.cborDecoder
					getfield_a_this 16;		// reference com/josh/vku2f/CTAP2.inBuf
					sconst_1;
					sload_2;
					invokevirtual 159;		// init([BSS)V
					getfield_a_this 19;		// reference com/josh/vku2f/CTAP2.cborDecoder
					sconst_5;
					invokevirtual 115;		// readMajorType(B)S
					pop;
					getfield_a_this 19;		// reference com/josh/vku2f/CTAP2.cborDecoder
					invokevirtual 120;		// readInt8()B
					sconst_1;
					if_scmpeq L3;
				L1:	bspush 18;
					invokestatic 131;		// javacard/framework/UserException.throwIt(S)V
				L2:	return;
				L3:	getfield_a_this 19;		// reference com/josh/vku2f/CTAP2.cborDecoder
					invokevirtual 120;		// readInt8()B
					sconst_1;
					if_scmpeq L6;
				L4:	bspush 18;
					invokestatic 131;		// javacard/framework/UserException.throwIt(S)V
				L5:	return;
				L6:	getfield_a_this 19;		// reference com/josh/vku2f/CTAP2.cborDecoder
					invokevirtual 120;		// readInt8()B
					sconst_2;
					if_scmpeq L9;
				L7:	bspush 18;
					invokestatic 131;		// javacard/framework/UserException.throwIt(S)V
				L8:	return;
				L9:	getfield_a_this 19;		// reference com/josh/vku2f/CTAP2.cborDecoder
					invokevirtual 120;		// readInt8()B
					slookupswitch L11 1 2 L10;
				L10:	aload_0;
					aload_1;
					invokespecial 200;		// com/josh/vku2f/CTAP2.generateDH(Ljavacard/framework/APDU;)V
					goto L13;
				L11:	bspush 43;
					invokestatic 131;		// javacard/framework/UserException.throwIt(S)V
				L12:	return;
				L13:	goto L15;
				L14:	astore_3;
					aload_0;
					aload_1;
					aload_3;
					invokevirtual 162;		// getReason()S
					invokevirtual 163;		// returnError(Ljavacard/framework/APDU;S)V
				L15:	return;
			.exceptionTable {
				// start_block end_block handler_block catch_type_index
				L0 L2 L14 158;
				L3 L5 L14 158;
				L6 L8 L14 158;
				L9 L12 L14 158;
			}
		}

		.method private addResident(Ljavacard/framework/APDU;Lcom/josh/vku2f/StoredCredential;)V {
			.stack 3;
			.locals 1;

			.descriptor	Ljavacard/framework/APDU;	2.10;

				L0:	getfield_a_this 21;		// reference com/josh/vku2f/CTAP2.discoverableCreds
					aload_2;
					invokevirtual 201;		// addCredential(Lcom/josh/vku2f/StoredCredential;)V
				L1:	goto L3;
				L2:	astore_3;
					aload_0;
					aload_1;
					aload_3;
					invokevirtual 162;		// getReason()S
					invokevirtual 163;		// returnError(Ljavacard/framework/APDU;S)V
				L3:	return;
			.exceptionTable {
				// start_block end_block handler_block catch_type_index
				L0 L1 L2 158;
			}
		}

		.method private generateDH(Ljavacard/framework/APDU;)V {
			.stack 4;
			.locals 2;

			.descriptor	Ljavacard/framework/APDU;	2.10;

				L0:	bspush 65;
					sconst_1;
					invokestatic 117;		// javacard/framework/JCSystem.makeTransientByteArray(SB)[B
					astore_2;
				L1:	goto L3;
				L2:	astore_3;
					bspush 65;
					newarray 11;
					astore_2;
				L3:	getfield_a_this 31;		// reference com/josh/vku2f/CTAP2.ecDhSet
					sconst_0;
					baload;
					ifne L5;
				L4:	getfield_a_this 30;		// reference com/josh/vku2f/CTAP2.ecDhKey
					invokevirtual 112;		// getPublic()Ljavacard/security/PublicKey;
					checkcast 0 122;		// T_CLASSORINTERFACE javacard/security/ECKey
					invokestatic 125;		// com/josh/vku2f/KeyParams.sec256r1params(Ljavacard/security/ECKey;)V
					getfield_a_this 30;		// reference com/josh/vku2f/CTAP2.ecDhKey
					invokevirtual 127;		// genKeyPair()V
				L5:	getfield_a_this 30;		// reference com/josh/vku2f/CTAP2.ecDhKey
					invokevirtual 112;		// getPublic()Ljavacard/security/PublicKey;
					checkcast 0 105;		// T_CLASSORINTERFACE javacard/security/ECPublicKey
					aload_2;
					sconst_0;
					invokeinterface 3 105 19;		// javacard/security/ECPublicKey
					pop;
					getfield_a_this 16;		// reference com/josh/vku2f/CTAP2.inBuf
					sconst_0;
					sconst_0;
					bastore;
					getfield_a_this 20;		// reference com/josh/vku2f/CTAP2.cborEncoder
					getfield_a_this 16;		// reference com/josh/vku2f/CTAP2.inBuf
					sconst_1;
					sspush 1199;
					invokevirtual 175;		// init([BSS)V
					getfield_a_this 20;		// reference com/josh/vku2f/CTAP2.cborEncoder
					sconst_1;
					invokevirtual 176;		// startMap(S)S
					pop;
					getfield_a_this 20;		// reference com/josh/vku2f/CTAP2.cborEncoder
					sconst_1;
					invokevirtual 202;		// encodeUInt8(B)S
					pop;
					getfield_a_this 20;		// reference com/josh/vku2f/CTAP2.cborEncoder
					sconst_5;
					invokevirtual 176;		// startMap(S)S
					pop;
					getfield_a_this 20;		// reference com/josh/vku2f/CTAP2.cborEncoder
					sconst_1;
					invokevirtual 202;		// encodeUInt8(B)S
					pop;
					getfield_a_this 20;		// reference com/josh/vku2f/CTAP2.cborEncoder
					sconst_2;
					invokevirtual 202;		// encodeUInt8(B)S
					pop;
					getfield_a_this 20;		// reference com/josh/vku2f/CTAP2.cborEncoder
					sconst_3;
					invokevirtual 202;		// encodeUInt8(B)S
					pop;
					getfield_a_this 20;		// reference com/josh/vku2f/CTAP2.cborEncoder
					bspush 6;
					invokevirtual 186;		// encodeNegativeUInt8(B)S
					pop;
					getfield_a_this 20;		// reference com/josh/vku2f/CTAP2.cborEncoder
					sconst_0;
					invokevirtual 186;		// encodeNegativeUInt8(B)S
					pop;
					getfield_a_this 20;		// reference com/josh/vku2f/CTAP2.cborEncoder
					sconst_1;
					invokevirtual 202;		// encodeUInt8(B)S
					pop;
					getfield_a_this 20;		// reference com/josh/vku2f/CTAP2.cborEncoder
					sconst_1;
					invokevirtual 186;		// encodeNegativeUInt8(B)S
					pop;
					getfield_a_this 20;		// reference com/josh/vku2f/CTAP2.cborEncoder
					aload_2;
					sconst_1;
					bspush 32;
					invokevirtual 189;		// encodeByteString([BSS)S
					pop;
					getfield_a_this 20;		// reference com/josh/vku2f/CTAP2.cborEncoder
					sconst_2;
					invokevirtual 186;		// encodeNegativeUInt8(B)S
					pop;
					getfield_a_this 20;		// reference com/josh/vku2f/CTAP2.cborEncoder
					aload_2;
					bspush 33;
					bspush 32;
					invokevirtual 189;		// encodeByteString([BSS)S
					pop;
					aload_0;
					aload_1;
					getfield_a_this 20;		// reference com/josh/vku2f/CTAP2.cborEncoder
					invokevirtual 96;		// getCurrentOffset()S
					invokevirtual 192;		// sendLongChaining(Ljavacard/framework/APDU;S)V
					return;
			.exceptionTable {
				// start_block end_block handler_block catch_type_index
				L0 L1 L2 106;
			}
		}

		.method private findCredentials(Ljavacard/framework/APDU;Lcom/josh/vku2f/AuthenticatorGetAssertion;)[Lcom/josh/vku2f/StoredCredential; {
			.stack 6;
			.locals 3;

			.descriptor	Ljavacard/framework/APDU;	2.10;

				L0:	aload_2;
					invokevirtual 203;		// hasAllow()Z
					ifeq_w L13;
				L1:	aload_2;
					getfield_a 7;		// reference com/josh/vku2f/AuthenticatorGetAssertion.allow
					arraylength;
					anewarray 204;		// com/josh/vku2f/StoredCredential
					astore_3;
					getfield_a_this 18;		// reference com/josh/vku2f/CTAP2.vars
					bspush 6;
					sconst_0;
					sastore;
					getfield_a_this 18;		// reference com/josh/vku2f/CTAP2.vars
					bspush 7;
					getfield_a_this 21;		// reference com/josh/vku2f/CTAP2.discoverableCreds
					invokevirtual 205;		// getLength()S
					sconst_1;
					ssub;
					sastore;
				L2:	getfield_a_this 18;		// reference com/josh/vku2f/CTAP2.vars
					bspush 7;
					saload;
					iflt_w L19;
				L3:	getfield_a_this 21;		// reference com/josh/vku2f/CTAP2.discoverableCreds
					getfield_a_this 18;		// reference com/josh/vku2f/CTAP2.vars
					bspush 7;
					saload;
					invokevirtual 206;		// getCred(S)Lcom/josh/vku2f/StoredCredential;
					astore 4;
					aload 4;
					ifnull L12;
				L4:	aload 4;
					getfield_a 34;		// reference com/josh/vku2f/StoredCredential.rp
					aload_2;
					getfield_a 5;		// reference com/josh/vku2f/AuthenticatorGetAssertion.rpId
					sconst_0;
					aload_2;
					getfield_a 5;		// reference com/josh/vku2f/AuthenticatorGetAssertion.rpId
					arraylength;
					invokevirtual 207;		// checkId([BSS)Z
					ifeq L12;
				L5:	getfield_a_this 18;		// reference com/josh/vku2f/CTAP2.vars
					sconst_5;
					sconst_0;
					sastore;
				L6:	getfield_a_this 18;		// reference com/josh/vku2f/CTAP2.vars
					sconst_5;
					saload;
					aload_2;
					getfield_a 7;		// reference com/josh/vku2f/AuthenticatorGetAssertion.allow
					arraylength;
					if_scmpge L12;
				L7:	aload_2;
					getfield_a 7;		// reference com/josh/vku2f/AuthenticatorGetAssertion.allow
					getfield_a_this 18;		// reference com/josh/vku2f/CTAP2.vars
					sconst_5;
					saload;
					aaload;
					getfield_a 37;		// reference com/josh/vku2f/PublicKeyCredentialDescriptor.id
					arraylength;
					aload 4;
					getfield_a 38;		// reference com/josh/vku2f/StoredCredential.id
					arraylength;
					if_scmpeq L9;
				L8:	goto L11;
				L9:	aload_2;
					getfield_a 7;		// reference com/josh/vku2f/AuthenticatorGetAssertion.allow
					getfield_a_this 18;		// reference com/josh/vku2f/CTAP2.vars
					sconst_5;
					saload;
					aaload;
					getfield_a 37;		// reference com/josh/vku2f/PublicKeyCredentialDescriptor.id
					sconst_0;
					aload 4;
					getfield_a 38;		// reference com/josh/vku2f/StoredCredential.id
					sconst_0;
					aload 4;
					getfield_a 38;		// reference com/josh/vku2f/StoredCredential.id
					arraylength;
					invokestatic 134;		// javacard/framework/Util.arrayCompare([BS[BSS)B
					ifne L11;
				L10:	aload_3;
					getfield_a_this 18;		// reference com/josh/vku2f/CTAP2.vars
					bspush 6;
					dup2;
					saload;
					dup_x 19;
					sconst_1;
					sadd;
					sastore;
					aload 4;
					aastore;
				L11:	getfield_a_this 18;		// reference com/josh/vku2f/CTAP2.vars
					sconst_5;
					dup2;
					saload;
					sconst_1;
					sadd;
					sastore;
					goto L6;
				L12:	getfield_a_this 18;		// reference com/josh/vku2f/CTAP2.vars
					bspush 7;
					dup2;
					saload;
					sconst_1;
					ssub;
					sastore;
					goto_w L2;
				L13:	getfield_a_this 21;		// reference com/josh/vku2f/CTAP2.discoverableCreds
					invokevirtual 205;		// getLength()S
					anewarray 204;		// com/josh/vku2f/StoredCredential
					astore_3;
					getfield_a_this 18;		// reference com/josh/vku2f/CTAP2.vars
					bspush 6;
					sconst_0;
					sastore;
					getfield_a_this 18;		// reference com/josh/vku2f/CTAP2.vars
					bspush 7;
					getfield_a_this 21;		// reference com/josh/vku2f/CTAP2.discoverableCreds
					invokevirtual 205;		// getLength()S
					sconst_1;
					ssub;
					sastore;
				L14:	getfield_a_this 18;		// reference com/josh/vku2f/CTAP2.vars
					bspush 7;
					saload;
					iflt L19;
				L15:	getfield_a_this 21;		// reference com/josh/vku2f/CTAP2.discoverableCreds
					getfield_a_this 18;		// reference com/josh/vku2f/CTAP2.vars
					bspush 7;
					saload;
					invokevirtual 206;		// getCred(S)Lcom/josh/vku2f/StoredCredential;
					astore 4;
					aload 4;
					ifnull L18;
				L16:	aload 4;
					getfield_a 34;		// reference com/josh/vku2f/StoredCredential.rp
					aload_2;
					getfield_a 5;		// reference com/josh/vku2f/AuthenticatorGetAssertion.rpId
					sconst_0;
					aload_2;
					getfield_a 5;		// reference com/josh/vku2f/AuthenticatorGetAssertion.rpId
					arraylength;
					invokevirtual 207;		// checkId([BSS)Z
					ifeq L18;
				L17:	aload_3;
					getfield_a_this 18;		// reference com/josh/vku2f/CTAP2.vars
					bspush 6;
					dup2;
					saload;
					dup_x 19;
					sconst_1;
					sadd;
					sastore;
					aload 4;
					aastore;
				L18:	getfield_a_this 18;		// reference com/josh/vku2f/CTAP2.vars
					bspush 7;
					dup2;
					saload;
					sconst_1;
					ssub;
					sastore;
					goto L14;
				L19:	getfield_a_this 18;		// reference com/josh/vku2f/CTAP2.vars
					bspush 6;
					saload;
					anewarray 204;		// com/josh/vku2f/StoredCredential
					astore 5;
					getfield_a_this 18;		// reference com/josh/vku2f/CTAP2.vars
					bspush 7;
					sconst_0;
					sastore;
				L20:	getfield_a_this 18;		// reference com/josh/vku2f/CTAP2.vars
					bspush 7;
					saload;
					getfield_a_this 18;		// reference com/josh/vku2f/CTAP2.vars
					bspush 6;
					saload;
					if_scmpge L22;
				L21:	aload 5;
					getfield_a_this 18;		// reference com/josh/vku2f/CTAP2.vars
					bspush 7;
					saload;
					aload_3;
					getfield_a_this 18;		// reference com/josh/vku2f/CTAP2.vars
					bspush 7;
					saload;
					aaload;
					aastore;
					getfield_a_this 18;		// reference com/josh/vku2f/CTAP2.vars
					bspush 7;
					dup2;
					saload;
					sconst_1;
					sadd;
					sastore;
					goto L20;
				L22:	invokestatic 210;		// javacard/framework/JCSystem.requestObjectDeletion()V
					aload 5;
					areturn;
		}

		.method private isPresent([Lcom/josh/vku2f/PublicKeyCredentialDescriptor;)Z {
			.stack 6;
			.locals 1;

				L0:	getfield_a_this 18;		// reference com/josh/vku2f/CTAP2.vars
					bspush 7;
					sconst_0;
					sastore;
				L1:	getfield_a_this 18;		// reference com/josh/vku2f/CTAP2.vars
					bspush 7;
					saload;
					getfield_a_this 21;		// reference com/josh/vku2f/CTAP2.discoverableCreds
					invokevirtual 205;		// getLength()S
					if_scmpge L10;
				L2:	getfield_a_this 21;		// reference com/josh/vku2f/CTAP2.discoverableCreds
					getfield_a_this 18;		// reference com/josh/vku2f/CTAP2.vars
					bspush 7;
					saload;
					invokevirtual 206;		// getCred(S)Lcom/josh/vku2f/StoredCredential;
					astore_2;
					aload_2;
					ifnonnull L4;
				L3:	goto L9;
				L4:	getfield_a_this 18;		// reference com/josh/vku2f/CTAP2.vars
					bspush 6;
					sconst_0;
					sastore;
				L5:	getfield_a_this 18;		// reference com/josh/vku2f/CTAP2.vars
					bspush 6;
					saload;
					aload_1;
					arraylength;
					if_scmpge L9;
				L6:	aload_2;
					aload_1;
					getfield_a_this 18;		// reference com/josh/vku2f/CTAP2.vars
					bspush 6;
					saload;
					aaload;
					getfield_a 37;		// reference com/josh/vku2f/PublicKeyCredentialDescriptor.id
					sconst_0;
					aload_1;
					getfield_a_this 18;		// reference com/josh/vku2f/CTAP2.vars
					bspush 6;
					saload;
					aaload;
					getfield_a 37;		// reference com/josh/vku2f/PublicKeyCredentialDescriptor.id
					arraylength;
					invokevirtual 211;		// checkId([BSS)Z
					ifeq L8;
				L7:	sconst_1;
					sreturn;
				L8:	getfield_a_this 18;		// reference com/josh/vku2f/CTAP2.vars
					bspush 6;
					dup2;
					saload;
					sconst_1;
					sadd;
					sastore;
					goto L5;
				L9:	getfield_a_this 18;		// reference com/josh/vku2f/CTAP2.vars
					bspush 7;
					dup2;
					saload;
					sconst_1;
					sadd;
					sastore;
					goto L1;
				L10:	sconst_0;
					sreturn;
		}

		.method private doReset(Ljavacard/framework/APDU;)V {
			.stack 4;
			.locals 0;

			.descriptor	Ljavacard/framework/APDU;	2.10;

				L0:	aload_0;
					new 113;		// com/josh/vku2f/CredentialArray
					dup;
					sconst_5;
					invokespecial 114;		// com/josh/vku2f/CredentialArray.<init>(S)V
					putfield_a 21;		// reference com/josh/vku2f/CTAP2.discoverableCreds
					invokestatic 210;		// javacard/framework/JCSystem.requestObjectDeletion()V
					aload_0;
					aload_1;
					sconst_0;
					invokevirtual 148;		// returnError(Ljavacard/framework/APDU;B)V
					return;
		}

		.method public returnError(Ljavacard/framework/APDU;B)V 17 {
			.stack 3;
			.locals 1;

			.descriptor	Ljavacard/framework/APDU;	2.10;

				L0:	aload_1;
					invokevirtual 133;		// getBuffer()[B
					astore_3;
					aload_3;
					sconst_0;
					sload_2;
					bastore;
					aload_1;
					sconst_0;
					sconst_1;
					invokevirtual 212;		// setOutgoingAndSend(SS)V
					return;
		}

		.method public returnError(Ljavacard/framework/APDU;S)V 18 {
			.stack 3;
			.locals 1;

			.descriptor	Ljavacard/framework/APDU;	2.10;

				L0:	aload_1;
					invokevirtual 133;		// getBuffer()[B
					astore_3;
					aload_3;
					sconst_0;
					sload_2;
					invokestatic 98;		// javacard/framework/Util.setShort([BSS)S
					pop;
					aload_1;
					sconst_1;
					sconst_1;
					invokevirtual 212;		// setOutgoingAndSend(SS)V
					return;
		}

		.method public authGetInfo(Ljavacard/framework/APDU;)V 19 {
			.stack 5;
			.locals 0;

			.descriptor	Ljavacard/framework/APDU;	2.10;

				L0:	getfield_a_this 39;		// reference com/josh/vku2f/CTAP2.info
					ifnonnull_w L2;
				L1:	getfield_a_this 16;		// reference com/josh/vku2f/CTAP2.inBuf
					sconst_0;
					sconst_0;
					bastore;
					getfield_a_this 20;		// reference com/josh/vku2f/CTAP2.cborEncoder
					getfield_a_this 16;		// reference com/josh/vku2f/CTAP2.inBuf
					sconst_1;
					sspush 1199;
					invokevirtual 175;		// init([BSS)V
					getfield_a_this 20;		// reference com/josh/vku2f/CTAP2.cborEncoder
					sconst_4;
					invokevirtual 176;		// startMap(S)S
					pop;
					getfield_a_this 20;		// reference com/josh/vku2f/CTAP2.cborEncoder
					sconst_1;
					invokevirtual 202;		// encodeUInt8(B)S
					pop;
					getfield_a_this 20;		// reference com/josh/vku2f/CTAP2.cborEncoder
					sconst_1;
					invokevirtual 191;		// startArray(S)S
					pop;
					getfield_a_this 20;		// reference com/josh/vku2f/CTAP2.cborEncoder
					getstatic_a 214;		// reference com/josh/vku2f/Utf8Strings.UTF8_FIDO2
					sconst_0;
					bspush 8;
					invokevirtual 178;		// encodeTextString([BSS)S
					pop;
					getfield_a_this 20;		// reference com/josh/vku2f/CTAP2.cborEncoder
					sconst_3;
					invokevirtual 202;		// encodeUInt8(B)S
					pop;
					getfield_a_this 20;		// reference com/josh/vku2f/CTAP2.cborEncoder
					getstatic_a 215;		// reference com/josh/vku2f/CTAP2.aaguid
					sconst_0;
					bspush 16;
					invokevirtual 189;		// encodeByteString([BSS)S
					pop;
					getfield_a_this 20;		// reference com/josh/vku2f/CTAP2.cborEncoder
					sconst_4;
					invokevirtual 202;		// encodeUInt8(B)S
					pop;
					getfield_a_this 20;		// reference com/josh/vku2f/CTAP2.cborEncoder
					sconst_3;
					invokevirtual 176;		// startMap(S)S
					pop;
					getfield_a_this 20;		// reference com/josh/vku2f/CTAP2.cborEncoder
					getstatic_a 298;		// reference com/josh/vku2f/Utf8Strings.UTF8_RK
					sconst_0;
					sconst_2;
					invokevirtual 178;		// encodeTextString([BSS)S
					pop;
					getfield_a_this 20;		// reference com/josh/vku2f/CTAP2.cborEncoder
					sconst_1;
					invokevirtual 216;		// encodeBoolean(Z)S
					pop;
					getfield_a_this 20;		// reference com/josh/vku2f/CTAP2.cborEncoder
					getstatic_a 195;		// reference com/josh/vku2f/Utf8Strings.UTF8_UP
					sconst_0;
					sconst_2;
					invokevirtual 178;		// encodeTextString([BSS)S
					pop;
					getfield_a_this 20;		// reference com/josh/vku2f/CTAP2.cborEncoder
					sconst_1;
					invokevirtual 216;		// encodeBoolean(Z)S
					pop;
					getfield_a_this 20;		// reference com/josh/vku2f/CTAP2.cborEncoder
					getstatic_a 208;		// reference com/josh/vku2f/Utf8Strings.UTF8_UV
					sconst_0;
					sconst_2;
					invokevirtual 178;		// encodeTextString([BSS)S
					pop;
					getfield_a_this 20;		// reference com/josh/vku2f/CTAP2.cborEncoder
					sconst_1;
					invokevirtual 216;		// encodeBoolean(Z)S
					pop;
					getfield_a_this 20;		// reference com/josh/vku2f/CTAP2.cborEncoder
					sconst_5;
					invokevirtual 202;		// encodeUInt8(B)S
					pop;
					getfield_a_this 20;		// reference com/josh/vku2f/CTAP2.cborEncoder
					sspush 1200;
					invokevirtual 217;		// encodeUInt16(S)S
					pop;
					invokestatic 218;		// javacard/framework/JCSystem.beginTransaction()V
					aload_0;
					getfield_a_this 20;		// reference com/josh/vku2f/CTAP2.cborEncoder
					invokevirtual 96;		// getCurrentOffset()S
					newarray 11;
					putfield_a 39;		// reference com/josh/vku2f/CTAP2.info
					getfield_a_this 16;		// reference com/josh/vku2f/CTAP2.inBuf
					sconst_0;
					getfield_a_this 39;		// reference com/josh/vku2f/CTAP2.info
					sconst_0;
					getfield_a_this 20;		// reference com/josh/vku2f/CTAP2.cborEncoder
					invokevirtual 96;		// getCurrentOffset()S
					invokestatic 104;		// javacard/framework/Util.arrayCopy([BS[BSS)S
					pop;
					invokestatic 219;		// javacard/framework/JCSystem.commitTransaction()V
				L2:	getfield_a_this 39;		// reference com/josh/vku2f/CTAP2.info
					sconst_0;
					getfield_a_this 16;		// reference com/josh/vku2f/CTAP2.inBuf
					sconst_0;
					getfield_a_this 39;		// reference com/josh/vku2f/CTAP2.info
					arraylength;
					invokestatic 86;		// javacard/framework/Util.arrayCopyNonAtomic([BS[BSS)S
					pop;
					aload_0;
					aload_1;
					getfield_a_this 39;		// reference com/josh/vku2f/CTAP2.info
					arraylength;
					invokevirtual 192;		// sendLongChaining(Ljavacard/framework/APDU;S)V
					return;
		}

		.method private doAssertionCommon(Lcom/josh/vku2f/CBOREncoder;S)V {
			.stack 8;
			.locals 1;

				L0:	sload_2;
					sconst_4;
					if_scmpne L2;
				L1:	aload_1;
					sconst_4;
					invokevirtual 176;		// startMap(S)S
					pop;
					goto L3;
				L2:	aload_1;
					sconst_5;
					invokevirtual 176;		// startMap(S)S
					pop;
				L3:	aload_1;
					sconst_1;
					invokevirtual 202;		// encodeUInt8(B)S
					pop;
					aload_1;
					sconst_2;
					invokevirtual 176;		// startMap(S)S
					pop;
					getfield_a_this 20;		// reference com/josh/vku2f/CTAP2.cborEncoder
					getstatic_a 132;		// reference com/josh/vku2f/Utf8Strings.UTF8_ID
					sconst_0;
					sconst_2;
					invokevirtual 178;		// encodeTextString([BSS)S
					pop;
					getfield_a_this 20;		// reference com/josh/vku2f/CTAP2.cborEncoder
					getfield_a_this 36;		// reference com/josh/vku2f/CTAP2.assertionCreds
					getfield_a_this 24;		// reference com/josh/vku2f/CTAP2.nextAssertion
					sconst_0;
					saload;
					aaload;
					getfield_a 38;		// reference com/josh/vku2f/StoredCredential.id
					sconst_0;
					getfield_a_this 36;		// reference com/josh/vku2f/CTAP2.assertionCreds
					getfield_a_this 24;		// reference com/josh/vku2f/CTAP2.nextAssertion
					sconst_0;
					saload;
					aaload;
					getfield_a 38;		// reference com/josh/vku2f/StoredCredential.id
					arraylength;
					invokevirtual 189;		// encodeByteString([BSS)S
					pop;
					getfield_a_this 20;		// reference com/josh/vku2f/CTAP2.cborEncoder
					getstatic_a 181;		// reference com/josh/vku2f/Utf8Strings.UTF8_TYPE
					sconst_0;
					sconst_4;
					invokevirtual 178;		// encodeTextString([BSS)S
					pop;
					getfield_a_this 20;		// reference com/josh/vku2f/CTAP2.cborEncoder
					getstatic_a 290;		// reference com/josh/vku2f/Utf8Strings.UTF8_PUBLIC_KEY
					sconst_0;
					bspush 10;
					invokevirtual 178;		// encodeTextString([BSS)S
					pop;
					getfield_a_this 20;		// reference com/josh/vku2f/CTAP2.cborEncoder
					sconst_2;
					invokevirtual 202;		// encodeUInt8(B)S
					pop;
					getfield_a_this 20;		// reference com/josh/vku2f/CTAP2.cborEncoder
					getfield_a_this 17;		// reference com/josh/vku2f/CTAP2.scratch
					sconst_0;
					bspush 37;
					invokevirtual 189;		// encodeByteString([BSS)S
					pop;
					getfield_a_this 20;		// reference com/josh/vku2f/CTAP2.cborEncoder
					sconst_3;
					invokevirtual 202;		// encodeUInt8(B)S
					pop;
					getfield_a_this 18;		// reference com/josh/vku2f/CTAP2.vars
					sconst_3;
					getfield_a_this 36;		// reference com/josh/vku2f/CTAP2.assertionCreds
					getfield_a_this 24;		// reference com/josh/vku2f/CTAP2.nextAssertion
					sconst_0;
					saload;
					aaload;
					getfield_a_this 17;		// reference com/josh/vku2f/CTAP2.scratch
					sconst_0;
					bspush 69;
					getfield_a_this 17;		// reference com/josh/vku2f/CTAP2.scratch
					bspush 69;
					invokevirtual 220;		// performSignature([BSS[BS)S
					sastore;
					getfield_a_this 20;		// reference com/josh/vku2f/CTAP2.cborEncoder
					getfield_a_this 17;		// reference com/josh/vku2f/CTAP2.scratch
					bspush 69;
					getfield_a_this 18;		// reference com/josh/vku2f/CTAP2.vars
					sconst_3;
					saload;
					invokevirtual 189;		// encodeByteString([BSS)S
					pop;
					getfield_a_this 20;		// reference com/josh/vku2f/CTAP2.cborEncoder
					sconst_4;
					invokevirtual 202;		// encodeUInt8(B)S
					pop;
					getfield_a_this 35;		// reference com/josh/vku2f/CTAP2.assertion
					getfield_a 4;		// reference com/josh/vku2f/AuthenticatorGetAssertion.options
					sconst_1;
					baload;
					ifeq_w L13;
				L4:	getfield_a_this 20;		// reference com/josh/vku2f/CTAP2.cborEncoder
					getfield_a_this 36;		// reference com/josh/vku2f/CTAP2.assertionCreds
					getfield_a_this 24;		// reference com/josh/vku2f/CTAP2.nextAssertion
					sconst_0;
					saload;
					aaload;
					getfield_a 40;		// reference com/josh/vku2f/StoredCredential.user
					getfield_b 41;		// byte com/josh/vku2f/PublicKeyCredentialUserEntity.numData
					invokevirtual 176;		// startMap(S)S
					pop;
					getfield_a_this 36;		// reference com/josh/vku2f/CTAP2.assertionCreds
					getfield_a_this 24;		// reference com/josh/vku2f/CTAP2.nextAssertion
					sconst_0;
					saload;
					aaload;
					invokevirtual 223;		// getPresentUser()[Z
					astore_3;
					aload_3;
					sconst_2;
					baload;
					ifeq L6;
				L5:	getfield_a_this 20;		// reference com/josh/vku2f/CTAP2.cborEncoder
					getstatic_a 255;		// reference com/josh/vku2f/Utf8Strings.UTF8_DISPLAYNAME
					sconst_0;
					bspush 11;
					invokevirtual 178;		// encodeTextString([BSS)S
					pop;
					getfield_a_this 20;		// reference com/josh/vku2f/CTAP2.cborEncoder
					getfield_a_this 36;		// reference com/josh/vku2f/CTAP2.assertionCreds
					getfield_a_this 24;		// reference com/josh/vku2f/CTAP2.nextAssertion
					sconst_0;
					saload;
					aaload;
					getfield_a 40;		// reference com/josh/vku2f/StoredCredential.user
					getfield_a 42;		// reference com/josh/vku2f/PublicKeyCredentialUserEntity.displayName
					getfield_a 43;		// reference com/josh/vku2f/DomString.str
					sconst_0;
					getfield_a_this 36;		// reference com/josh/vku2f/CTAP2.assertionCreds
					getfield_a_this 24;		// reference com/josh/vku2f/CTAP2.nextAssertion
					sconst_0;
					saload;
					aaload;
					getfield_a 40;		// reference com/josh/vku2f/StoredCredential.user
					getfield_a 42;		// reference com/josh/vku2f/PublicKeyCredentialUserEntity.displayName
					getfield_s 44;		// short com/josh/vku2f/DomString.len
					invokevirtual 178;		// encodeTextString([BSS)S
					pop;
				L6:	aload_3;
					sconst_1;
					baload;
					ifeq L8;
				L7:	getfield_a_this 20;		// reference com/josh/vku2f/CTAP2.cborEncoder
					getstatic_a 132;		// reference com/josh/vku2f/Utf8Strings.UTF8_ID
					sconst_0;
					sconst_2;
					invokevirtual 178;		// encodeTextString([BSS)S
					pop;
					getfield_a_this 20;		// reference com/josh/vku2f/CTAP2.cborEncoder
					getfield_a_this 36;		// reference com/josh/vku2f/CTAP2.assertionCreds
					getfield_a_this 24;		// reference com/josh/vku2f/CTAP2.nextAssertion
					sconst_0;
					saload;
					aaload;
					getfield_a 40;		// reference com/josh/vku2f/StoredCredential.user
					getfield_a 45;		// reference com/josh/vku2f/PublicKeyCredentialUserEntity.id
					sconst_0;
					getfield_a_this 36;		// reference com/josh/vku2f/CTAP2.assertionCreds
					getfield_a_this 24;		// reference com/josh/vku2f/CTAP2.nextAssertion
					sconst_0;
					saload;
					aaload;
					getfield_a 40;		// reference com/josh/vku2f/StoredCredential.user
					getfield_a 45;		// reference com/josh/vku2f/PublicKeyCredentialUserEntity.id
					arraylength;
					invokevirtual 189;		// encodeByteString([BSS)S
					pop;
				L8:	aload_3;
					sconst_0;
					baload;
					ifeq L10;
				L9:	getfield_a_this 20;		// reference com/josh/vku2f/CTAP2.cborEncoder
					getstatic_a 227;		// reference com/josh/vku2f/Utf8Strings.UTF8_NAME
					sconst_0;
					sconst_4;
					invokevirtual 178;		// encodeTextString([BSS)S
					pop;
					getfield_a_this 20;		// reference com/josh/vku2f/CTAP2.cborEncoder
					getfield_a_this 36;		// reference com/josh/vku2f/CTAP2.assertionCreds
					getfield_a_this 24;		// reference com/josh/vku2f/CTAP2.nextAssertion
					sconst_0;
					saload;
					aaload;
					getfield_a 40;		// reference com/josh/vku2f/StoredCredential.user
					getfield_a 46;		// reference com/josh/vku2f/PublicKeyCredentialEntity.name
					getfield_a 43;		// reference com/josh/vku2f/DomString.str
					sconst_0;
					getfield_a_this 36;		// reference com/josh/vku2f/CTAP2.assertionCreds
					getfield_a_this 24;		// reference com/josh/vku2f/CTAP2.nextAssertion
					sconst_0;
					saload;
					aaload;
					getfield_a 40;		// reference com/josh/vku2f/StoredCredential.user
					getfield_a 46;		// reference com/josh/vku2f/PublicKeyCredentialEntity.name
					getfield_s 44;		// short com/josh/vku2f/DomString.len
					invokevirtual 178;		// encodeTextString([BSS)S
					pop;
				L10:	aload_3;
					sconst_3;
					baload;
					ifeq L12;
				L11:	getfield_a_this 20;		// reference com/josh/vku2f/CTAP2.cborEncoder
					getstatic_a 268;		// reference com/josh/vku2f/Utf8Strings.UTF8_ICON
					sconst_0;
					sconst_4;
					invokevirtual 178;		// encodeTextString([BSS)S
					pop;
					getfield_a_this 20;		// reference com/josh/vku2f/CTAP2.cborEncoder
					getfield_a_this 36;		// reference com/josh/vku2f/CTAP2.assertionCreds
					getfield_a_this 24;		// reference com/josh/vku2f/CTAP2.nextAssertion
					sconst_0;
					saload;
					aaload;
					getfield_a 40;		// reference com/josh/vku2f/StoredCredential.user
					getfield_a 47;		// reference com/josh/vku2f/PublicKeyCredentialUserEntity.icon
					sconst_0;
					getfield_a_this 36;		// reference com/josh/vku2f/CTAP2.assertionCreds
					getfield_a_this 24;		// reference com/josh/vku2f/CTAP2.nextAssertion
					sconst_0;
					saload;
					aaload;
					getfield_a 40;		// reference com/josh/vku2f/StoredCredential.user
					getfield_a 47;		// reference com/josh/vku2f/PublicKeyCredentialUserEntity.icon
					arraylength;
					invokevirtual 178;		// encodeTextString([BSS)S
					pop;
				L12:	goto L14;
				L13:	getfield_a_this 20;		// reference com/josh/vku2f/CTAP2.cborEncoder
					sconst_1;
					invokevirtual 176;		// startMap(S)S
					pop;
					getfield_a_this 20;		// reference com/josh/vku2f/CTAP2.cborEncoder
					getstatic_a 132;		// reference com/josh/vku2f/Utf8Strings.UTF8_ID
					sconst_0;
					sconst_2;
					invokevirtual 178;		// encodeTextString([BSS)S
					pop;
					getfield_a_this 20;		// reference com/josh/vku2f/CTAP2.cborEncoder
					getfield_a_this 36;		// reference com/josh/vku2f/CTAP2.assertionCreds
					getfield_a_this 24;		// reference com/josh/vku2f/CTAP2.nextAssertion
					sconst_0;
					saload;
					aaload;
					getfield_a 40;		// reference com/josh/vku2f/StoredCredential.user
					getfield_a 45;		// reference com/josh/vku2f/PublicKeyCredentialUserEntity.id
					sconst_0;
					getfield_a_this 36;		// reference com/josh/vku2f/CTAP2.assertionCreds
					getfield_a_this 24;		// reference com/josh/vku2f/CTAP2.nextAssertion
					sconst_0;
					saload;
					aaload;
					getfield_a 40;		// reference com/josh/vku2f/StoredCredential.user
					getfield_a 45;		// reference com/josh/vku2f/PublicKeyCredentialUserEntity.id
					arraylength;
					invokevirtual 189;		// encodeByteString([BSS)S
					pop;
				L14:	sload_2;
					sconst_5;
					if_scmpne L16;
				L15:	getfield_a_this 20;		// reference com/josh/vku2f/CTAP2.cborEncoder
					sconst_5;
					invokevirtual 202;		// encodeUInt8(B)S
					pop;
					getfield_a_this 20;		// reference com/josh/vku2f/CTAP2.cborEncoder
					getfield_a_this 36;		// reference com/josh/vku2f/CTAP2.assertionCreds
					arraylength;
					s2b;
					invokevirtual 202;		// encodeUInt8(B)S
					pop;
				L16:	return;
		}

		.method static isCommandChainingCLA(Ljavacard/framework/APDU;)Z {
			.stack 2;
			.locals 1;

			.descriptor	Ljavacard/framework/APDU;	2.10;

				L0:	aload_0;
					invokevirtual 133;		// getBuffer()[B
					astore_1;
					aload_1;
					sconst_0;
					baload;
					bspush 16;
					sand;
					bspush 16;
					if_scmpne L2;
				L1:	sconst_1;
					goto L3;
				L2:	sconst_0;
				L3:	sreturn;
		}

		.method private doApduIngestion(Ljavacard/framework/APDU;)S {
			.stack 8;
			.locals 1;

			.descriptor	Ljavacard/framework/APDU;	2.10;

				L0:	aload_1;
					invokevirtual 133;		// getBuffer()[B
					astore_2;
					getfield_a_this 18;		// reference com/josh/vku2f/CTAP2.vars
					sconst_4;
					aload_1;
					invokevirtual 230;		// setIncomingAndReceive()S
					sastore;
					getfield_a_this 18;		// reference com/josh/vku2f/CTAP2.vars
					sconst_3;
					aload_1;
					invokevirtual 231;		// getIncomingLength()S
					sastore;
					getfield_a_this 18;		// reference com/josh/vku2f/CTAP2.vars
					sconst_3;
					saload;
					sspush 1200;
					if_scmple L2;
				L1:	aload_0;
					aload_1;
					bspush 57;
					invokevirtual 148;		// returnError(Ljavacard/framework/APDU;B)V
					sconst_0;
					sreturn;
				L2:	aload_1;
					invokestatic 232;		// com/josh/vku2f/CTAP2.isCommandChainingCLA(Ljavacard/framework/APDU;)Z
					ifeq L6;
				L3:	getfield_a_this 26;		// reference com/josh/vku2f/CTAP2.isChaining
					sconst_0;
					baload;
					ifne L5;
				L4:	getfield_a_this 26;		// reference com/josh/vku2f/CTAP2.isChaining
					sconst_0;
					sconst_1;
					bastore;
					getfield_a_this 27;		// reference com/josh/vku2f/CTAP2.chainRam
					sconst_0;
					sconst_0;
					sastore;
				L5:	getfield_a_this 27;		// reference com/josh/vku2f/CTAP2.chainRam
					sconst_1;
					getfield_a_this 18;		// reference com/josh/vku2f/CTAP2.vars
					sconst_4;
					saload;
					sastore;
					getfield_a_this 27;		// reference com/josh/vku2f/CTAP2.chainRam
					sconst_0;
					aload_2;
					aload_1;
					invokevirtual 233;		// getOffsetCdata()S
					getfield_a_this 16;		// reference com/josh/vku2f/CTAP2.inBuf
					getfield_a_this 27;		// reference com/josh/vku2f/CTAP2.chainRam
					sconst_0;
					saload;
					getfield_a_this 27;		// reference com/josh/vku2f/CTAP2.chainRam
					sconst_1;
					saload;
					invokestatic 86;		// javacard/framework/Util.arrayCopyNonAtomic([BS[BSS)S
					sastore;
					sconst_0;
					sreturn;
				L6:	getfield_a_this 26;		// reference com/josh/vku2f/CTAP2.isChaining
					sconst_0;
					baload;
					ifeq L8;
				L7:	getfield_a_this 27;		// reference com/josh/vku2f/CTAP2.chainRam
					sconst_1;
					getfield_a_this 18;		// reference com/josh/vku2f/CTAP2.vars
					sconst_4;
					saload;
					sastore;
					getfield_a_this 27;		// reference com/josh/vku2f/CTAP2.chainRam
					sconst_0;
					aload_2;
					aload_1;
					invokevirtual 233;		// getOffsetCdata()S
					getfield_a_this 16;		// reference com/josh/vku2f/CTAP2.inBuf
					getfield_a_this 27;		// reference com/josh/vku2f/CTAP2.chainRam
					sconst_0;
					saload;
					getfield_a_this 27;		// reference com/josh/vku2f/CTAP2.chainRam
					sconst_1;
					saload;
					invokestatic 86;		// javacard/framework/Util.arrayCopyNonAtomic([BS[BSS)S
					sastore;
					getfield_a_this 26;		// reference com/josh/vku2f/CTAP2.isChaining
					sconst_0;
					sconst_0;
					bastore;
					getfield_a_this 26;		// reference com/josh/vku2f/CTAP2.isChaining
					sconst_1;
					sconst_1;
					bastore;
					getfield_a_this 27;		// reference com/josh/vku2f/CTAP2.chainRam
					sconst_0;
					saload;
					sreturn;
				L8:	getfield_a_this 18;		// reference com/josh/vku2f/CTAP2.vars
					sconst_3;
					saload;
					sconst_1;
					if_scmpne L10;
				L9:	getfield_a_this 16;		// reference com/josh/vku2f/CTAP2.inBuf
					sconst_0;
					aload_2;
					aload_1;
					invokevirtual 233;		// getOffsetCdata()S
					baload;
					bastore;
					sconst_1;
					sreturn;
				L10:	aload_1;
					invokevirtual 234;		// getCurrentState()B
					sconst_2;
					if_scmpne L12;
				L11:	aload_2;
					aload_1;
					invokevirtual 233;		// getOffsetCdata()S
					getfield_a_this 16;		// reference com/josh/vku2f/CTAP2.inBuf
					sconst_0;
					getfield_a_this 18;		// reference com/josh/vku2f/CTAP2.vars
					sconst_3;
					saload;
					invokestatic 86;		// javacard/framework/Util.arrayCopyNonAtomic([BS[BSS)S
					pop;
					getfield_a_this 18;		// reference com/josh/vku2f/CTAP2.vars
					sconst_4;
					saload;
					sreturn;
				L12:	getfield_a_this 18;		// reference com/josh/vku2f/CTAP2.vars
					sconst_5;
					getfield_a_this 18;		// reference com/josh/vku2f/CTAP2.vars
					sconst_4;
					saload;
					sastore;
					getfield_a_this 18;		// reference com/josh/vku2f/CTAP2.vars
					sconst_4;
					sconst_0;
					sastore;
				L13:	getfield_a_this 18;		// reference com/josh/vku2f/CTAP2.vars
					sconst_3;
					saload;
					ifle L15;
				L14:	getfield_a_this 18;		// reference com/josh/vku2f/CTAP2.vars
					sconst_4;
					aload_2;
					aload_1;
					invokevirtual 233;		// getOffsetCdata()S
					getfield_a_this 16;		// reference com/josh/vku2f/CTAP2.inBuf
					getfield_a_this 18;		// reference com/josh/vku2f/CTAP2.vars
					sconst_4;
					saload;
					getfield_a_this 18;		// reference com/josh/vku2f/CTAP2.vars
					sconst_5;
					saload;
					invokestatic 86;		// javacard/framework/Util.arrayCopyNonAtomic([BS[BSS)S
					sastore;
					getfield_a_this 18;		// reference com/josh/vku2f/CTAP2.vars
					sconst_3;
					dup2;
					saload;
					getfield_a_this 18;		// reference com/josh/vku2f/CTAP2.vars
					sconst_5;
					saload;
					ssub;
					sastore;
					getfield_a_this 18;		// reference com/josh/vku2f/CTAP2.vars
					sconst_5;
					aload_1;
					aload_1;
					invokevirtual 233;		// getOffsetCdata()S
					invokevirtual 235;		// receiveBytes(S)S
					sastore;
					goto L13;
				L15:	getfield_a_this 18;		// reference com/josh/vku2f/CTAP2.vars
					sconst_4;
					saload;
					sreturn;
		}

		.method public getData(Ljavacard/framework/APDU;)V 20 {
			.stack 6;
			.locals 1;

			.descriptor	Ljavacard/framework/APDU;	2.10;

				L0:	getfield_a_this 28;		// reference com/josh/vku2f/CTAP2.outChainRam
					sconst_0;
					saload;
					sspush 256;
					if_scmple L5;
				L1:	getfield_a_this 28;		// reference com/josh/vku2f/CTAP2.outChainRam
					sconst_0;
					dup2;
					saload;
					sspush 256;
					ssub;
					sastore;
					aload_1;
					invokevirtual 133;		// getBuffer()[B
					astore_2;
					getfield_a_this 16;		// reference com/josh/vku2f/CTAP2.inBuf
					getfield_a_this 28;		// reference com/josh/vku2f/CTAP2.outChainRam
					sconst_1;
					saload;
					aload_2;
					sconst_0;
					sspush 256;
					invokestatic 86;		// javacard/framework/Util.arrayCopyNonAtomic([BS[BSS)S
					pop;
					aload_1;
					sconst_0;
					sspush 256;
					invokevirtual 212;		// setOutgoingAndSend(SS)V
					getfield_a_this 28;		// reference com/josh/vku2f/CTAP2.outChainRam
					sconst_1;
					dup2;
					saload;
					sspush 256;
					sadd;
					sastore;
					getfield_a_this 28;		// reference com/josh/vku2f/CTAP2.outChainRam
					sconst_0;
					saload;
					sspush 255;
					if_scmple L3;
				L2:	sspush 24832;
					invokestatic 74;		// javacard/framework/ISOException.throwIt(S)V
					goto L4;
				L3:	bspush 97;
					getfield_a_this 28;		// reference com/josh/vku2f/CTAP2.outChainRam
					sconst_0;
					saload;
					s2b;
					invokestatic 287;		// javacard/framework/Util.makeShort(BB)S
					invokestatic 74;		// javacard/framework/ISOException.throwIt(S)V
				L4:	goto L6;
				L5:	aload_1;
					invokevirtual 133;		// getBuffer()[B
					astore_2;
					getfield_a_this 16;		// reference com/josh/vku2f/CTAP2.inBuf
					getfield_a_this 28;		// reference com/josh/vku2f/CTAP2.outChainRam
					sconst_1;
					saload;
					aload_2;
					sconst_0;
					getfield_a_this 28;		// reference com/josh/vku2f/CTAP2.outChainRam
					sconst_0;
					saload;
					invokestatic 86;		// javacard/framework/Util.arrayCopyNonAtomic([BS[BSS)S
					pop;
					aload_1;
					sconst_0;
					getfield_a_this 28;		// reference com/josh/vku2f/CTAP2.outChainRam
					sconst_0;
					saload;
					invokevirtual 212;		// setOutgoingAndSend(SS)V
					getfield_a_this 29;		// reference com/josh/vku2f/CTAP2.isOutChaining
					sconst_0;
					sconst_0;
					bastore;
					getfield_a_this 28;		// reference com/josh/vku2f/CTAP2.outChainRam
					sconst_0;
					sconst_0;
					sastore;
					getfield_a_this 28;		// reference com/josh/vku2f/CTAP2.outChainRam
					sconst_1;
					sconst_0;
					sastore;
					sspush -28672;
					invokestatic 74;		// javacard/framework/ISOException.throwIt(S)V
				L6:	return;
		}

		.method public sendLongChaining(Ljavacard/framework/APDU;S)V 21 {
			.stack 5;
			.locals 1;

			.descriptor	Ljavacard/framework/APDU;	2.10;

				L0:	sload_2;
					sspush 256;
					if_scmple L5;
				L1:	getfield_a_this 29;		// reference com/josh/vku2f/CTAP2.isOutChaining
					sconst_0;
					sconst_1;
					bastore;
					getfield_a_this 28;		// reference com/josh/vku2f/CTAP2.outChainRam
					sconst_0;
					sload_2;
					sspush 256;
					ssub;
					sastore;
					aload_1;
					invokevirtual 133;		// getBuffer()[B
					astore_3;
					getfield_a_this 16;		// reference com/josh/vku2f/CTAP2.inBuf
					sconst_0;
					aload_3;
					sconst_0;
					sspush 256;
					invokestatic 86;		// javacard/framework/Util.arrayCopyNonAtomic([BS[BSS)S
					pop;
					aload_1;
					sconst_0;
					sspush 256;
					invokevirtual 212;		// setOutgoingAndSend(SS)V
					getfield_a_this 28;		// reference com/josh/vku2f/CTAP2.outChainRam
					sconst_1;
					sspush 256;
					sastore;
					getfield_a_this 28;		// reference com/josh/vku2f/CTAP2.outChainRam
					sconst_0;
					saload;
					sspush 255;
					if_scmple L3;
				L2:	sspush 24832;
					invokestatic 74;		// javacard/framework/ISOException.throwIt(S)V
					goto L4;
				L3:	bspush 97;
					getfield_a_this 28;		// reference com/josh/vku2f/CTAP2.outChainRam
					sconst_0;
					saload;
					s2b;
					invokestatic 287;		// javacard/framework/Util.makeShort(BB)S
					invokestatic 74;		// javacard/framework/ISOException.throwIt(S)V
				L4:	goto L6;
				L5:	getfield_a_this 29;		// reference com/josh/vku2f/CTAP2.isOutChaining
					sconst_0;
					sconst_0;
					bastore;
					aload_1;
					invokevirtual 151;		// setOutgoing()S
					pop;
					aload_1;
					sload_2;
					invokevirtual 152;		// setOutgoingLength(S)V
					aload_1;
					getfield_a_this 16;		// reference com/josh/vku2f/CTAP2.inBuf
					sconst_0;
					sload_2;
					invokevirtual 153;		// sendBytesLong([BSS)V
					sspush -28672;
					invokestatic 74;		// javacard/framework/ISOException.throwIt(S)V
				L6:	return;
		}

		.method public isChaining()Z 22 {
			.stack 2;
			.locals 0;

				L0:	getfield_a_this 29;		// reference com/josh/vku2f/CTAP2.isOutChaining
					sconst_0;
					baload;
					sreturn;
		}

		.method private getCert(Ljavacard/framework/APDU;)V {
			.stack 5;
			.locals 0;

			.descriptor	Ljavacard/framework/APDU;	2.10;

				L0:	getfield_a_this 16;		// reference com/josh/vku2f/CTAP2.inBuf
					sconst_0;
					sconst_0;
					bastore;
					getfield_a_this 18;		// reference com/josh/vku2f/CTAP2.vars
					sconst_0;
					getfield_a_this 23;		// reference com/josh/vku2f/CTAP2.attestation
					getfield_a_this 16;		// reference com/josh/vku2f/CTAP2.inBuf
					sconst_1;
					invokevirtual 236;		// getCert([BS)S
					sconst_1;
					sadd;
					sastore;
					aload_0;
					aload_1;
					getfield_a_this 18;		// reference com/josh/vku2f/CTAP2.vars
					sconst_0;
					saload;
					invokevirtual 192;		// sendLongChaining(Ljavacard/framework/APDU;S)V
					return;
		}

		.method public process(Ljavacard/framework/APDU;)V 7 {
			.stack 5;
			.locals 1;

			.descriptor	Ljavacard/framework/APDU;	2.10;

				L0:	aload_1;
					invokevirtual 133;		// getBuffer()[B
					astore_2;
					aload_0;
					invokevirtual 237;		// selectingApplet()Z
					ifeq L2;
				L1:	getstatic_a 214;		// reference com/josh/vku2f/Utf8Strings.UTF8_FIDO2
					sconst_0;
					aload_2;
					sconst_0;
					getstatic_a 214;		// reference com/josh/vku2f/Utf8Strings.UTF8_FIDO2
					arraylength;
					invokestatic 86;		// javacard/framework/Util.arrayCopyNonAtomic([BS[BSS)S
					pop;
					aload_1;
					sconst_0;
					getstatic_a 214;		// reference com/josh/vku2f/Utf8Strings.UTF8_FIDO2
					arraylength;
					invokevirtual 212;		// setOutgoingAndSend(SS)V
					return;
				L2:	aload_1;
					invokevirtual 238;		// isCommandChainingCLA()Z
					ifne L5;
				L3:	aload_1;
					invokevirtual 239;		// isISOInterindustryCLA()Z
					ifeq L5;
				L4:	sspush 28160;
					invokestatic 74;		// javacard/framework/ISOException.throwIt(S)V
				L5:	invokestatic 210;		// javacard/framework/JCSystem.requestObjectDeletion()V
					aload_2;
					sconst_1;
					baload;
					slookupswitch L11 3 -64 L6 16 L9 18 L10;
				L6:	aload_0;
					invokevirtual 240;		// isChaining()Z
					ifeq L8;
				L7:	aload_0;
					aload_1;
					invokevirtual 241;		// getData(Ljavacard/framework/APDU;)V
					goto L12;
				L8:	sspush 27013;
					invokestatic 74;		// javacard/framework/ISOException.throwIt(S)V
					goto L12;
				L9:	aload_0;
					aload_1;
					invokevirtual 242;		// handle(Ljavacard/framework/APDU;)V
					goto L12;
				L10:	sspush -28672;
					invokestatic 74;		// javacard/framework/ISOException.throwIt(S)V
					goto L12;
				L11:	sspush 27904;
					invokestatic 74;		// javacard/framework/ISOException.throwIt(S)V
				L12:	return;
		}

		.method public static install([BSB)V 0 {
			.stack 5;
			.locals 3;

				L0:	sload_1;
					sstore_3;
					sload_3;
					aload_0;
					sload_3;
					baload;
					sconst_1;
					sadd;
					sadd;
					sstore_3;
					sload_3;
					aload_0;
					sload_3;
					baload;
					sconst_1;
					sadd;
					sadd;
					sstore_3;
					new 243;		// com/josh/vku2f/CTAP2
					dup;
					invokespecial 244;		// com/josh/vku2f/CTAP2.<init>()V
					astore 4;
				L1:	aload 4;
					aload_0;
					sload_1;
					sconst_1;
					sadd;
					aload_0;
					sload_1;
					baload;
					invokevirtual 245;		// register([BSB)V
				L2:	goto L4;
				L3:	astore 5;
					aload 4;
					invokevirtual 246;		// register()V
				L4:	return;
			.exceptionTable {
				// start_block end_block handler_block catch_type_index
				L1 L2 L3 106;
			}
		}

	}

	.class public CTAP2Exception 7 extends 2.4 {		// extends javacard/framework/CardException

		.fields {
			private static CTAP2Exception systemInstance;		// Lcom/josh/vku2f/CTAP2Exception;
		}

		.publicMethodTable 3 {
			equals(Ljava/lang/Object;)Z;
			getReason()S;
			setReason(S)V;
		}

		.packageMethodTable 0 {
		}

		.method public <init>(S)V 0 {
			.stack 2;
			.locals 0;

				L0:	aload_0;
					sload_1;
					invokespecial 247;		// javacard/framework/CardException.<init>(S)V
					getstatic_a 248;		// reference com/josh/vku2f/CTAP2Exception.systemInstance
					ifnonnull L2;
				L1:	aload_0;
					putstatic_a 248;		// reference com/josh/vku2f/CTAP2Exception.systemInstance
				L2:	return;
		}

		.method public static throwIt(S)V 1 {
			.stack 2;
			.locals 0;

				L0:	getstatic_a 248;		// reference com/josh/vku2f/CTAP2Exception.systemInstance
					sload_0;
					invokevirtual 249;		// setReason(S)V
					getstatic_a 248;		// reference com/josh/vku2f/CTAP2Exception.systemInstance
					athrow;
		}

		.method public static throwIt(B)V 2 {
			.stack 2;
			.locals 0;

				L0:	getstatic_a 248;		// reference com/josh/vku2f/CTAP2Exception.systemInstance
					sload_0;
					invokevirtual 249;		// setReason(S)V
					getstatic_a 248;		// reference com/josh/vku2f/CTAP2Exception.systemInstance
					athrow;
		}

	}

	.class public CredentialArray 8 extends 0.0 {		// extends java/lang/Object

		.fields {
			private StoredCredential[] creds 0;		// [Lcom/josh/vku2f/StoredCredential;
			private boolean[] slotStatus 1;		// [Z
			private short size 2;		// S
			private short counter 3;		// S
			private short count 4;		// S
		}

		.publicMethodTable 1 {
			equals(Ljava/lang/Object;)Z;
			addCredential(Lcom/josh/vku2f/StoredCredential;)V;
			getCredential([BSS[BSS)Lcom/josh/vku2f/StoredCredential;;
			alreadyExists(Lcom/josh/vku2f/StoredCredential;)S;
			getLength()S;
			getCount()S;
			getCred(S)Lcom/josh/vku2f/StoredCredential;;
		}

		.packageMethodTable 0 {
		}

		.method public <init>(S)V 0 {
			.stack 2;
			.locals 0;

				L0:	aload_0;
					invokespecial 69;		// java/lang/Object.<init>()V
					sconst_0;
					putfield_s_this 48;		// short com/josh/vku2f/CredentialArray.count
					aload_0;
					sload_1;
					anewarray 204;		// com/josh/vku2f/StoredCredential
					putfield_a 49;		// reference com/josh/vku2f/CredentialArray.creds
					aload_0;
					sload_1;
					newarray 10;
					putfield_a 50;		// reference com/josh/vku2f/CredentialArray.slotStatus
					sload_1;
					putfield_s_this 51;		// short com/josh/vku2f/CredentialArray.size
					return;
		}

		.method public addCredential(Lcom/josh/vku2f/StoredCredential;)V 1 {
			.stack 3;
			.locals 1;

				L0:	aload_0;
					aload_1;
					invokevirtual 254;		// alreadyExists(Lcom/josh/vku2f/StoredCredential;)S
					sstore_2;
					getfield_a_this 49;		// reference com/josh/vku2f/CredentialArray.creds
					sload_2;
					aload_1;
					aastore;
					getfield_a_this 50;		// reference com/josh/vku2f/CredentialArray.slotStatus
					sload_2;
					sconst_1;
					bastore;
					aload_0;
					sload_2;
					sconst_1;
					sadd;
					putfield_s 48;		// short com/josh/vku2f/CredentialArray.count
				L1:	goto L3;
				L2:	astore_2;
					bspush 40;
					invokestatic 131;		// javacard/framework/UserException.throwIt(S)V
				L3:	return;
			.exceptionTable {
				// start_block end_block handler_block catch_type_index
				L0 L1 L2 106;
			}
		}

		.method public getCredential([BSS[BSS)Lcom/josh/vku2f/StoredCredential; 2 {
			.stack 4;
			.locals 0;

				L0:	sconst_0;
					putfield_s_this 52;		// short com/josh/vku2f/CredentialArray.counter
				L1:	getfield_s_this 52;		// short com/josh/vku2f/CredentialArray.counter
					getfield_s_this 51;		// short com/josh/vku2f/CredentialArray.size
					if_scmpge L7;
				L2:	getfield_a_this 50;		// reference com/josh/vku2f/CredentialArray.slotStatus
					getfield_s_this 52;		// short com/josh/vku2f/CredentialArray.counter
					baload;
					ifeq L6;
				L3:	getfield_a_this 49;		// reference com/josh/vku2f/CredentialArray.creds
					getfield_s_this 52;		// short com/josh/vku2f/CredentialArray.counter
					aaload;
					getfield_a 34;		// reference com/josh/vku2f/StoredCredential.rp
					aload_1;
					sload_2;
					sload_3;
					invokevirtual 207;		// checkId([BSS)Z
					ifeq L6;
				L4:	getfield_a_this 49;		// reference com/josh/vku2f/CredentialArray.creds
					getfield_s_this 52;		// short com/josh/vku2f/CredentialArray.counter
					aaload;
					getfield_a 40;		// reference com/josh/vku2f/StoredCredential.user
					aload 4;
					sload 5;
					sload 6;
					invokevirtual 256;		// checkId([BSS)Z
					ifeq L6;
				L5:	getfield_a_this 49;		// reference com/josh/vku2f/CredentialArray.creds
					getfield_s_this 52;		// short com/josh/vku2f/CredentialArray.counter
					aaload;
					areturn;
				L6:	aload_0;
					dup;
					getfield_s 52;		// short com/josh/vku2f/CredentialArray.counter
					sconst_1;
					sadd;
					putfield_s 52;		// short com/josh/vku2f/CredentialArray.counter
					goto L1;
				L7:	aconst_null;
					areturn;
		}

		.method public alreadyExists(Lcom/josh/vku2f/StoredCredential;)S 3 {
			.stack 4;
			.locals 2;

				L0:	sconst_0;
					putfield_s_this 52;		// short com/josh/vku2f/CredentialArray.counter
				L1:	getfield_s_this 52;		// short com/josh/vku2f/CredentialArray.counter
					getfield_s_this 51;		// short com/josh/vku2f/CredentialArray.size
					if_scmpge L7;
				L2:	getfield_a_this 50;		// reference com/josh/vku2f/CredentialArray.slotStatus
					getfield_s_this 52;		// short com/josh/vku2f/CredentialArray.counter
					baload;
					ifeq L6;
				L3:	getfield_a_this 49;		// reference com/josh/vku2f/CredentialArray.creds
					getfield_s_this 52;		// short com/josh/vku2f/CredentialArray.counter
					aaload;
					getfield_a 34;		// reference com/josh/vku2f/StoredCredential.rp
					aload_1;
					getfield_a 34;		// reference com/josh/vku2f/StoredCredential.rp
					invokevirtual 257;		// checkId(Lcom/josh/vku2f/PublicKeyCredentialRpEntity;)Z
					ifeq L6;
				L4:	getfield_a_this 49;		// reference com/josh/vku2f/CredentialArray.creds
					getfield_s_this 52;		// short com/josh/vku2f/CredentialArray.counter
					aaload;
					getfield_a 40;		// reference com/josh/vku2f/StoredCredential.user
					aload_1;
					getfield_a 40;		// reference com/josh/vku2f/StoredCredential.user
					invokevirtual 258;		// checkId(Lcom/josh/vku2f/PublicKeyCredentialUserEntity;)Z
					ifeq L6;
				L5:	getfield_s_this 52;		// short com/josh/vku2f/CredentialArray.counter
					sreturn;
				L6:	aload_0;
					dup;
					getfield_s 52;		// short com/josh/vku2f/CredentialArray.counter
					sconst_1;
					sadd;
					putfield_s 52;		// short com/josh/vku2f/CredentialArray.counter
					goto L1;
				L7:	sconst_0;
					putfield_s_this 52;		// short com/josh/vku2f/CredentialArray.counter
				L8:	getfield_s_this 52;		// short com/josh/vku2f/CredentialArray.counter
					getfield_s_this 51;		// short com/josh/vku2f/CredentialArray.size
					if_scmpge L12;
				L9:	getfield_a_this 50;		// reference com/josh/vku2f/CredentialArray.slotStatus
					getfield_s_this 52;		// short com/josh/vku2f/CredentialArray.counter
					baload;
					ifne L11;
				L10:	getfield_s_this 52;		// short com/josh/vku2f/CredentialArray.counter
					sreturn;
				L11:	aload_0;
					dup;
					getfield_s 52;		// short com/josh/vku2f/CredentialArray.counter
					sconst_1;
					sadd;
					putfield_s 52;		// short com/josh/vku2f/CredentialArray.counter
					goto L8;
				L12:	getfield_s_this 51;		// short com/josh/vku2f/CredentialArray.size
					anewarray 204;		// com/josh/vku2f/StoredCredential
					astore_2;
					getfield_s_this 51;		// short com/josh/vku2f/CredentialArray.size
					newarray 10;
					astore_3;
					sconst_0;
					putfield_s_this 52;		// short com/josh/vku2f/CredentialArray.counter
				L13:	getfield_s_this 52;		// short com/josh/vku2f/CredentialArray.counter
					getfield_s_this 51;		// short com/josh/vku2f/CredentialArray.size
					if_scmpge L15;
				L14:	aload_2;
					getfield_s_this 52;		// short com/josh/vku2f/CredentialArray.counter
					getfield_a_this 49;		// reference com/josh/vku2f/CredentialArray.creds
					getfield_s_this 52;		// short com/josh/vku2f/CredentialArray.counter
					aaload;
					aastore;
					aload_3;
					getfield_s_this 52;		// short com/josh/vku2f/CredentialArray.counter
					getfield_a_this 50;		// reference com/josh/vku2f/CredentialArray.slotStatus
					getfield_s_this 52;		// short com/josh/vku2f/CredentialArray.counter
					baload;
					bastore;
					aload_0;
					dup;
					getfield_s 52;		// short com/josh/vku2f/CredentialArray.counter
					sconst_1;
					sadd;
					putfield_s 52;		// short com/josh/vku2f/CredentialArray.counter
					goto L13;
				L15:	aload_0;
					getfield_s_this 51;		// short com/josh/vku2f/CredentialArray.size
					sconst_2;
					smul;
					anewarray 204;		// com/josh/vku2f/StoredCredential
					putfield_a 49;		// reference com/josh/vku2f/CredentialArray.creds
					aload_0;
					getfield_s_this 51;		// short com/josh/vku2f/CredentialArray.size
					sconst_2;
					smul;
					newarray 10;
					putfield_a 50;		// reference com/josh/vku2f/CredentialArray.slotStatus
					sconst_0;
					putfield_s_this 52;		// short com/josh/vku2f/CredentialArray.counter
				L16:	getfield_s_this 52;		// short com/josh/vku2f/CredentialArray.counter
					getfield_s_this 51;		// short com/josh/vku2f/CredentialArray.size
					if_scmpge L18;
				L17:	getfield_a_this 49;		// reference com/josh/vku2f/CredentialArray.creds
					getfield_s_this 52;		// short com/josh/vku2f/CredentialArray.counter
					aload_2;
					getfield_s_this 52;		// short com/josh/vku2f/CredentialArray.counter
					aaload;
					aastore;
					getfield_a_this 50;		// reference com/josh/vku2f/CredentialArray.slotStatus
					getfield_s_this 52;		// short com/josh/vku2f/CredentialArray.counter
					aload_3;
					getfield_s_this 52;		// short com/josh/vku2f/CredentialArray.counter
					baload;
					bastore;
					aload_0;
					dup;
					getfield_s 52;		// short com/josh/vku2f/CredentialArray.counter
					sconst_1;
					sadd;
					putfield_s 52;		// short com/josh/vku2f/CredentialArray.counter
					goto L16;
				L18:	aload_0;
					dup;
					getfield_s 51;		// short com/josh/vku2f/CredentialArray.size
					sconst_2;
					smul;
					putfield_s 51;		// short com/josh/vku2f/CredentialArray.size
					invokestatic 210;		// javacard/framework/JCSystem.requestObjectDeletion()V
					getfield_s_this 52;		// short com/josh/vku2f/CredentialArray.counter
					sconst_1;
					sadd;
					sreturn;
		}

		.method public getLength()S 4 {
			.stack 1;
			.locals 0;

				L0:	getfield_s_this 51;		// short com/josh/vku2f/CredentialArray.size
					sreturn;
		}

		.method public getCount()S 5 {
			.stack 1;
			.locals 0;

				L0:	getfield_s_this 48;		// short com/josh/vku2f/CredentialArray.count
					sreturn;
		}

		.method public getCred(S)Lcom/josh/vku2f/StoredCredential; 6 {
			.stack 2;
			.locals 0;

				L0:	getfield_a_this 49;		// reference com/josh/vku2f/CredentialArray.creds
					sload_1;
					aaload;
					areturn;
		}

	}

	.class public DomString 9 extends 0.0 {		// extends java/lang/Object

		.fields {
			public short len 0;		// S
			public byte[] str 1;		// [B
		}

		.publicMethodTable 1 {
			equals(Ljava/lang/Object;)Z;
			checkEquals([BSS)Z;
			checkEquals(Lcom/josh/vku2f/DomString;)Z;
		}

		.packageMethodTable 0 {
		}

		.method public <init>([BS)V 0 {
			.stack 5;
			.locals 0;

				L0:	aload_0;
					invokespecial 69;		// java/lang/Object.<init>()V
					sload_2;
					bspush 64;
					if_scmple L2;
				L1:	bspush 64;
					sstore_2;
				L2:	aload_0;
					sload_2;
					newarray 11;
					putfield_a 43;		// reference com/josh/vku2f/DomString.str
					aload_1;
					sconst_0;
					getfield_a_this 43;		// reference com/josh/vku2f/DomString.str
					sconst_0;
					sload_2;
					invokestatic 104;		// javacard/framework/Util.arrayCopy([BS[BSS)S
					pop;
					sload_2;
					putfield_s_this 44;		// short com/josh/vku2f/DomString.len
					return;
		}

		.method public checkEquals([BSS)Z 1 {
			.stack 5;
			.locals 0;

				L0:	sload_3;
					bspush 64;
					if_scmple L2;
				L1:	bspush 64;
					sstore_3;
				L2:	sload_3;
					getfield_s_this 44;		// short com/josh/vku2f/DomString.len
					if_scmpeq L4;
				L3:	sconst_0;
					sreturn;
				L4:	aload_1;
					sload_2;
					getfield_a_this 43;		// reference com/josh/vku2f/DomString.str
					sconst_0;
					getfield_s_this 44;		// short com/josh/vku2f/DomString.len
					invokestatic 134;		// javacard/framework/Util.arrayCompare([BS[BSS)B
					ifne L6;
				L5:	sconst_1;
					goto L7;
				L6:	sconst_0;
				L7:	sreturn;
		}

		.method public checkEquals(Lcom/josh/vku2f/DomString;)Z 2 {
			.stack 4;
			.locals 0;

				L0:	aload_1;
					getfield_a_this 43;		// reference com/josh/vku2f/DomString.str
					sconst_0;
					getfield_s_this 44;		// short com/josh/vku2f/DomString.len
					invokevirtual 259;		// checkEquals([BSS)Z
					sreturn;
		}

	}

	.class public ICUtil 10 extends 0.0 {		// extends java/lang/Object

		.publicMethodTable 1 {
			equals(Ljava/lang/Object;)Z;
		}

		.packageMethodTable 0 {
		}

		.method public <init>()V 0 {
			.stack 1;
			.locals 0;

				L0:	aload_0;
					invokespecial 69;		// java/lang/Object.<init>()V
					return;
		}

		.method public static sign(S)S 1 {
			.stack 2;
			.locals 0;

				L0:	sload_0;
					bspush 15;
					sushr;
					sconst_1;
					sand;
					s2b;
					sreturn;
		}

		.method public static min(SS)S 2 {
			.stack 2;
			.locals 0;

				L0:	sload_0;
					sload_1;
					if_scmpge L2;
				L1:	sload_0;
					sreturn;
				L2:	sload_1;
					sreturn;
		}

		.method public static max(SS)S 3 {
			.stack 2;
			.locals 0;

				L0:	sload_0;
					sload_1;
					if_scmple L2;
				L1:	sload_0;
					sreturn;
				L2:	sload_1;
					sreturn;
		}

		.method public static setBit([BSZ)V 4 {
			.stack 5;
			.locals 2;

				L0:	sload_1;
					sconst_3;
					sushr;
					sstore_3;
					sconst_1;
					sload_1;
					bspush 7;
					sand;
					sshl;
					s2b;
					sstore 4;
					sload_2;
					ifeq L2;
				L1:	aload_0;
					sload_3;
					dup2;
					baload;
					sload 4;
					sor;
					bastore;
					goto L3;
				L2:	aload_0;
					sload_3;
					dup2;
					baload;
					sload 4;
					sconst_m1;
					sxor;
					sand;
					bastore;
				L3:	return;
		}

		.method public static getBit(BB)Z 5 {
			.stack 3;
			.locals 1;

				L0:	sconst_1;
					sload_1;
					bspush 7;
					sand;
					sshl;
					s2b;
					sstore_2;
					sload_2;
					sload_0;
					sload_2;
					sand;
					if_scmpne L2;
				L1:	sconst_1;
					goto L3;
				L2:	sconst_0;
				L3:	sreturn;
		}

		.method public static setBit(BBZ)B 6 {
			.stack 3;
			.locals 1;

				L0:	sconst_1;
					sload_1;
					bspush 7;
					sand;
					sshl;
					s2b;
					sstore_3;
					sload_2;
					ifeq L2;
				L1:	sload_0;
					sload_3;
					sor;
					sstore_0;
					goto L3;
				L2:	sload_0;
					sload_3;
					sconst_m1;
					sxor;
					sand;
					sstore_0;
				L3:	sload_0;
					sreturn;
		}

		.method public static getBit([BS)Z 7 {
			.stack 3;
			.locals 2;

				L0:	sload_1;
					sconst_3;
					sushr;
					sstore_2;
					sconst_1;
					sload_1;
					bspush 7;
					sand;
					sshl;
					s2b;
					sstore_3;
					sload_3;
					aload_0;
					sload_2;
					baload;
					sload_3;
					sand;
					if_scmpne L2;
				L1:	sconst_1;
					goto L3;
				L2:	sconst_0;
				L3:	sreturn;
		}

		.method public static isLessThanAsUnsignedShort(SS)Z 8 {
			.stack 3;
			.locals 0;

				L0:	sload_0;
					sload_1;
					if_scmpge L2;
				L1:	sconst_1;
					goto L3;
				L2:	sconst_0;
				L3:	sload_0;
					ifge L5;
				L4:	sconst_1;
					goto L6;
				L5:	sconst_0;
				L6:	sload_1;
					ifge L8;
				L7:	sconst_1;
					goto L9;
				L8:	sconst_0;
				L9:	if_scmpeq L11;
				L10:	sconst_1;
					goto L12;
				L11:	sconst_0;
				L12:	sxor;
					sreturn;
		}

		.method public static shortArrayFillNonAtomic([SSSS)S 9 {
			.stack 3;
			.locals 0;

				L0:	sload_2;
					sload_1;
					sadd;
					sstore_2;
				L1:	sload_1;
					sload_2;
					if_scmpge L3;
				L2:	aload_0;
					sload_1;
					sload_3;
					sastore;
					sinc 1 1;
					goto L1;
				L3:	sload_1;
					sreturn;
		}

	}

	.class public KeyParams 11 extends 0.0 {		// extends java/lang/Object

		.fields {
			public static final short secp256r1K = 1;		// S
			public static final byte[] secp256r1p 0 = {-1,-1,-1,-1,0,0,0,1,0,0,0,0,0,0,0,0,0,0,0,0,-1,-1,-1,-1,-1,-1,-1,-1,-1,-1,-1,-1};		// [B
			public static final byte[] secp256r1A 1 = {-1,-1,-1,-1,0,0,0,1,0,0,0,0,0,0,0,0,0,0,0,0,-1,-1,-1,-1,-1,-1,-1,-1,-1,-1,-1,-4};		// [B
			public static final byte[] secp256r1B 2 = {90,-58,53,-40,-86,58,-109,-25,-77,-21,-67,85,118,-104,-122,-68,101,29,6,-80,-52,83,-80,-10,59,-50,60,62,39,-46,96,75};		// [B
			public static final byte[] secp256r1G 3 = {4,107,23,-47,-14,-31,44,66,71,-8,-68,-26,-27,99,-92,64,-14,119,3,125,-127,45,-21,51,-96,-12,-95,57,69,-40,-104,-62,-106,79,-29,66,-30,-2,26,127,-101,-114,-25,-21,74,124,15,-98,22,43,-50,51,87,107,49,94,-50,-53,-74,64,104,55,-65,81,-11};		// [B
			public static final byte[] secp256r1R 4 = {-1,-1,-1,-1,0,0,0,0,-1,-1,-1,-1,-1,-1,-1,-1,-68,-26,-6,-83,-89,23,-98,-124,-13,-71,-54,-62,-4,99,37,81};		// [B
		}

		.publicMethodTable 1 {
			equals(Ljava/lang/Object;)Z;
		}

		.packageMethodTable 0 {
		}

		.method public <init>()V 0 {
			.stack 1;
			.locals 0;

				L0:	aload_0;
					invokespecial 69;		// java/lang/Object.<init>()V
					return;
		}

		.method public static sec256r1params(Ljavacard/security/ECKey;)V 1 {
			.stack 4;
			.locals 0;

			.descriptor	Ljavacard/security/ECKey;	1.17;

				L0:	aload_0;
					getstatic_a 260;		// reference com/josh/vku2f/KeyParams.secp256r1p
					sconst_0;
					bspush 32;
					invokeinterface 4 122 0;		// javacard/security/ECKey
					aload_0;
					getstatic_a 261;		// reference com/josh/vku2f/KeyParams.secp256r1A
					sconst_0;
					bspush 32;
					invokeinterface 4 122 3;		// javacard/security/ECKey
					aload_0;
					getstatic_a 262;		// reference com/josh/vku2f/KeyParams.secp256r1B
					sconst_0;
					bspush 32;
					invokeinterface 4 122 4;		// javacard/security/ECKey
					aload_0;
					getstatic_a 263;		// reference com/josh/vku2f/KeyParams.secp256r1G
					sconst_0;
					bspush 65;
					invokeinterface 4 122 5;		// javacard/security/ECKey
					aload_0;
					getstatic_a 264;		// reference com/josh/vku2f/KeyParams.secp256r1R
					sconst_0;
					bspush 32;
					invokeinterface 4 122 6;		// javacard/security/ECKey
					aload_0;
					sconst_1;
					invokeinterface 2 122 7;		// javacard/security/ECKey
					return;
		}

	}

	.class public PublicKeyCredentialDescriptor 12 extends 0.0 {		// extends java/lang/Object

		.fields {
			 byte[] type 0;		// [B
			 byte[] id 1;		// [B
		}

		.publicMethodTable 1 {
			equals(Ljava/lang/Object;)Z;
		}

		.packageMethodTable 0 {
		}

		.method public <init>([BSS)V 0 {
			.stack 5;
			.locals 0;

				L0:	aload_0;
					invokespecial 69;		// java/lang/Object.<init>()V
					aload_0;
					getstatic_a 290;		// reference com/josh/vku2f/Utf8Strings.UTF8_PUBLIC_KEY
					arraylength;
					newarray 11;
					putfield_a 53;		// reference com/josh/vku2f/PublicKeyCredentialDescriptor.type
					getstatic_a 290;		// reference com/josh/vku2f/Utf8Strings.UTF8_PUBLIC_KEY
					sconst_0;
					getfield_a_this 53;		// reference com/josh/vku2f/PublicKeyCredentialDescriptor.type
					sconst_0;
					getfield_a_this 53;		// reference com/josh/vku2f/PublicKeyCredentialDescriptor.type
					arraylength;
					invokestatic 104;		// javacard/framework/Util.arrayCopy([BS[BSS)S
					pop;
					aload_0;
					sload_3;
					newarray 11;
					putfield_a 37;		// reference com/josh/vku2f/PublicKeyCredentialDescriptor.id
					aload_1;
					sload_2;
					getfield_a_this 37;		// reference com/josh/vku2f/PublicKeyCredentialDescriptor.id
					sconst_0;
					getfield_a_this 37;		// reference com/josh/vku2f/PublicKeyCredentialDescriptor.id
					arraylength;
					invokestatic 104;		// javacard/framework/Util.arrayCopy([BS[BSS)S
					pop;
					return;
		}

	}

	.class public abstract PublicKeyCredentialEntity 13 extends 0.0 {		// extends java/lang/Object

		.fields {
			public DomString name 0;		// Lcom/josh/vku2f/DomString;
		}

		.publicMethodTable 1 {
			equals(Ljava/lang/Object;)Z;
			setName([BS)V;
		}

		.packageMethodTable 0 {
		}

		.method public <init>()V 0 {
			.stack 1;
			.locals 0;

				L0:	aload_0;
					invokespecial 69;		// java/lang/Object.<init>()V
					return;
		}

		.method public setName([BS)V 1 {
			.stack 5;
			.locals 0;

				L0:	aload_0;
					new 266;		// com/josh/vku2f/DomString
					dup;
					aload_1;
					sload_2;
					invokespecial 267;		// com/josh/vku2f/DomString.<init>([BS)V
					putfield_a 54;		// reference com/josh/vku2f/PublicKeyCredentialEntity.name
					return;
		}

	}

	.class public PublicKeyCredentialParams 14 extends 0.0 {		// extends java/lang/Object

		.fields {
			private short[] paramList 0;		// [S
			private short listIndex 1;		// S
			public static final short COSE_ES256 = -7;		// S
			public static final short COSE_RS256 = -257;		// S
			public static final short COSE_PS256 = -37;		// S
		}

		.publicMethodTable 1 {
			equals(Ljava/lang/Object;)Z;
			addAlgorithm(S)V;
			getAlgorithm()B;
		}

		.packageMethodTable 0 {
		}

		.method public <init>(S)V 0 {
			.stack 2;
			.locals 0;

				L0:	aload_0;
					invokespecial 69;		// java/lang/Object.<init>()V
					aload_0;
					sload_1;
					newarray 12;
					putfield_a 55;		// reference com/josh/vku2f/PublicKeyCredentialParams.paramList
					sconst_0;
					putfield_s_this 56;		// short com/josh/vku2f/PublicKeyCredentialParams.listIndex
					return;
		}

		.method public addAlgorithm(S)V 1 {
			.stack 5;
			.locals 0;

				L0:	getfield_a_this 55;		// reference com/josh/vku2f/PublicKeyCredentialParams.paramList
					aload_0;
					dup;
					getfield_s 56;		// short com/josh/vku2f/PublicKeyCredentialParams.listIndex
					dup_x 18;
					sconst_1;
					sadd;
					putfield_s 56;		// short com/josh/vku2f/PublicKeyCredentialParams.listIndex
					sload_1;
					sastore;
					return;
		}

		.method public getAlgorithm()B 2 {
			.stack 2;
			.locals 1;

				L0:	sconst_0;
					sstore_1;
				L1:	sload_1;
					getfield_s_this 56;		// short com/josh/vku2f/PublicKeyCredentialParams.listIndex
					if_scmpge L9;
				L2:	getfield_a_this 55;		// reference com/josh/vku2f/PublicKeyCredentialParams.paramList
					sload_1;
					saload;
					bspush -7;
					if_scmpne L4;
				L3:	bspush 33;
					sreturn;
				L4:	getfield_a_this 55;		// reference com/josh/vku2f/PublicKeyCredentialParams.paramList
					sload_1;
					saload;
					sspush -257;
					if_scmpne L6;
				L5:	bspush 40;
					sreturn;
				L6:	getfield_a_this 55;		// reference com/josh/vku2f/PublicKeyCredentialParams.paramList
					sload_1;
					saload;
					bspush -37;
					if_scmpne L8;
				L7:	bspush 44;
					sreturn;
				L8:	sinc 1 1;
					goto L1;
				L9:	sconst_0;
					sreturn;
		}

	}

	.class public PublicKeyCredentialRpEntity 15 extends PublicKeyCredentialEntity {

		.fields {
			 DomString rpId 0;		// Lcom/josh/vku2f/DomString;
		}

		.publicMethodTable 2 {
			equals(Ljava/lang/Object;)Z;
			setName([BS)V;
			setRp([BS)V;
			checkId([BSS)Z;
			checkId(Lcom/josh/vku2f/PublicKeyCredentialRpEntity;)Z;
			getRp([BS)V;
			getRpLen()S;
		}

		.packageMethodTable 0 {
		}

		.method public <init>()V 0 {
			.stack 1;
			.locals 0;

				L0:	aload_0;
					invokespecial 271;		// com/josh/vku2f/PublicKeyCredentialEntity.<init>()V
					return;
		}

		.method public setRp([BS)V 2 {
			.stack 5;
			.locals 0;

				L0:	aload_0;
					new 266;		// com/josh/vku2f/DomString
					dup;
					aload_1;
					sload_2;
					invokespecial 267;		// com/josh/vku2f/DomString.<init>([BS)V
					putfield_a 57;		// reference com/josh/vku2f/PublicKeyCredentialRpEntity.rpId
					return;
		}

		.method public checkId([BSS)Z 3 {
			.stack 4;
			.locals 0;

				L0:	getfield_a_this 57;		// reference com/josh/vku2f/PublicKeyCredentialRpEntity.rpId
					aload_1;
					sload_2;
					sload_3;
					invokevirtual 259;		// checkEquals([BSS)Z
					sreturn;
		}

		.method public checkId(Lcom/josh/vku2f/PublicKeyCredentialRpEntity;)Z 4 {
			.stack 2;
			.locals 0;

				L0:	getfield_a_this 57;		// reference com/josh/vku2f/PublicKeyCredentialRpEntity.rpId
					aload_1;
					getfield_a 57;		// reference com/josh/vku2f/PublicKeyCredentialRpEntity.rpId
					invokevirtual 273;		// checkEquals(Lcom/josh/vku2f/DomString;)Z
					sreturn;
		}

		.method public getRp([BS)V 5 {
			.stack 5;
			.locals 0;

				L0:	getfield_a_this 57;		// reference com/josh/vku2f/PublicKeyCredentialRpEntity.rpId
					getfield_a 43;		// reference com/josh/vku2f/DomString.str
					sconst_0;
					aload_1;
					sload_2;
					getfield_a_this 57;		// reference com/josh/vku2f/PublicKeyCredentialRpEntity.rpId
					getfield_s 44;		// short com/josh/vku2f/DomString.len
					invokestatic 104;		// javacard/framework/Util.arrayCopy([BS[BSS)S
					pop;
					return;
		}

		.method public getRpLen()S 6 {
			.stack 1;
			.locals 0;

				L0:	getfield_a_this 57;		// reference com/josh/vku2f/PublicKeyCredentialRpEntity.rpId
					getfield_s 44;		// short com/josh/vku2f/DomString.len
					sreturn;
		}

	}

	.class public PublicKeyCredentialUserEntity 16 extends PublicKeyCredentialEntity {

		.fields {
			public byte numData 0;		// B
			public byte[] id 1;		// [B
			public DomString displayName 2;		// Lcom/josh/vku2f/DomString;
			public boolean[] dataPresent 3;		// [Z
			public byte[] icon 4;		// [B
		}

		.publicMethodTable 1 {
			equals(Ljava/lang/Object;)Z;
			setName([BS)V;
			setId([BSS)V;
			setIcon([BS)V;
			setDisplayName([BS)V;
			checkId([BSS)Z;
			checkId(Lcom/josh/vku2f/PublicKeyCredentialUserEntity;)Z;
		}

		.packageMethodTable 0 {
		}

		.method public <init>()V 0 {
			.stack 2;
			.locals 0;

				L0:	aload_0;
					invokespecial 271;		// com/josh/vku2f/PublicKeyCredentialEntity.<init>()V
					aload_0;
					sconst_4;
					newarray 10;
					putfield_a 58;		// reference com/josh/vku2f/PublicKeyCredentialUserEntity.dataPresent
					sconst_0;
					putfield_b_this 41;		// byte com/josh/vku2f/PublicKeyCredentialUserEntity.numData
					return;
		}

		.method public setId([BSS)V 2 {
			.stack 5;
			.locals 0;

				L0:	aload_0;
					sload_3;
					newarray 11;
					putfield_a 45;		// reference com/josh/vku2f/PublicKeyCredentialUserEntity.id
					aload_1;
					sload_2;
					getfield_a_this 45;		// reference com/josh/vku2f/PublicKeyCredentialUserEntity.id
					sconst_0;
					sload_3;
					invokestatic 104;		// javacard/framework/Util.arrayCopy([BS[BSS)S
					pop;
					getfield_a_this 58;		// reference com/josh/vku2f/PublicKeyCredentialUserEntity.dataPresent
					sconst_1;
					baload;
					ifne L2;
				L1:	getfield_a_this 58;		// reference com/josh/vku2f/PublicKeyCredentialUserEntity.dataPresent
					sconst_1;
					sconst_1;
					bastore;
					aload_0;
					dup;
					getfield_b 41;		// byte com/josh/vku2f/PublicKeyCredentialUserEntity.numData
					sconst_1;
					sadd;
					s2b;
					putfield_b 41;		// byte com/josh/vku2f/PublicKeyCredentialUserEntity.numData
				L2:	return;
		}

		.method public setIcon([BS)V 3 {
			.stack 5;
			.locals 1;

				L0:	aload_0;
					sload_2;
					newarray 11;
					putfield_a 47;		// reference com/josh/vku2f/PublicKeyCredentialUserEntity.icon
					aload_1;
					sconst_0;
					getfield_a_this 47;		// reference com/josh/vku2f/PublicKeyCredentialUserEntity.icon
					sconst_0;
					sload_2;
					invokestatic 104;		// javacard/framework/Util.arrayCopy([BS[BSS)S
					pop;
					getfield_a_this 58;		// reference com/josh/vku2f/PublicKeyCredentialUserEntity.dataPresent
					sconst_3;
					baload;
					ifne L2;
				L1:	getfield_a_this 58;		// reference com/josh/vku2f/PublicKeyCredentialUserEntity.dataPresent
					sconst_3;
					sconst_1;
					bastore;
					aload_0;
					dup;
					getfield_b 41;		// byte com/josh/vku2f/PublicKeyCredentialUserEntity.numData
					sconst_1;
					sadd;
					s2b;
					putfield_b 41;		// byte com/josh/vku2f/PublicKeyCredentialUserEntity.numData
				L2:	goto L4;
				L3:	astore_3;
					bspush -6;
					invokestatic 131;		// javacard/framework/UserException.throwIt(S)V
				L4:	return;
			.exceptionTable {
				// start_block end_block handler_block catch_type_index
				L0 L2 L3 275;
			}
		}

		.method public setDisplayName([BS)V 4 {
			.stack 5;
			.locals 0;

				L0:	aload_0;
					new 266;		// com/josh/vku2f/DomString
					dup;
					aload_1;
					sload_2;
					invokespecial 267;		// com/josh/vku2f/DomString.<init>([BS)V
					putfield_a 42;		// reference com/josh/vku2f/PublicKeyCredentialUserEntity.displayName
					getfield_a_this 58;		// reference com/josh/vku2f/PublicKeyCredentialUserEntity.dataPresent
					sconst_2;
					baload;
					ifne L2;
				L1:	getfield_a_this 58;		// reference com/josh/vku2f/PublicKeyCredentialUserEntity.dataPresent
					sconst_2;
					sconst_1;
					bastore;
					aload_0;
					dup;
					getfield_b 41;		// byte com/josh/vku2f/PublicKeyCredentialUserEntity.numData
					sconst_1;
					sadd;
					s2b;
					putfield_b 41;		// byte com/josh/vku2f/PublicKeyCredentialUserEntity.numData
				L2:	return;
		}

		.method public checkId([BSS)Z 5 {
			.stack 5;
			.locals 0;

				L0:	sload_3;
					getfield_a_this 45;		// reference com/josh/vku2f/PublicKeyCredentialUserEntity.id
					arraylength;
					if_scmpeq L2;
				L1:	sconst_0;
					sreturn;
				L2:	aload_1;
					sload_2;
					getfield_a_this 45;		// reference com/josh/vku2f/PublicKeyCredentialUserEntity.id
					sconst_0;
					sload_3;
					invokestatic 134;		// javacard/framework/Util.arrayCompare([BS[BSS)B
					ifne L4;
				L3:	sconst_1;
					goto L5;
				L4:	sconst_0;
				L5:	sreturn;
		}

		.method public setName([BS)V 1 {
			.stack 5;
			.locals 0;

				L0:	aload_0;
					new 266;		// com/josh/vku2f/DomString
					dup;
					aload_1;
					sload_2;
					invokespecial 267;		// com/josh/vku2f/DomString.<init>([BS)V
					putfield_a 54;		// reference com/josh/vku2f/PublicKeyCredentialEntity.name
					getfield_a_this 58;		// reference com/josh/vku2f/PublicKeyCredentialUserEntity.dataPresent
					sconst_0;
					baload;
					ifne L2;
				L1:	getfield_a_this 58;		// reference com/josh/vku2f/PublicKeyCredentialUserEntity.dataPresent
					sconst_0;
					sconst_1;
					bastore;
					aload_0;
					dup;
					getfield_b 41;		// byte com/josh/vku2f/PublicKeyCredentialUserEntity.numData
					sconst_1;
					sadd;
					s2b;
					putfield_b 41;		// byte com/josh/vku2f/PublicKeyCredentialUserEntity.numData
				L2:	return;
		}

		.method public checkId(Lcom/josh/vku2f/PublicKeyCredentialUserEntity;)Z 6 {
			.stack 4;
			.locals 0;

				L0:	aload_1;
					getfield_a_this 45;		// reference com/josh/vku2f/PublicKeyCredentialUserEntity.id
					sconst_0;
					getfield_a_this 45;		// reference com/josh/vku2f/PublicKeyCredentialUserEntity.id
					arraylength;
					invokevirtual 256;		// checkId([BSS)Z
					sreturn;
		}

	}

	.class public ServerKeyCrypto 17 extends 0.0 {		// extends java/lang/Object

		.fields {
			private static 1.14 rng;		// Ljavacard/security/RandomData;
		}

		.publicMethodTable 1 {
			equals(Ljava/lang/Object;)Z;
		}

		.packageMethodTable 0 {
		}

		.method public <init>()V 0 {
			.stack 1;
			.locals 0;

				L0:	aload_0;
					invokespecial 69;		// java/lang/Object.<init>()V
					return;
		}

		.method public static getRng()Ljavacard/security/RandomData; 1 {
			.stack 1;
			.locals 0;

			.descriptor	Ljavacard/security/RandomData;	1.14;

				L0:	getstatic_a 276;		// reference com/josh/vku2f/ServerKeyCrypto.rng
					ifnonnull L2;
				L1:	sconst_2;
					invokestatic 277;		// javacard/security/RandomData.getInstance(B)Ljavacard/security/RandomData;
					putstatic_a 276;		// reference com/josh/vku2f/ServerKeyCrypto.rng
				L2:	getstatic_a 276;		// reference com/josh/vku2f/ServerKeyCrypto.rng
					areturn;
		}

	}

	.class public abstract StoredCredential 18 extends 0.0 {		// extends java/lang/Object

		.fields {
			protected boolean initialised 0;		// Z
			protected boolean hmacEnabled 1;		// Z
			protected byte[] credRandom 2;		// [B
			 byte[] id 3;		// [B
			 1.16 kp 4;		// Ljavacard/security/KeyPair;
			 PublicKeyCredentialUserEntity user 5;		// Lcom/josh/vku2f/PublicKeyCredentialUserEntity;
			 PublicKeyCredentialRpEntity rp 6;		// Lcom/josh/vku2f/PublicKeyCredentialRpEntity;
			private byte[] sigCounter 7;		// [B
			private static 1.14 rng;		// Ljavacard/security/RandomData;
		}

		.publicMethodTable 1 {
			equals(Ljava/lang/Object;)Z;
			doHmacSecret([BSS)S;
			initialiseCredSecret()Z;
			checkId([BSS)Z;
			getPresentUser()[Z;
			incrementCounter()V;
			readCounter([BS)S;
			doAttestationCommon([BS)V;
			performSignature([BSS[BS)S;
			getAttestedData([BS)S;
			getAttestedLen()S;
		}

		.packageMethodTable 0 {
		}

		.method protected <init>()V 0 {
			.stack 4;
			.locals 0;

				L0:	aload_0;
					invokespecial 69;		// java/lang/Object.<init>()V
					getstatic_a 278;		// reference com/josh/vku2f/StoredCredential.rng
					ifnonnull L2;
				L1:	invokestatic 279;		// com/josh/vku2f/ServerKeyCrypto.getRng()Ljavacard/security/RandomData;
					putstatic_a 278;		// reference com/josh/vku2f/StoredCredential.rng
				L2:	aload_0;
					bspush 16;
					newarray 11;
					putfield_a 38;		// reference com/josh/vku2f/StoredCredential.id
					getstatic_a 278;		// reference com/josh/vku2f/StoredCredential.rng
					getfield_a_this 38;		// reference com/josh/vku2f/StoredCredential.id
					sconst_0;
					bspush 16;
					invokevirtual 280;		// generateData([BSS)V
					aload_0;
					sconst_4;
					newarray 11;
					putfield_a 59;		// reference com/josh/vku2f/StoredCredential.sigCounter
					sconst_0;
					putfield_b_this 60;		// boolean com/josh/vku2f/StoredCredential.initialised
					sconst_0;
					putfield_b_this 61;		// boolean com/josh/vku2f/StoredCredential.hmacEnabled
					return;
		}

		.method public doHmacSecret([BSS)S 1 {
			.stack 1;
			.locals 0;

				L0:	sconst_0;
					sreturn;
		}

		.method public initialiseCredSecret()Z 2 {
			.stack 4;
			.locals 0;

				L0:	aload_0;
					bspush 32;
					newarray 11;
					putfield_a 62;		// reference com/josh/vku2f/StoredCredential.credRandom
					getstatic_a 278;		// reference com/josh/vku2f/StoredCredential.rng
					getfield_a_this 62;		// reference com/josh/vku2f/StoredCredential.credRandom
					sconst_0;
					bspush 32;
					invokevirtual 280;		// generateData([BSS)V
					sconst_1;
					putfield_b_this 61;		// boolean com/josh/vku2f/StoredCredential.hmacEnabled
					sconst_1;
					sreturn;
		}

		.method public checkId([BSS)Z 3 {
			.stack 5;
			.locals 0;

				L0:	sload_3;
					bspush 16;
					if_scmpeq L2;
				L1:	sconst_0;
					sreturn;
				L2:	getfield_a_this 38;		// reference com/josh/vku2f/StoredCredential.id
					sconst_0;
					aload_1;
					sload_2;
					sload_3;
					invokestatic 134;		// javacard/framework/Util.arrayCompare([BS[BSS)B
					ifne L4;
				L3:	sconst_1;
					goto L5;
				L4:	sconst_0;
				L5:	sreturn;
		}

		.method public getPresentUser()[Z 4 {
			.stack 1;
			.locals 0;

				L0:	getfield_a_this 40;		// reference com/josh/vku2f/StoredCredential.user
					getfield_a 58;		// reference com/josh/vku2f/PublicKeyCredentialUserEntity.dataPresent
					areturn;
		}

		.method protected incrementCounter()V 5 {
			.stack 4;
			.locals 1;

				L0:	invokestatic 218;		// javacard/framework/JCSystem.beginTransaction()V
					sconst_3;
					sstore_1;
				L1:	sload_1;
					sconst_1;
					if_scmple L5;
				L2:	getfield_a_this 59;		// reference com/josh/vku2f/StoredCredential.sigCounter
					sload_1;
					baload;
					sspush 255;
					if_scmpne L4;
				L3:	getfield_a_this 59;		// reference com/josh/vku2f/StoredCredential.sigCounter
					sload_1;
					sconst_1;
					ssub;
					dup2;
					baload;
					sconst_1;
					sadd;
					s2b;
					bastore;
					getfield_a_this 59;		// reference com/josh/vku2f/StoredCredential.sigCounter
					sload_1;
					sconst_0;
					bastore;
					invokestatic 219;		// javacard/framework/JCSystem.commitTransaction()V
					return;
				L4:	sinc 1 -1;
					goto L1;
				L5:	getfield_a_this 59;		// reference com/josh/vku2f/StoredCredential.sigCounter
					sconst_0;
					baload;
					sspush 255;
					if_scmpne L10;
				L6:	getfield_a_this 59;		// reference com/josh/vku2f/StoredCredential.sigCounter
					sconst_1;
					baload;
					sspush 255;
					if_scmpne L10;
				L7:	getfield_a_this 59;		// reference com/josh/vku2f/StoredCredential.sigCounter
					sconst_2;
					baload;
					sspush 255;
					if_scmpne L10;
				L8:	getfield_a_this 59;		// reference com/josh/vku2f/StoredCredential.sigCounter
					sconst_3;
					baload;
					sspush 255;
					if_scmpne L10;
				L9:	getfield_a_this 59;		// reference com/josh/vku2f/StoredCredential.sigCounter
					sconst_0;
					sconst_4;
					sconst_0;
					invokestatic 285;		// javacard/framework/Util.arrayFillNonAtomic([BSSB)S
					pop;
					invokestatic 219;		// javacard/framework/JCSystem.commitTransaction()V
					return;
				L10:	getfield_a_this 59;		// reference com/josh/vku2f/StoredCredential.sigCounter
					sconst_3;
					dup2;
					baload;
					sconst_1;
					sadd;
					s2b;
					bastore;
					invokestatic 219;		// javacard/framework/JCSystem.commitTransaction()V
					return;
		}

		.method public readCounter([BS)S 6 {
			.stack 5;
			.locals 0;

				L0:	getfield_a_this 59;		// reference com/josh/vku2f/StoredCredential.sigCounter
					sconst_0;
					aload_1;
					sload_2;
					sconst_4;
					invokestatic 104;		// javacard/framework/Util.arrayCopy([BS[BSS)S
					pop;
					sconst_4;
					sreturn;
		}

		.method protected doAttestationCommon([BS)V 7 {
			.stack 5;
			.locals 0;

				L0:	getstatic_a 215;		// reference com/josh/vku2f/CTAP2.aaguid
					sconst_0;
					aload_1;
					sload_2;
					bspush 16;
					invokestatic 104;		// javacard/framework/Util.arrayCopy([BS[BSS)S
					pop;
					aload_1;
					sload_2;
					bspush 16;
					sadd;
					sconst_0;
					bastore;
					aload_1;
					sload_2;
					bspush 17;
					sadd;
					bspush 16;
					bastore;
					getfield_a_this 38;		// reference com/josh/vku2f/StoredCredential.id
					sconst_0;
					aload_1;
					sload_2;
					bspush 18;
					sadd;
					bspush 16;
					invokestatic 104;		// javacard/framework/Util.arrayCopy([BS[BSS)S
					pop;
					return;
		}

		.method public abstract performSignature([BSS[BS)S 8 {
		}

		.method public abstract getAttestedData([BS)S 9 {
		}

		.method public abstract getAttestedLen()S 10 {
		}

	}

	.class public StoredES256Credential 19 extends StoredCredential {

		.fields {
			 1.15 sig 0;		// Ljavacard/security/Signature;
		}

		.publicMethodTable 8 {
			equals(Ljava/lang/Object;)Z;
			doHmacSecret([BSS)S;
			initialiseCredSecret()Z;
			checkId([BSS)Z;
			getPresentUser()[Z;
			incrementCounter()V;
			readCounter([BS)S;
			doAttestationCommon([BS)V;
			performSignature([BSS[BS)S;
			getAttestedData([BS)S;
			getAttestedLen()S;
		}

		.packageMethodTable 0 {
		}

		.method public <init>(Lcom/josh/vku2f/AuthenticatorMakeCredential;)V 0 {
			.stack 5;
			.locals 0;

				L0:	aload_0;
					invokespecial 286;		// com/josh/vku2f/StoredCredential.<init>()V
					aload_0;
					new 221;		// javacard/security/KeyPair
					dup;
					sconst_5;
					sspush 256;
					invokespecial 68;		// javacard/security/KeyPair.<init>(BS)V
					putfield_a 63;		// reference com/josh/vku2f/StoredCredential.kp
					getfield_a_this 63;		// reference com/josh/vku2f/StoredCredential.kp
					invokevirtual 112;		// getPublic()Ljavacard/security/PublicKey;
					checkcast 0 122;		// T_CLASSORINTERFACE javacard/security/ECKey
					invokestatic 125;		// com/josh/vku2f/KeyParams.sec256r1params(Ljavacard/security/ECKey;)V
					getfield_a_this 63;		// reference com/josh/vku2f/StoredCredential.kp
					invokevirtual 127;		// genKeyPair()V
					aload_0;
					aload_1;
					invokevirtual 288;		// getUser()Lcom/josh/vku2f/PublicKeyCredentialUserEntity;
					putfield_a 40;		// reference com/josh/vku2f/StoredCredential.user
					aload_0;
					aload_1;
					invokevirtual 289;		// getRp()Lcom/josh/vku2f/PublicKeyCredentialRpEntity;
					putfield_a 34;		// reference com/josh/vku2f/StoredCredential.rp
					aload_0;
					bspush 33;
					sconst_0;
					invokestatic 213;		// javacard/security/Signature.getInstance(BZ)Ljavacard/security/Signature;
					putfield_a 64;		// reference com/josh/vku2f/StoredES256Credential.sig
					getfield_a_this 64;		// reference com/josh/vku2f/StoredES256Credential.sig
					getfield_a_this 63;		// reference com/josh/vku2f/StoredCredential.kp
					invokevirtual 225;		// getPrivate()Ljavacard/security/PrivateKey;
					sconst_1;
					invokevirtual 251;		// init(Ljavacard/security/Key;B)V
					return;
		}

		.method public performSignature([BSS[BS)S 8 {
			.stack 6;
			.locals 0;

				L0:	aload_0;
					invokevirtual 291;		// incrementCounter()V
					getfield_a_this 64;		// reference com/josh/vku2f/StoredES256Credential.sig
					aload_1;
					sload_2;
					sload_3;
					aload 4;
					sload 5;
					invokevirtual 274;		// sign([BSS[BS)S
					sreturn;
		}

		.method public getAttestedLen()S 10 {
			.stack 1;
			.locals 0;

				L0:	bspush 111;
					sreturn;
		}

		.method public getAttestedData([BS)S 9 {
			.stack 4;
			.locals 3;

				L0:	new 110;		// com/josh/vku2f/CBOREncoder
					dup;
					invokespecial 111;		// com/josh/vku2f/CBOREncoder.<init>()V
					astore_3;
				L1:	bspush 65;
					sconst_1;
					invokestatic 117;		// javacard/framework/JCSystem.makeTransientByteArray(SB)[B
					astore 4;
				L2:	goto L4;
				L3:	astore 5;
					bspush 65;
					newarray 11;
					astore 4;
				L4:	getfield_a_this 63;		// reference com/josh/vku2f/StoredCredential.kp
					invokevirtual 112;		// getPublic()Ljavacard/security/PublicKey;
					checkcast 0 105;		// T_CLASSORINTERFACE javacard/security/ECPublicKey
					aload 4;
					sconst_0;
					invokeinterface 3 105 19;		// javacard/security/ECPublicKey
					pop;
					aload_0;
					aload_1;
					sload_2;
					invokevirtual 292;		// doAttestationCommon([BS)V
					aload_3;
					aload_1;
					sload_2;
					bspush 34;
					sadd;
					sspush 1000;
					invokevirtual 175;		// init([BSS)V
					aload_3;
					sconst_5;
					invokevirtual 176;		// startMap(S)S
					pop;
					aload_3;
					sconst_1;
					invokevirtual 91;		// writeRawByte(B)S
					pop;
					aload_3;
					sconst_2;
					invokevirtual 202;		// encodeUInt8(B)S
					pop;
					aload_3;
					sconst_3;
					invokevirtual 91;		// writeRawByte(B)S
					pop;
					aload_3;
					bspush 6;
					invokevirtual 186;		// encodeNegativeUInt8(B)S
					pop;
					aload_3;
					sconst_0;
					invokevirtual 186;		// encodeNegativeUInt8(B)S
					pop;
					aload_3;
					sconst_1;
					invokevirtual 202;		// encodeUInt8(B)S
					pop;
					aload_3;
					sconst_1;
					invokevirtual 186;		// encodeNegativeUInt8(B)S
					pop;
					aload_3;
					aload 4;
					sconst_1;
					bspush 32;
					invokevirtual 189;		// encodeByteString([BSS)S
					pop;
					aload_3;
					sconst_2;
					invokevirtual 186;		// encodeNegativeUInt8(B)S
					pop;
					aload_3;
					aload 4;
					bspush 33;
					bspush 32;
					invokevirtual 189;		// encodeByteString([BSS)S
					pop;
					aconst_null;
					astore 4;
					invokestatic 210;		// javacard/framework/JCSystem.requestObjectDeletion()V
					bspush 111;
					sreturn;
			.exceptionTable {
				// start_block end_block handler_block catch_type_index
				L1 L2 L3 106;
			}
		}

	}

	.class public StoredPS256Credential 20 extends StoredCredential {

		.fields {
			 1.15 kpSignature 0;		// Ljavacard/security/Signature;
		}

		.publicMethodTable 8 {
			equals(Ljava/lang/Object;)Z;
			doHmacSecret([BSS)S;
			initialiseCredSecret()Z;
			checkId([BSS)Z;
			getPresentUser()[Z;
			incrementCounter()V;
			readCounter([BS)S;
			doAttestationCommon([BS)V;
			performSignature([BSS[BS)S;
			getAttestedData([BS)S;
			getAttestedLen()S;
		}

		.packageMethodTable 0 {
		}

		.method public <init>(Lcom/josh/vku2f/AuthenticatorMakeCredential;)V 0 {
			.stack 5;
			.locals 0;

				L0:	aload_0;
					invokespecial 286;		// com/josh/vku2f/StoredCredential.<init>()V
					aload_0;
					new 221;		// javacard/security/KeyPair
					dup;
					sconst_2;
					sspush 2048;
					invokespecial 68;		// javacard/security/KeyPair.<init>(BS)V
					putfield_a 63;		// reference com/josh/vku2f/StoredCredential.kp
					getfield_a_this 63;		// reference com/josh/vku2f/StoredCredential.kp
					invokevirtual 127;		// genKeyPair()V
					aload_0;
					aload_1;
					invokevirtual 288;		// getUser()Lcom/josh/vku2f/PublicKeyCredentialUserEntity;
					putfield_a 40;		// reference com/josh/vku2f/StoredCredential.user
					aload_0;
					aload_1;
					invokevirtual 289;		// getRp()Lcom/josh/vku2f/PublicKeyCredentialRpEntity;
					putfield_a 34;		// reference com/josh/vku2f/StoredCredential.rp
					aload_0;
					bspush 44;
					sconst_0;
					invokestatic 213;		// javacard/security/Signature.getInstance(BZ)Ljavacard/security/Signature;
					putfield_a 65;		// reference com/josh/vku2f/StoredPS256Credential.kpSignature
					getfield_a_this 65;		// reference com/josh/vku2f/StoredPS256Credential.kpSignature
					getfield_a_this 63;		// reference com/josh/vku2f/StoredCredential.kp
					invokevirtual 225;		// getPrivate()Ljavacard/security/PrivateKey;
					sconst_1;
					invokevirtual 251;		// init(Ljavacard/security/Key;B)V
					return;
		}

		.method public performSignature([BSS[BS)S 8 {
			.stack 6;
			.locals 0;

				L0:	aload_0;
					invokevirtual 294;		// incrementCounter()V
					getfield_a_this 65;		// reference com/josh/vku2f/StoredPS256Credential.kpSignature
					aload_1;
					sload_2;
					sload_3;
					aload 4;
					sload 5;
					invokevirtual 274;		// sign([BSS[BS)S
					sreturn;
		}

		.method public getAttestedLen()S 10 {
			.stack 1;
			.locals 0;

				L0:	sspush 305;
					sreturn;
		}

		.method public getAttestedData([BS)S 9 {
			.stack 4;
			.locals 2;

				L0:	new 110;		// com/josh/vku2f/CBOREncoder
					dup;
					invokespecial 111;		// com/josh/vku2f/CBOREncoder.<init>()V
					astore_3;
					aload_0;
					aload_1;
					sload_2;
					invokevirtual 295;		// doAttestationCommon([BS)V
					aload_3;
					aload_1;
					sload_2;
					bspush 34;
					sadd;
					sspush 1000;
					invokevirtual 175;		// init([BSS)V
					aload_3;
					sconst_4;
					invokevirtual 176;		// startMap(S)S
					pop;
					aload_3;
					sconst_1;
					invokevirtual 91;		// writeRawByte(B)S
					pop;
					aload_3;
					sconst_3;
					invokevirtual 202;		// encodeUInt8(B)S
					pop;
					aload_3;
					sconst_3;
					invokevirtual 91;		// writeRawByte(B)S
					pop;
					aload_3;
					bspush 36;
					invokevirtual 186;		// encodeNegativeUInt8(B)S
					pop;
					aload_3;
					sconst_0;
					invokevirtual 186;		// encodeNegativeUInt8(B)S
					pop;
					aload_3;
					sspush 256;
					invokevirtual 180;		// startByteString(S)S
					sstore 4;
					getfield_a_this 63;		// reference com/josh/vku2f/StoredCredential.kp
					invokevirtual 112;		// getPublic()Ljavacard/security/PublicKey;
					checkcast 0 296;		// T_CLASSORINTERFACE javacard/security/RSAPublicKey
					aload_1;
					sload 4;
					invokeinterface 3 296 5;		// javacard/security/RSAPublicKey
					pop;
					aload_3;
					sconst_1;
					invokevirtual 186;		// encodeNegativeUInt8(B)S
					pop;
					aload_3;
					sconst_3;
					invokevirtual 180;		// startByteString(S)S
					sstore 4;
					getfield_a_this 63;		// reference com/josh/vku2f/StoredCredential.kp
					invokevirtual 112;		// getPublic()Ljavacard/security/PublicKey;
					checkcast 0 296;		// T_CLASSORINTERFACE javacard/security/RSAPublicKey
					aload_1;
					sload 4;
					invokeinterface 3 296 4;		// javacard/security/RSAPublicKey
					pop;
					sspush 305;
					sreturn;
		}

	}

	.class public StoredRS256Credential 21 extends StoredCredential {

		.fields {
			 4.1 kpSignature 0;		// Ljavacardx/crypto/Cipher;
		}

		.publicMethodTable 8 {
			equals(Ljava/lang/Object;)Z;
			doHmacSecret([BSS)S;
			initialiseCredSecret()Z;
			checkId([BSS)Z;
			getPresentUser()[Z;
			incrementCounter()V;
			readCounter([BS)S;
			doAttestationCommon([BS)V;
			performSignature([BSS[BS)S;
			getAttestedData([BS)S;
			getAttestedLen()S;
		}

		.packageMethodTable 0 {
		}

		.method public <init>(Lcom/josh/vku2f/AuthenticatorMakeCredential;)V 0 {
			.stack 5;
			.locals 0;

				L0:	aload_0;
					invokespecial 286;		// com/josh/vku2f/StoredCredential.<init>()V
					aload_0;
					new 221;		// javacard/security/KeyPair
					dup;
					sconst_2;
					sspush 2048;
					invokespecial 68;		// javacard/security/KeyPair.<init>(BS)V
					putfield_a 63;		// reference com/josh/vku2f/StoredCredential.kp
					getfield_a_this 63;		// reference com/josh/vku2f/StoredCredential.kp
					invokevirtual 127;		// genKeyPair()V
					aload_0;
					aload_1;
					invokevirtual 288;		// getUser()Lcom/josh/vku2f/PublicKeyCredentialUserEntity;
					putfield_a 40;		// reference com/josh/vku2f/StoredCredential.user
					aload_0;
					aload_1;
					invokevirtual 289;		// getRp()Lcom/josh/vku2f/PublicKeyCredentialRpEntity;
					putfield_a 34;		// reference com/josh/vku2f/StoredCredential.rp
					aload_0;
					bspush 10;
					sconst_0;
					invokestatic 297;		// javacardx/crypto/Cipher.getInstance(BZ)Ljavacardx/crypto/Cipher;
					putfield_a 66;		// reference com/josh/vku2f/StoredRS256Credential.kpSignature
					getfield_a_this 66;		// reference com/josh/vku2f/StoredRS256Credential.kpSignature
					getfield_a_this 63;		// reference com/josh/vku2f/StoredCredential.kp
					invokevirtual 225;		// getPrivate()Ljavacard/security/PrivateKey;
					sconst_2;
					invokevirtual 299;		// init(Ljavacard/security/Key;B)V
					return;
		}

		.method public performSignature([BSS[BS)S 8 {
			.stack 6;
			.locals 0;

				L0:	aload_0;
					invokevirtual 300;		// incrementCounter()V
					getfield_a_this 66;		// reference com/josh/vku2f/StoredRS256Credential.kpSignature
					aload_1;
					sload_2;
					sload_3;
					aload 4;
					sload 5;
					invokevirtual 301;		// doFinal([BSS[BS)S
					sreturn;
		}

		.method public getAttestedLen()S 10 {
			.stack 1;
			.locals 0;

				L0:	sspush 307;
					sreturn;
		}

		.method public getAttestedData([BS)S 9 {
			.stack 4;
			.locals 2;

				L0:	new 110;		// com/josh/vku2f/CBOREncoder
					dup;
					invokespecial 111;		// com/josh/vku2f/CBOREncoder.<init>()V
					astore_3;
					aload_0;
					aload_1;
					sload_2;
					invokevirtual 302;		// doAttestationCommon([BS)V
					aload_3;
					aload_1;
					sload_2;
					bspush 34;
					sadd;
					sspush 1000;
					invokevirtual 175;		// init([BSS)V
					aload_3;
					sconst_4;
					invokevirtual 176;		// startMap(S)S
					pop;
					aload_3;
					sconst_1;
					invokevirtual 91;		// writeRawByte(B)S
					pop;
					aload_3;
					sconst_3;
					invokevirtual 202;		// encodeUInt8(B)S
					pop;
					aload_3;
					sconst_3;
					invokevirtual 91;		// writeRawByte(B)S
					pop;
					aload_3;
					sspush 256;
					invokevirtual 303;		// encodeNegativeUInt16(S)S
					pop;
					aload_3;
					sconst_0;
					invokevirtual 186;		// encodeNegativeUInt8(B)S
					pop;
					aload_3;
					sspush 256;
					invokevirtual 180;		// startByteString(S)S
					sstore 4;
					getfield_a_this 63;		// reference com/josh/vku2f/StoredCredential.kp
					invokevirtual 112;		// getPublic()Ljavacard/security/PublicKey;
					checkcast 0 296;		// T_CLASSORINTERFACE javacard/security/RSAPublicKey
					aload_1;
					sload 4;
					invokeinterface 3 296 5;		// javacard/security/RSAPublicKey
					pop;
					aload_3;
					sconst_1;
					invokevirtual 186;		// encodeNegativeUInt8(B)S
					pop;
					aload_3;
					sconst_3;
					invokevirtual 180;		// startByteString(S)S
					sstore 4;
					getfield_a_this 63;		// reference com/josh/vku2f/StoredCredential.kp
					invokevirtual 112;		// getPublic()Ljavacard/security/PublicKey;
					checkcast 0 296;		// T_CLASSORINTERFACE javacard/security/RSAPublicKey
					aload_1;
					sload 4;
					invokeinterface 3 296 4;		// javacard/security/RSAPublicKey
					pop;
					sspush 306;
					sreturn;
		}

	}

	.class public Utf8Strings 22 extends 0.0 {		// extends java/lang/Object

		.fields {
			public static final byte[] UTF8_UP 0 = {117,112};		// [B
			public static final byte[] UTF8_ID 1 = {105,100};		// [B
			public static final byte[] UTF8_NAME 2 = {110,97,109,101};		// [B
			public static final byte[] UTF8_DISPLAYNAME 3 = {100,105,115,112,108,97,121,78,97,109,101};		// [B
			public static final byte[] UTF8_ALG 4 = {97,108,103};		// [B
			public static final byte[] UTF8_UV 5 = {117,118};		// [B
			public static final byte[] UTF8_RK 6 = {114,107};		// [B
			public static final byte[] UTF8_TYPE 7 = {116,121,112,101};		// [B
			public static final byte[] UTF8_PACKED 8 = {112,97,99,107,101,100};		// [B
			public static final byte[] UTF8_SIG 9 = {115,105,103};		// [B
			public static final byte[] UTF8_X5C 10 = {120,53,99};		// [B
			public static final byte[] UTF8_PUBLIC_KEY 11 = {112,117,98,108,105,99,45,107,101,121};		// [B
			public static final byte[] UTF8_FIDO2 12 = {70,73,68,79,95,50,95,48};		// [B
			public static final byte[] UTF8_ICON 13 = {105,99,111,110};		// [B
		}

		.publicMethodTable 1 {
			equals(Ljava/lang/Object;)Z;
		}

		.packageMethodTable 0 {
		}

		.method public <init>()V 0 {
			.stack 1;
			.locals 0;

				L0:	aload_0;
					invokespecial 69;		// java/lang/Object.<init>()V
					return;
		}

	}

}
